[{"condition": "Near Mint", "variant": "Normal", "language": "English", "quantity": 1, "title": "Balduvian Atrocity", "listingType": "ListingWithoutPhotos", "customListingId": "", "purchasePrice": 0.01, "shippingPrice": 0.0, "orderDate": "2023-04-26T10:25:43.123+00:00"}, {"condition": "Near Mint", "variant": "Normal", "language": "English", "quantity": 1, "title": "Balduvian Atrocity", "listingType": "ListingWithoutPhotos", "customListingId": "", "purchasePrice": 0.01, "shippingPrice": 0.0, "orderDate": "2023-04-26T07:15:36.766+00:00"}, {"condition": "Near Mint", "variant": "Normal", "language": "English", "quantity": 1, "title": "Balduvian Atrocity", "listingType": "ListingWithoutPhotos", "customListingId": "", "purchasePrice": 0.03, "shippingPrice": 0.89, "orderDate": "2023-04-25T20:27:12.363+00:00"}, {"condition": "Near Mint", "variant": "Normal", "language": "English", "quantity": 2, "title": "Balduvian Atrocity", "listingType": "ListingWithoutPhotos", "customListingId": "", "purchasePrice": 0.01, "shippingPrice": 0.0, "orderDate": "2023-04-25T20:01:24.4+00:00"}, {"condition": "Near Mint", "variant": "Normal", "language": "English", "quantity": 2, "title": "Balduvian Atrocity", "listingType": "ListingWithoutPhotos", "customListingId": "", "purchasePrice": 0.01, "shippingPrice": 0.0, "orderDate": "2023-04-25T20:01:24.376+00:00"}, {"condition": "Near Mint", "variant": "Normal", "language": "English", "quantity": 1, "title": "Balduvian Atrocity", "listingType": "ListingWithoutPhotos", "customListingId": "", "purchasePrice": 0.01, "shippingPrice": 0.0, "orderDate": "2023-04-23T12:05:29.943+00:00"}, {"condition": "Lightly Played", "variant": "Normal", "language": "English", "quantity": 1, "title": "Balduvian Atrocity", "listingType": "ListingWithoutPhotos", "customListingId": "", "purchasePrice": 0.03, "shippingPrice": 1.25, "orderDate": "2023-04-22T08:06:09.41+00:00"}, {"condition": "Near Mint", "variant": "Normal", "language": "English", "quantity": 4, "title": "Balduvian Atrocity", "listingType": "ListingWithoutPhotos", "customListingId": "", "purchasePrice": 0.2, "shippingPrice": 0.0, "orderDate": "2023-04-17T06:30:18.99+00:00"}, {"condition": "Near Mint", "variant": "Normal", "language": "English", "quantity": 1, "title": "Balduvian Atrocity", "listingType": "ListingWithoutPhotos", "customListingId": "", "purchasePrice": 0.01, "shippingPrice": 0.0, "orderDate": "2023-04-13T17:57:02.166+00:00"}, {"condition": "Near Mint", "variant": "Normal", "language": "English", "quantity": 1, "title": "Balduvian Atrocity", "listingType": "ListingWithoutPhotos", "customListingId": "", "purchasePrice": 0.02, "shippingPrice": 0.99, "orderDate": "2023-04-13T15:43:25.416+00:00"}, {"condition": "Near Mint", "variant": "Normal", "language": "English", "quantity": 1, "title": "Balduvian Atrocity", "listingType": "ListingWithoutPhotos", "customListingId": "", "purchasePrice": 0.01, "shippingPrice": 0.0, "orderDate": "2023-04-10T00:54:39.486+00:00"}, {"condition": "Near Mint", "variant": "Normal", "language": "English", "quantity": 1, "title": "Balduvian Atrocity", "listingType": "ListingWithoutPhotos", "customListingId": "", "purchasePrice": 0.02, "shippingPrice": 0.0, "orderDate": "2023-04-09T19:35:10.876+00:00"}, {"condition": "Near Mint", "variant": "Normal", "language": "English", "quantity": 1, "title": "Balduvian Atrocity", "listingType": "ListingWithoutPhotos", "customListingId": "", "purchasePrice": 0.01, "shippingPrice": 0.0, "orderDate": "2023-04-08T04:43:45.023+00:00"}, {"condition": "Near Mint", "variant": "Normal", "language": "English", "quantity": 1, "title": "Balduvian Atrocity", "listingType": "ListingWithoutPhotos", "customListingId": "", "purchasePrice": 0.01, "shippingPrice": 0.0, "orderDate": "2023-04-04T21:30:50.89+00:00"}, {"condition": "Near Mint", "variant": "Normal", "language": "English", "quantity": 1, "title": "Balduvian Atrocity", "listingType": "ListingWithoutPhotos", "customListingId": "", "purchasePrice": 0.01, "shippingPrice": 0.0, "orderDate": "2023-04-02T01:55:14.226+00:00"}, {"condition": "Near Mint", "variant": "Foil", "language": "English", "quantity": 1, "title": "Balduvian Atrocity", "listingType": "ListingWithoutPhotos", "customListingId": "", "purchasePrice": 0.05, "shippingPrice": 0.0, "orderDate": "2023-03-31T05:42:34.566+00:00"}, {"condition": "Near Mint", "variant": "Normal", "language": "English", "quantity": 1, "title": "Balduvian Atrocity", "listingType": "ListingWithoutPhotos", "customListingId": "", "purchasePrice": 0.01, "shippingPrice": 0.0, "orderDate": "2023-03-31T04:27:54.876+00:00"}, {"condition": "Near Mint", "variant": "Foil", "language": "English", "quantity": 1, "title": "Balduvian Atrocity", "listingType": "ListingWithoutPhotos", "customListingId": "", "purchasePrice": 0.01, "shippingPrice": 2.0, "orderDate": "2023-03-29T04:44:13.16+00:00"}, {"condition": "Near Mint", "variant": "Normal", "language": "English", "quantity": 1, "title": "Balduvian Atrocity", "listingType": "ListingWithoutPhotos", "customListingId": "", "purchasePrice": 0.01, "shippingPrice": 0.99, "orderDate": "2023-03-28T14:31:41.796+00:00"}, {"condition": "Near Mint", "variant": "Normal", "language": "English", "quantity": 1, "title": "Balduvian Atrocity", "listingType": "ListingWithoutPhotos", "customListingId": "", "purchasePrice": 0.01, "shippingPrice": 0.0, "orderDate": "2023-03-27T22:10:23.73+00:00"}, {"condition": "Near Mint", "variant": "Normal", "language": "English", "quantity": 4, "title": "Balduvian Atrocity", "listingType": "ListingWithoutPhotos", "customListingId": "", "purchasePrice": 0.02, "shippingPrice": 0.0, "orderDate": "2023-03-26T05:51:15.243+00:00"}, {"condition": "Near Mint", "variant": "Normal", "language": "English", "quantity": 5, "title": "Balduvian Atrocity", "listingType": "ListingWithoutPhotos", "customListingId": "", "purchasePrice": 0.02, "shippingPrice": 0.0, "orderDate": "2023-03-26T05:51:15.24+00:00"}, {"condition": "Near Mint", "variant": "Normal", "language": "English", "quantity": 1, "title": "Balduvian Atrocity", "listingType": "ListingWithoutPhotos", "customListingId": "", "purchasePrice": 0.02, "shippingPrice": 0.0, "orderDate": "2023-03-24T19:05:19.963+00:00"}, {"condition": "Near Mint", "variant": "Normal", "language": "English", "quantity": 2, "title": "Balduvian Atrocity", "listingType": "ListingWithoutPhotos", "customListingId": "", "purchasePrice": 0.02, "shippingPrice": 0.0, "orderDate": "2023-03-22T19:54:33.22+00:00"}, {"condition": "Near Mint", "variant": "Normal", "language": "English", "quantity": 1, "title": "Balduvian Atrocity", "listingType": "ListingWithoutPhotos", "customListingId": "", "purchasePrice": 0.05, "shippingPrice": 0.0, "orderDate": "2023-03-21T02:09:50.61+00:00"}, {"condition": "Near Mint", "variant": "Normal", "language": "English", "quantity": 1, "title": "Balduvian Atrocity", "listingType": "ListingWithoutPhotos", "customListingId": "", "purchasePrice": 0.02, "shippingPrice": 0.0, "orderDate": "2023-03-20T07:49:39.073+00:00"}, {"condition": "Near Mint", "variant": "Normal", "language": "English", "quantity": 1, "title": "Balduvian Atrocity", "listingType": "ListingWithoutPhotos", "customListingId": "", "purchasePrice": 0.02, "shippingPrice": 0.0, "orderDate": "2023-03-17T20:28:36.94+00:00"}, {"condition": "Near Mint", "variant": "Normal", "language": "English", "quantity": 1, "title": "Balduvian Atrocity", "listingType": "ListingWithoutPhotos", "customListingId": "", "purchasePrice": 0.01, "shippingPrice": 0.99, "orderDate": "2023-03-17T20:02:13.546+00:00"}, {"condition": "Near Mint", "variant": "Normal", "language": "English", "quantity": 1, "title": "Balduvian Atrocity", "listingType": "ListingWithoutPhotos", "customListingId": "", "purchasePrice": 0.02, "shippingPrice": 0.0, "orderDate": "2023-03-17T03:56:08.723+00:00"}, {"condition": "Near Mint", "variant": "Normal", "language": "English", "quantity": 1, "title": "Balduvian Atrocity", "listingType": "ListingWithoutPhotos", "customListingId": "", "purchasePrice": 0.02, "shippingPrice": 0.0, "orderDate": "2023-03-15T13:13:03.876+00:00"}, {"condition": "Near Mint", "variant": "Normal", "language": "English", "quantity": 1, "title": "Balduvian Atrocity", "listingType": "ListingWithoutPhotos", "customListingId": "", "purchasePrice": 0.02, "shippingPrice": 0.0, "orderDate": "2023-03-13T19:49:50.046+00:00"}, {"condition": "Near Mint", "variant": "Normal", "language": "English", "quantity": 1, "title": "Balduvian Atrocity", "listingType": "ListingWithoutPhotos", "customListingId": "", "purchasePrice": 0.02, "shippingPrice": 0.0, "orderDate": "2023-03-13T18:38:18.856+00:00"}, {"condition": "Near Mint", "variant": "Normal", "language": "English", "quantity": 1, "title": "Balduvian Atrocity", "listingType": "ListingWithoutPhotos", "customListingId": "", "purchasePrice": 0.03, "shippingPrice": 0.5, "orderDate": "2023-03-13T05:46:27.863+00:00"}, {"condition": "Near Mint", "variant": "Normal", "language": "English", "quantity": 1, "title": "Balduvian Atrocity", "listingType": "ListingWithoutPhotos", "customListingId": "", "purchasePrice": 0.03, "shippingPrice": 0.99, "orderDate": "2023-03-12T03:48:50.643+00:00"}, {"condition": "Near Mint", "variant": "Foil", "language": "English", "quantity": 1, "title": "Balduvian Atrocity", "listingType": "ListingWithoutPhotos", "customListingId": "", "purchasePrice": 0.25, "shippingPrice": 0.0, "orderDate": "2023-03-11T11:47:51.28+00:00"}, {"condition": "Near Mint", "variant": "Normal", "language": "English", "quantity": 1, "title": "Balduvian Atrocity", "listingType": "ListingWithoutPhotos", "customListingId": "", "purchasePrice": 0.02, "shippingPrice": 0.0, "orderDate": "2023-03-10T02:52:48.373+00:00"}, {"condition": "Near Mint", "variant": "Normal", "language": "English", "quantity": 1, "title": "Balduvian Atrocity", "listingType": "ListingWithoutPhotos", "customListingId": "", "purchasePrice": 0.02, "shippingPrice": 0.0, "orderDate": "2023-03-07T15:25:16.89+00:00"}, {"condition": "Near Mint", "variant": "Normal", "language": "English", "quantity": 1, "title": "Balduvian Atrocity", "listingType": "ListingWithoutPhotos", "customListingId": "", "purchasePrice": 0.01, "shippingPrice": 0.99, "orderDate": "2023-03-04T20:23:43.396+00:00"}, {"condition": "Near Mint", "variant": "Normal", "language": "English", "quantity": 3, "title": "Balduvian Atrocity", "listingType": "ListingWithoutPhotos", "customListingId": "", "purchasePrice": 0.02, "shippingPrice": 0.0, "orderDate": "2023-03-01T22:29:43.786+00:00"}, {"condition": "Near Mint", "variant": "Normal", "language": "English", "quantity": 2, "title": "Balduvian Atrocity", "listingType": "ListingWithoutPhotos", "customListingId": "", "purchasePrice": 0.02, "shippingPrice": 0.0, "orderDate": "2023-02-26T07:01:24.12+00:00"}, {"condition": "Lightly Played", "variant": "Foil", "language": "English", "quantity": 1, "title": "Balduvian Atrocity", "listingType": "ListingWithoutPhotos", "customListingId": "", "purchasePrice": 0.13, "shippingPrice": 1.2, "orderDate": "2023-02-26T03:09:39.613+00:00"}, {"condition": "Near Mint", "variant": "Normal", "language": "English", "quantity": 1, "title": "Balduvian Atrocity", "listingType": "ListingWithoutPhotos", "customListingId": "", "purchasePrice": 0.01, "shippingPrice": 0.99, "orderDate": "2023-02-26T01:55:07.21+00:00"}, {"condition": "Near Mint", "variant": "Normal", "language": "English", "quantity": 1, "title": "Balduvian Atrocity", "listingType": "ListingWithoutPhotos", "customListingId": "", "purchasePrice": 0.02, "shippingPrice": 0.0, "orderDate": "2023-02-25T18:27:45.56+00:00"}, {"condition": "Near Mint", "variant": "Normal", "language": "English", "quantity": 3, "title": "Balduvian Atrocity", "listingType": "ListingWithoutPhotos", "customListingId": "", "purchasePrice": 0.01, "shippingPrice": 0.0, "orderDate": "2023-02-25T18:27:45.486+00:00"}, {"condition": "Near Mint", "variant": "Normal", "language": "English", "quantity": 2, "title": "Balduvian Atrocity", "listingType": "ListingWithoutPhotos", "customListingId": "", "purchasePrice": 0.15, "shippingPrice": 0.0, "orderDate": "2023-02-25T15:41:34.256+00:00"}, {"condition": "Near Mint", "variant": "Normal", "language": "English", "quantity": 1, "title": "Balduvian Atrocity", "listingType": "ListingWithoutPhotos", "customListingId": "", "purchasePrice": 0.01, "shippingPrice": 0.0, "orderDate": "2023-02-25T03:16:59.266+00:00"}, {"condition": "Near Mint", "variant": "Normal", "language": "English", "quantity": 1, "title": "Balduvian Atrocity", "listingType": "ListingWithoutPhotos", "customListingId": "", "purchasePrice": 0.01, "shippingPrice": 0.0, "orderDate": "2023-02-24T01:13:18.516+00:00"}, {"condition": "Near Mint", "variant": "Foil", "language": "English", "quantity": 1, "title": "Balduvian Atrocity", "listingType": "ListingWithoutPhotos", "customListingId": "", "purchasePrice": 0.08, "shippingPrice": 0.0, "orderDate": "2023-02-23T06:26:47.626+00:00"}, {"condition": "Near Mint", "variant": "Normal", "language": "English", "quantity": 1, "title": "Balduvian Atrocity", "listingType": "ListingWithoutPhotos", "customListingId": "", "purchasePrice": 0.01, "shippingPrice": 1.99, "orderDate": "2023-02-23T02:37:08.926+00:00"}, {"condition": "Near Mint", "variant": "Normal", "language": "English", "quantity": 1, "title": "Balduvian Atrocity", "listingType": "ListingWithoutPhotos", "customListingId": "", "purchasePrice": 0.01, "shippingPrice": 0.99, "orderDate": "2023-02-22T16:55:34.68+00:00"}, {"condition": "Lightly Played", "variant": "Normal", "language": "English", "quantity": 1, "title": "Balduvian Atrocity", "listingType": "ListingWithoutPhotos", "customListingId": "", "purchasePrice": 0.01, "shippingPrice": 1.25, "orderDate": "2023-02-21T21:01:20.82+00:00"}, {"condition": "Near Mint", "variant": "Normal", "language": "English", "quantity": 1, "title": "Balduvian Atrocity", "listingType": "ListingWithoutPhotos", "customListingId": "", "purchasePrice": 0.01, "shippingPrice": 0.0, "orderDate": "2023-02-21T05:43:48.443+00:00"}, {"condition": "Near Mint", "variant": "Normal", "language": "English", "quantity": 3, "title": "Balduvian Atrocity", "listingType": "ListingWithoutPhotos", "customListingId": "", "purchasePrice": 0.01, "shippingPrice": 1.05, "orderDate": "2023-02-20T02:23:56.52+00:00"}, {"condition": "Near Mint", "variant": "Normal", "language": "English", "quantity": 1, "title": "Balduvian Atrocity", "listingType": "ListingWithoutPhotos", "customListingId": "", "purchasePrice": 0.02, "shippingPrice": 0.99, "orderDate": "2023-02-20T02:23:56.193+00:00"}, {"condition": "Near Mint", "variant": "Normal", "language": "English", "quantity": 3, "title": "Balduvian Atrocity", "listingType": "ListingWithoutPhotos", "customListingId": "", "purchasePrice": 0.01, "shippingPrice": 0.0, "orderDate": "2023-02-18T21:15:58.113+00:00"}, {"condition": "Near Mint", "variant": "Normal", "language": "English", "quantity": 1, "title": "Balduvian Atrocity", "listingType": "ListingWithoutPhotos", "customListingId": "", "purchasePrice": 0.01, "shippingPrice": 0.0, "orderDate": "2023-02-18T01:58:55.526+00:00"}, {"condition": "Near Mint", "variant": "Normal", "language": "English", "quantity": 1, "title": "Balduvian Atrocity", "listingType": "ListingWithoutPhotos", "customListingId": "", "purchasePrice": 0.01, "shippingPrice": 0.0, "orderDate": "2023-02-17T06:27:43.223+00:00"}, {"condition": "Near Mint", "variant": "Normal", "language": "English", "quantity": 1, "title": "Balduvian Atrocity", "listingType": "ListingWithoutPhotos", "customListingId": "", "purchasePrice": 0.01, "shippingPrice": 0.0, "orderDate": "2023-02-17T02:23:51.463+00:00"}, {"condition": "Near Mint", "variant": "Normal", "language": "English", "quantity": 4, "title": "Balduvian Atrocity", "listingType": "ListingWithoutPhotos", "customListingId": "", "purchasePrice": 0.02, "shippingPrice": 0.99, "orderDate": "2023-02-16T02:14:49.35+00:00"}, {"condition": "Near Mint", "variant": "Normal", "language": "English", "quantity": 1, "title": "Balduvian Atrocity", "listingType": "ListingWithoutPhotos", "customListingId": "", "purchasePrice": 0.02, "shippingPrice": 0.0, "orderDate": "2023-02-15T19:27:30.35+00:00"}, {"condition": "Near Mint", "variant": "Normal", "language": "English", "quantity": 1, "title": "Balduvian Atrocity", "listingType": "ListingWithoutPhotos", "customListingId": "", "purchasePrice": 0.01, "shippingPrice": 0.0, "orderDate": "2023-02-10T18:26:55.74+00:00"}, {"condition": "Near Mint", "variant": "Normal", "language": "English", "quantity": 2, "title": "Balduvian Atrocity", "listingType": "ListingWithoutPhotos", "customListingId": "", "purchasePrice": 0.01, "shippingPrice": 0.0, "orderDate": "2023-02-10T14:51:37.37+00:00"}, {"condition": "Near Mint", "variant": "Normal", "language": "English", "quantity": 1, "title": "Balduvian Atrocity", "listingType": "ListingWithoutPhotos", "customListingId": "", "purchasePrice": 0.01, "shippingPrice": 0.0, "orderDate": "2023-02-10T05:49:58+00:00"}, {"condition": "Near Mint", "variant": "Normal", "language": "English", "quantity": 1, "title": "Balduvian Atrocity", "listingType": "ListingWithPhotos", "customListingId": "no4kH7ngTH81", "purchasePrice": 0.01, "shippingPrice": 0.99, "orderDate": "2023-02-09T22:02:37.61+00:00"}, {"condition": "Near Mint", "variant": "Normal", "language": "English", "quantity": 1, "title": "Balduvian Atrocity", "listingType": "ListingWithoutPhotos", "customListingId": "", "purchasePrice": 0.01, "shippingPrice": 0.0, "orderDate": "2023-02-09T14:37:46.516+00:00"}, {"condition": "Near Mint", "variant": "Normal", "language": "English", "quantity": 2, "title": "Balduvian Atrocity", "listingType": "ListingWithoutPhotos", "customListingId": "", "purchasePrice": 0.05, "shippingPrice": 0.0, "orderDate": "2023-02-09T05:15:48.63+00:00"}, {"condition": "Near Mint", "variant": "Normal", "language": "English", "quantity": 1, "title": "Balduvian Atrocity", "listingType": "ListingWithoutPhotos", "customListingId": "", "purchasePrice": 0.01, "shippingPrice": 0.0, "orderDate": "2023-02-06T01:43:54.96+00:00"}, {"condition": "Near Mint", "variant": "Foil", "language": "English", "quantity": 1, "title": "Balduvian Atrocity", "listingType": "ListingWithoutPhotos", "customListingId": "", "purchasePrice": 0.08, "shippingPrice": 0.0, "orderDate": "2023-02-04T01:43:18.35+00:00"}, {"condition": "Near Mint", "variant": "Normal", "language": "English", "quantity": 1, "title": "Balduvian Atrocity", "listingType": "ListingWithoutPhotos", "customListingId": "", "purchasePrice": 0.02, "shippingPrice": 0.0, "orderDate": "2023-02-01T21:48:35.406+00:00"}, {"condition": "Near Mint", "variant": "Normal", "language": "English", "quantity": 1, "title": "Balduvian Atrocity", "listingType": "ListingWithoutPhotos", "customListingId": "", "purchasePrice": 0.05, "shippingPrice": 0.0, "orderDate": "2023-01-31T01:22:32.403+00:00"}, {"condition": "Near Mint", "variant": "Normal", "language": "English", "quantity": 1, "title": "Balduvian Atrocity", "listingType": "ListingWithoutPhotos", "customListingId": "", "purchasePrice": 0.01, "shippingPrice": 0.0, "orderDate": "2023-01-30T07:31:41.326+00:00"}, {"condition": "Near Mint", "variant": "Normal", "language": "English", "quantity": 1, "title": "Balduvian Atrocity", "listingType": "ListingWithoutPhotos", "customListingId": "", "purchasePrice": 0.02, "shippingPrice": 0.99, "orderDate": "2023-01-29T23:21:27.496+00:00"}, {"condition": "Near Mint", "variant": "Normal", "language": "English", "quantity": 2, "title": "Balduvian Atrocity", "listingType": "ListingWithoutPhotos", "customListingId": "", "purchasePrice": 0.01, "shippingPrice": 0.0, "orderDate": "2023-01-28T23:25:16.093+00:00"}, {"condition": "Near Mint", "variant": "Normal", "language": "English", "quantity": 1, "title": "Balduvian Atrocity", "listingType": "ListingWithoutPhotos", "customListingId": "", "purchasePrice": 0.01, "shippingPrice": 0.0, "orderDate": "2023-01-27T19:06:54.21+00:00"}, {"condition": "Near Mint", "variant": "Foil", "language": "English", "quantity": 1, "title": "Balduvian Atrocity", "listingType": "ListingWithoutPhotos", "customListingId": "", "purchasePrice": 0.08, "shippingPrice": 0.0, "orderDate": "2023-01-25T02:09:03.09+00:00"}, {"condition": "Near Mint", "variant": "Normal", "language": "English", "quantity": 1, "title": "Balduvian Atrocity", "listingType": "ListingWithoutPhotos", "customListingId": "", "purchasePrice": 0.03, "shippingPrice": 0.5, "orderDate": "2023-01-24T20:29:31.76+00:00"}, {"condition": "Near Mint", "variant": "Normal", "language": "English", "quantity": 1, "title": "Balduvian Atrocity", "listingType": "ListingWithoutPhotos", "customListingId": "", "purchasePrice": 0.02, "shippingPrice": 0.0, "orderDate": "2023-01-23T20:34:12.25+00:00"}, {"condition": "Near Mint", "variant": "Normal", "language": "English", "quantity": 1, "title": "Balduvian Atrocity", "listingType": "ListingWithoutPhotos", "customListingId": "", "purchasePrice": 0.02, "shippingPrice": 0.0, "orderDate": "2023-01-23T16:31:18.55+00:00"}, {"condition": "Near Mint", "variant": "Normal", "language": "English", "quantity": 1, "title": "Balduvian Atrocity", "listingType": "ListingWithoutPhotos", "customListingId": "", "purchasePrice": 0.01, "shippingPrice": 0.99, "orderDate": "2023-01-21T03:25:11.786+00:00"}, {"condition": "Near Mint", "variant": "Normal", "language": "English", "quantity": 1, "title": "Balduvian Atrocity", "listingType": "ListingWithoutPhotos", "customListingId": "", "purchasePrice": 0.02, "shippingPrice": 0.0, "orderDate": "2023-01-19T22:36:42.553+00:00"}, {"condition": "Near Mint", "variant": "Normal", "language": "English", "quantity": 1, "title": "Balduvian Atrocity", "listingType": "ListingWithoutPhotos", "customListingId": "", "purchasePrice": 0.02, "shippingPrice": 0.0, "orderDate": "2023-01-19T04:35:28.976+00:00"}, {"condition": "Near Mint", "variant": "Normal", "language": "English", "quantity": 1, "title": "Balduvian Atrocity", "listingType": "ListingWithoutPhotos", "customListingId": "", "purchasePrice": 0.02, "shippingPrice": 0.0, "orderDate": "2023-01-19T04:26:23.28+00:00"}, {"condition": "Near Mint", "variant": "Normal", "language": "English", "quantity": 1, "title": "Balduvian Atrocity", "listingType": "ListingWithoutPhotos", "customListingId": "", "purchasePrice": 0.02, "shippingPrice": 0.0, "orderDate": "2023-01-18T03:59:41.146+00:00"}, {"condition": "Near Mint", "variant": "Foil", "language": "English", "quantity": 1, "title": "Balduvian Atrocity", "listingType": "ListingWithoutPhotos", "customListingId": "", "purchasePrice": 0.1, "shippingPrice": 1.99, "orderDate": "2023-01-17T18:47:13.556+00:00"}, {"condition": "Near Mint", "variant": "Normal", "language": "English", "quantity": 1, "title": "Balduvian Atrocity", "listingType": "ListingWithoutPhotos", "customListingId": "", "purchasePrice": 0.03, "shippingPrice": 0.0, "orderDate": "2023-01-15T06:52:04.766+00:00"}, {"condition": "Near Mint", "variant": "Normal", "language": "English", "quantity": 1, "title": "Balduvian Atrocity", "listingType": "ListingWithoutPhotos", "customListingId": "", "purchasePrice": 0.02, "shippingPrice": 0.0, "orderDate": "2023-01-13T20:59:59.39+00:00"}, {"condition": "Near Mint", "variant": "Normal", "language": "English", "quantity": 3, "title": "Balduvian Atrocity", "listingType": "ListingWithoutPhotos", "customListingId": "", "purchasePrice": 0.01, "shippingPrice": 0.99, "orderDate": "2023-01-10T00:14:00.8+00:00"}, {"condition": "Near Mint", "variant": "Normal", "language": "English", "quantity": 1, "title": "Balduvian Atrocity", "listingType": "ListingWithoutPhotos", "customListingId": "", "purchasePrice": 0.02, "shippingPrice": 0.0, "orderDate": "2023-01-10T00:14:00.22+00:00"}, {"condition": "Near Mint", "variant": "Normal", "language": "English", "quantity": 1, "title": "Balduvian Atrocity", "listingType": "ListingWithoutPhotos", "customListingId": "", "purchasePrice": 0.01, "shippingPrice": 0.99, "orderDate": "2023-01-08T19:18:24.03+00:00"}, {"condition": "Near Mint", "variant": "Normal", "language": "English", "quantity": 1, "title": "Balduvian Atrocity", "listingType": "ListingWithoutPhotos", "customListingId": "", "purchasePrice": 0.02, "shippingPrice": 1.99, "orderDate": "2023-01-07T17:56:35.866+00:00"}, {"condition": "Near Mint", "variant": "Normal", "language": "English", "quantity": 1, "title": "Balduvian Atrocity", "listingType": "ListingWithoutPhotos", "customListingId": "", "purchasePrice": 0.04, "shippingPrice": 0.0, "orderDate": "2023-01-07T14:38:01.313+00:00"}, {"condition": "Near Mint", "variant": "Normal", "language": "English", "quantity": 1, "title": "Balduvian Atrocity", "listingType": "ListingWithoutPhotos", "customListingId": "", "purchasePrice": 0.06, "shippingPrice": 0.0, "orderDate": "2023-01-05T04:17:22.296+00:00"}, {"condition": "Near Mint", "variant": "Foil", "language": "English", "quantity": 1, "title": "Balduvian Atrocity", "listingType": "ListingWithoutPhotos", "customListingId": "", "purchasePrice": 0.1, "shippingPrice": 0.0, "orderDate": "2023-01-04T19:18:36.2+00:00"}, {"condition": "Near Mint", "variant": "Foil", "language": "English", "quantity": 1, "title": "Balduvian Atrocity", "listingType": "ListingWithoutPhotos", "customListingId": "", "purchasePrice": 0.1, "shippingPrice": 0.0, "orderDate": "2023-01-04T02:07:44.043+00:00"}, {"condition": "Near Mint", "variant": "Foil", "language": "English", "quantity": 1, "title": "Balduvian Atrocity", "listingType": "ListingWithoutPhotos", "customListingId": "", "purchasePrice": 0.1, "shippingPrice": 0.0, "orderDate": "2023-01-01T22:29:15.206+00:00"}, {"condition": "Near Mint", "variant": "Foil", "language": "English", "quantity": 1, "title": "Balduvian Atrocity", "listingType": "ListingWithoutPhotos", "customListingId": "", "purchasePrice": 0.09, "shippingPrice": 0.0, "orderDate": "2023-01-01T15:13:18.046+00:00"}, {"condition": "Near Mint", "variant": "Foil", "language": "English", "quantity": 1, "title": "Balduvian Atrocity", "listingType": "ListingWithoutPhotos", "customListingId": "", "purchasePrice": 0.09, "shippingPrice": 0.0, "orderDate": "2023-01-01T06:31:05.05+00:00"}, {"condition": "Near Mint", "variant": "Normal", "language": "English", "quantity": 2, "title": "Balduvian Atrocity", "listingType": "ListingWithoutPhotos", "customListingId": "", "purchasePrice": 0.07, "shippingPrice": 0.0, "orderDate": "2023-01-01T03:52:22.3+00:00"}, {"condition": "Near Mint", "variant": "Normal", "language": "English", "quantity": 1, "title": "Balduvian Atrocity", "listingType": "ListingWithoutPhotos", "customListingId": "", "purchasePrice": 0.02, "shippingPrice": 0.0, "orderDate": "2022-12-31T17:38:04.393+00:00"}, {"condition": "Near Mint", "variant": "Normal", "language": "English", "quantity": 1, "title": "Balduvian Atrocity", "listingType": "ListingWithoutPhotos", "customListingId": "", "purchasePrice": 0.02, "shippingPrice": 0.0, "orderDate": "2022-12-31T04:52:23.7+00:00"}, {"condition": "Near Mint", "variant": "Normal", "language": "English", "quantity": 2, "title": "Balduvian Atrocity", "listingType": "ListingWithoutPhotos", "customListingId": "", "purchasePrice": 0.02, "shippingPrice": 0.0, "orderDate": "2022-12-31T03:28:19.586+00:00"}, {"condition": "Near Mint", "variant": "Normal", "language": "English", "quantity": 1, "title": "Balduvian Atrocity", "listingType": "ListingWithoutPhotos", "customListingId": "", "purchasePrice": 0.01, "shippingPrice": 0.99, "orderDate": "2022-12-30T20:12:31.52+00:00"}, {"condition": "Near Mint", "variant": "Normal", "language": "English", "quantity": 1, "title": "Balduvian Atrocity", "listingType": "ListingWithoutPhotos", "customListingId": "", "purchasePrice": 0.03, "shippingPrice": 0.99, "orderDate": "2022-12-29T15:53:10.78+00:00"}, {"condition": "Near Mint", "variant": "Normal", "language": "English", "quantity": 1, "title": "Balduvian Atrocity", "listingType": "ListingWithoutPhotos", "customListingId": "", "purchasePrice": 0.02, "shippingPrice": 0.0, "orderDate": "2022-12-28T06:19:38.613+00:00"}]