[{"condition": "Lightly Played", "variant": "Normal", "language": "English", "quantity": 1, "title": "Silver Scrutiny (Extended Art)", "listingType": "ListingWithoutPhotos", "customListingId": "", "purchasePrice": 0.47, "shippingPrice": 0.0, "orderDate": "2023-04-25T08:31:42.4+00:00"}, {"condition": "Near Mint", "variant": "Foil", "language": "English", "quantity": 1, "title": "Silver Scrutiny (Extended Art)", "listingType": "ListingWithoutPhotos", "customListingId": "", "purchasePrice": 0.27, "shippingPrice": 0.0, "orderDate": "2023-04-25T05:12:55.553+00:00"}, {"condition": "Near Mint", "variant": "Foil", "language": "English", "quantity": 1, "title": "Silver Scrutiny (Extended Art)", "listingType": "ListingWithoutPhotos", "customListingId": "", "purchasePrice": 0.27, "shippingPrice": 0.0, "orderDate": "2023-04-24T18:31:26.83+00:00"}, {"condition": "Near Mint", "variant": "Foil", "language": "English", "quantity": 2, "title": "Silver Scrutiny (Extended Art)", "listingType": "ListingWithoutPhotos", "customListingId": "", "purchasePrice": 0.27, "shippingPrice": 0.0, "orderDate": "2023-04-24T18:31:26.816+00:00"}, {"condition": "Near Mint", "variant": "Normal", "language": "English", "quantity": 1, "title": "Silver Scrutiny (Extended Art)", "listingType": "ListingWithoutPhotos", "customListingId": "", "purchasePrice": 0.19, "shippingPrice": 0.99, "orderDate": "2023-04-24T03:24:25.646+00:00"}, {"condition": "Near Mint", "variant": "Normal", "language": "English", "quantity": 1, "title": "Silver Scrutiny (Extended Art)", "listingType": "ListingWithoutPhotos", "customListingId": "", "purchasePrice": 0.55, "shippingPrice": 3.5, "orderDate": "2023-04-23T20:09:43.806+00:00"}, {"condition": "Near Mint", "variant": "Normal", "language": "English", "quantity": 2, "title": "Silver Scrutiny (Extended Art)", "listingType": "ListingWithoutPhotos", "customListingId": "", "purchasePrice": 0.28, "shippingPrice": 0.0, "orderDate": "2023-04-23T14:11:27.92+00:00"}, {"condition": "Near Mint", "variant": "Foil", "language": "English", "quantity": 1, "title": "Silver Scrutiny (Extended Art)", "listingType": "ListingWithoutPhotos", "customListingId": "", "purchasePrice": 0.29, "shippingPrice": 0.0, "orderDate": "2023-04-22T18:31:10.2+00:00"}, {"condition": "Lightly Played", "variant": "Normal", "language": "English", "quantity": 4, "title": "Silver Scrutiny (Extended Art)", "listingType": "ListingWithoutPhotos", "customListingId": "", "purchasePrice": 0.5, "shippingPrice": 0.99, "orderDate": "2023-04-21T20:14:37.146+00:00"}, {"condition": "Lightly Played", "variant": "Normal", "language": "English", "quantity": 2, "title": "Silver Scrutiny (Extended Art)", "listingType": "ListingWithoutPhotos", "customListingId": "", "purchasePrice": 0.36, "shippingPrice": 0.0, "orderDate": "2023-04-21T08:54:10.013+00:00"}, {"condition": "Near Mint", "variant": "Normal", "language": "English", "quantity": 1, "title": "Silver Scrutiny (Extended Art)", "listingType": "ListingWithoutPhotos", "customListingId": "", "purchasePrice": 0.3, "shippingPrice": 0.0, "orderDate": "2023-04-20T03:49:14.036+00:00"}, {"condition": "Near Mint", "variant": "Normal", "language": "English", "quantity": 2, "title": "Silver Scrutiny (Extended Art)", "listingType": "ListingWithoutPhotos", "customListingId": "", "purchasePrice": 0.29, "shippingPrice": 0.0, "orderDate": "2023-04-20T02:09:20.813+00:00"}, {"condition": "Near Mint", "variant": "Normal", "language": "English", "quantity": 1, "title": "Silver Scrutiny (Extended Art)", "listingType": "ListingWithoutPhotos", "customListingId": "", "purchasePrice": 0.3, "shippingPrice": 0.0, "orderDate": "2023-04-19T20:42:37.35+00:00"}, {"condition": "Lightly Played", "variant": "Foil", "language": "English", "quantity": 1, "title": "Silver Scrutiny (Extended Art)", "listingType": "ListingWithoutPhotos", "customListingId": "", "purchasePrice": 0.28, "shippingPrice": 0.0, "orderDate": "2023-04-18T06:02:08.916+00:00"}, {"condition": "Near Mint", "variant": "Normal", "language": "English", "quantity": 1, "title": "Silver Scrutiny (Extended Art)", "listingType": "ListingWithoutPhotos", "customListingId": "", "purchasePrice": 0.18, "shippingPrice": 0.99, "orderDate": "2023-04-15T01:33:06.846+00:00"}, {"condition": "Near Mint", "variant": "Foil", "language": "English", "quantity": 2, "title": "Silver Scrutiny (Extended Art)", "listingType": "ListingWithoutPhotos", "customListingId": "", "purchasePrice": 0.35, "shippingPrice": 0.0, "orderDate": "2023-04-14T02:00:21.816+00:00"}, {"condition": "Near Mint", "variant": "Foil", "language": "English", "quantity": 1, "title": "Silver Scrutiny (Extended Art)", "listingType": "ListingWithoutPhotos", "customListingId": "", "purchasePrice": 0.35, "shippingPrice": 0.0, "orderDate": "2023-04-13T03:06:04.333+00:00"}, {"condition": "Lightly Played", "variant": "Normal", "language": "English", "quantity": 1, "title": "Silver Scrutiny (Extended Art)", "listingType": "ListingWithoutPhotos", "customListingId": "", "purchasePrice": 0.36, "shippingPrice": 0.99, "orderDate": "2023-04-12T23:38:44.213+00:00"}, {"condition": "Lightly Played", "variant": "Foil", "language": "English", "quantity": 1, "title": "Silver Scrutiny (Extended Art)", "listingType": "ListingWithoutPhotos", "customListingId": "", "purchasePrice": 0.35, "shippingPrice": 0.0, "orderDate": "2023-04-10T21:20:00.483+00:00"}, {"condition": "Near Mint", "variant": "Normal", "language": "English", "quantity": 1, "title": "Silver Scrutiny (Extended Art)", "listingType": "ListingWithoutPhotos", "customListingId": "", "purchasePrice": 0.42, "shippingPrice": 0.0, "orderDate": "2023-04-09T04:46:03.546+00:00"}, {"condition": "Near Mint", "variant": "Normal", "language": "English", "quantity": 2, "title": "Silver Scrutiny (Extended Art)", "listingType": "ListingWithoutPhotos", "customListingId": "", "purchasePrice": 0.42, "shippingPrice": 0.0, "orderDate": "2023-04-09T02:42:29.106+00:00"}, {"condition": "Near Mint", "variant": "Foil", "language": "English", "quantity": 3, "title": "Silver Scrutiny (Extended Art)", "listingType": "ListingWithoutPhotos", "customListingId": "", "purchasePrice": 0.42, "shippingPrice": 0.0, "orderDate": "2023-04-09T02:42:29.036+00:00"}, {"condition": "Near Mint", "variant": "Foil", "language": "English", "quantity": 1, "title": "Silver Scrutiny (Extended Art)", "listingType": "ListingWithoutPhotos", "customListingId": "", "purchasePrice": 0.42, "shippingPrice": 0.0, "orderDate": "2023-04-08T20:05:20.65+00:00"}, {"condition": "Near Mint", "variant": "Foil", "language": "English", "quantity": 1, "title": "Silver Scrutiny (Extended Art)", "listingType": "ListingWithoutPhotos", "customListingId": "", "purchasePrice": 0.42, "shippingPrice": 0.0, "orderDate": "2023-04-07T23:17:06.583+00:00"}, {"condition": "Near Mint", "variant": "Foil", "language": "English", "quantity": 1, "title": "Silver Scrutiny (Extended Art)", "listingType": "ListingWithoutPhotos", "customListingId": "", "purchasePrice": 0.42, "shippingPrice": 0.0, "orderDate": "2023-04-07T18:40:03.796+00:00"}, {"condition": "Near Mint", "variant": "Foil", "language": "English", "quantity": 1, "title": "Silver Scrutiny (Extended Art)", "listingType": "ListingWithoutPhotos", "customListingId": "", "purchasePrice": 0.42, "shippingPrice": 0.0, "orderDate": "2023-04-07T10:32:59.753+00:00"}, {"condition": "Near Mint", "variant": "Normal", "language": "English", "quantity": 1, "title": "Silver Scrutiny (Extended Art)", "listingType": "ListingWithoutPhotos", "customListingId": "", "purchasePrice": 0.44, "shippingPrice": 0.0, "orderDate": "2023-04-05T04:01:21.953+00:00"}, {"condition": "Moderately Played", "variant": "Foil", "language": "English", "quantity": 1, "title": "Silver Scrutiny (Extended Art)", "listingType": "ListingWithoutPhotos", "customListingId": "", "purchasePrice": 0.38, "shippingPrice": 0.0, "orderDate": "2023-04-05T00:28:55.886+00:00"}, {"condition": "Near Mint", "variant": "Foil", "language": "English", "quantity": 1, "title": "Silver Scrutiny (Extended Art)", "listingType": "ListingWithoutPhotos", "customListingId": "", "purchasePrice": 0.44, "shippingPrice": 0.0, "orderDate": "2023-04-03T16:13:44.01+00:00"}, {"condition": "Near Mint", "variant": "Foil", "language": "English", "quantity": 1, "title": "Silver Scrutiny (Extended Art)", "listingType": "ListingWithoutPhotos", "customListingId": "", "purchasePrice": 0.48, "shippingPrice": 0.0, "orderDate": "2023-03-31T17:11:46.126+00:00"}, {"condition": "Near Mint", "variant": "Normal", "language": "English", "quantity": 1, "title": "Silver Scrutiny (Extended Art)", "listingType": "ListingWithoutPhotos", "customListingId": "", "purchasePrice": 0.45, "shippingPrice": 0.0, "orderDate": "2023-03-31T04:45:36.73+00:00"}, {"condition": "Near Mint", "variant": "Normal", "language": "English", "quantity": 1, "title": "Silver Scrutiny (Extended Art)", "listingType": "ListingWithoutPhotos", "customListingId": "", "purchasePrice": 0.24, "shippingPrice": 0.0, "orderDate": "2023-03-29T03:54:47.64+00:00"}, {"condition": "Near Mint", "variant": "Foil", "language": "English", "quantity": 1, "title": "Silver Scrutiny (Extended Art)", "listingType": "ListingWithoutPhotos", "customListingId": "", "purchasePrice": 0.51, "shippingPrice": 0.0, "orderDate": "2023-03-29T02:35:56.633+00:00"}, {"condition": "Lightly Played", "variant": "Foil", "language": "English", "quantity": 1, "title": "Silver Scrutiny (Extended Art)", "listingType": "ListingWithoutPhotos", "customListingId": "", "purchasePrice": 0.31, "shippingPrice": 0.0, "orderDate": "2023-03-29T00:46:53.713+00:00"}, {"condition": "Near Mint", "variant": "Normal", "language": "English", "quantity": 2, "title": "Silver Scrutiny (Extended Art)", "listingType": "ListingWithoutPhotos", "customListingId": "", "purchasePrice": 0.53, "shippingPrice": 0.0, "orderDate": "2023-03-28T00:42:55.286+00:00"}, {"condition": "Near Mint", "variant": "Foil", "language": "English", "quantity": 1, "title": "Silver Scrutiny (Extended Art)", "listingType": "ListingWithoutPhotos", "customListingId": "", "purchasePrice": 0.3, "shippingPrice": 0.0, "orderDate": "2023-03-27T21:34:35.003+00:00"}, {"condition": "Lightly Played", "variant": "Foil", "language": "English", "quantity": 1, "title": "Silver Scrutiny (Extended Art)", "listingType": "ListingWithoutPhotos", "customListingId": "", "purchasePrice": 0.37, "shippingPrice": 0.0, "orderDate": "2023-03-27T16:49:50.52+00:00"}, {"condition": "Near Mint", "variant": "Foil", "language": "English", "quantity": 1, "title": "Silver Scrutiny (Extended Art)", "listingType": "ListingWithoutPhotos", "customListingId": "", "purchasePrice": 0.25, "shippingPrice": 0.99, "orderDate": "2023-03-23T10:08:35.836+00:00"}, {"condition": "Lightly Played", "variant": "Foil", "language": "English", "quantity": 1, "title": "Silver Scrutiny (Extended Art)", "listingType": "ListingWithoutPhotos", "customListingId": "", "purchasePrice": 0.28, "shippingPrice": 0.99, "orderDate": "2023-03-23T10:04:19.173+00:00"}, {"condition": "Near Mint", "variant": "Foil", "language": "English", "quantity": 1, "title": "Silver Scrutiny (Extended Art)", "listingType": "ListingWithoutPhotos", "customListingId": "", "purchasePrice": 0.25, "shippingPrice": 0.99, "orderDate": "2023-03-23T08:32:29.51+00:00"}, {"condition": "Lightly Played", "variant": "Foil", "language": "English", "quantity": 1, "title": "Silver Scrutiny (Extended Art)", "listingType": "ListingWithoutPhotos", "customListingId": "", "purchasePrice": 0.28, "shippingPrice": 0.99, "orderDate": "2023-03-23T08:32:29.51+00:00"}, {"condition": "Near Mint", "variant": "Foil", "language": "English", "quantity": 2, "title": "Silver Scrutiny (Extended Art)", "listingType": "ListingWithoutPhotos", "customListingId": "", "purchasePrice": 0.75, "shippingPrice": 0.99, "orderDate": "2023-03-22T06:19:00.566+00:00"}, {"condition": "Lightly Played", "variant": "Foil", "language": "English", "quantity": 1, "title": "Silver Scrutiny (Extended Art)", "listingType": "ListingWithoutPhotos", "customListingId": "", "purchasePrice": 0.37, "shippingPrice": 0.0, "orderDate": "2023-03-21T04:34:05.496+00:00"}, {"condition": "Near Mint", "variant": "Foil", "language": "English", "quantity": 1, "title": "Silver Scrutiny (Extended Art)", "listingType": "ListingWithoutPhotos", "customListingId": "", "purchasePrice": 0.45, "shippingPrice": 0.0, "orderDate": "2023-03-20T22:51:24.95+00:00"}, {"condition": "Near Mint", "variant": "Foil", "language": "English", "quantity": 1, "title": "Silver Scrutiny (Extended Art)", "listingType": "ListingWithoutPhotos", "customListingId": "", "purchasePrice": 0.57, "shippingPrice": 0.0, "orderDate": "2023-03-20T11:57:19.453+00:00"}, {"condition": "Near Mint", "variant": "Foil", "language": "English", "quantity": 2, "title": "Silver Scrutiny (Extended Art)", "listingType": "ListingWithoutPhotos", "customListingId": "", "purchasePrice": 0.57, "shippingPrice": 0.0, "orderDate": "2023-03-20T11:57:19.44+00:00"}, {"condition": "Lightly Played", "variant": "Foil", "language": "English", "quantity": 1, "title": "Silver Scrutiny (Extended Art)", "listingType": "ListingWithoutPhotos", "customListingId": "", "purchasePrice": 0.34, "shippingPrice": 0.0, "orderDate": "2023-03-20T11:57:19.423+00:00"}, {"condition": "Near Mint", "variant": "Normal", "language": "English", "quantity": 3, "title": "Silver Scrutiny (Extended Art)", "listingType": "ListingWithoutPhotos", "customListingId": "", "purchasePrice": 0.53, "shippingPrice": 0.0, "orderDate": "2023-03-20T05:47:26.513+00:00"}, {"condition": "Lightly Played", "variant": "Foil", "language": "English", "quantity": 3, "title": "Silver Scrutiny (Extended Art)", "listingType": "ListingWithoutPhotos", "customListingId": "", "purchasePrice": 0.29, "shippingPrice": 1.49, "orderDate": "2023-03-18T17:24:19.12+00:00"}, {"condition": "Near Mint", "variant": "Foil", "language": "English", "quantity": 1, "title": "Silver Scrutiny (Extended Art)", "listingType": "ListingWithoutPhotos", "customListingId": "", "purchasePrice": 0.45, "shippingPrice": 3.99, "orderDate": "2023-03-18T17:24:17.916+00:00"}, {"condition": "Near Mint", "variant": "Normal", "language": "English", "quantity": 1, "title": "Silver Scrutiny (Extended Art)", "listingType": "ListingWithoutPhotos", "customListingId": "", "purchasePrice": 0.5, "shippingPrice": 0.0, "orderDate": "2023-03-16T10:16:57.376+00:00"}, {"condition": "Near Mint", "variant": "Foil", "language": "English", "quantity": 1, "title": "Silver Scrutiny (Extended Art)", "listingType": "ListingWithoutPhotos", "customListingId": "", "purchasePrice": 0.75, "shippingPrice": 0.0, "orderDate": "2023-03-15T23:11:38.89+00:00"}, {"condition": "Near Mint", "variant": "Foil", "language": "English", "quantity": 1, "title": "Silver Scrutiny (Extended Art)", "listingType": "ListingWithoutPhotos", "customListingId": "", "purchasePrice": 0.75, "shippingPrice": 0.0, "orderDate": "2023-03-15T21:59:43.79+00:00"}, {"condition": "Lightly Played", "variant": "Normal", "language": "English", "quantity": 1, "title": "Silver Scrutiny (Extended Art)", "listingType": "ListingWithoutPhotos", "customListingId": "", "purchasePrice": 0.36, "shippingPrice": 0.99, "orderDate": "2023-03-15T12:41:18.94+00:00"}, {"condition": "Lightly Played", "variant": "Normal", "language": "English", "quantity": 1, "title": "Silver Scrutiny (Extended Art)", "listingType": "ListingWithoutPhotos", "customListingId": "", "purchasePrice": 0.31, "shippingPrice": 0.0, "orderDate": "2023-03-15T12:41:18.663+00:00"}, {"condition": "Lightly Played", "variant": "Normal", "language": "English", "quantity": 1, "title": "Silver Scrutiny (Extended Art)", "listingType": "ListingWithoutPhotos", "customListingId": "", "purchasePrice": 0.3, "shippingPrice": 0.99, "orderDate": "2023-03-15T12:41:18.633+00:00"}, {"condition": "Lightly Played", "variant": "Foil", "language": "English", "quantity": 1, "title": "Silver Scrutiny (Extended Art)", "listingType": "ListingWithoutPhotos", "customListingId": "", "purchasePrice": 0.5, "shippingPrice": 0.0, "orderDate": "2023-03-15T09:22:16.45+00:00"}, {"condition": "Near Mint", "variant": "Normal", "language": "English", "quantity": 1, "title": "Silver Scrutiny (Extended Art)", "listingType": "ListingWithoutPhotos", "customListingId": "", "purchasePrice": 0.3, "shippingPrice": 0.99, "orderDate": "2023-03-14T05:19:31.776+00:00"}, {"condition": "Near Mint", "variant": "Foil", "language": "English", "quantity": 1, "title": "Silver Scrutiny (Extended Art)", "listingType": "ListingWithoutPhotos", "customListingId": "", "purchasePrice": 0.75, "shippingPrice": 0.0, "orderDate": "2023-03-14T05:19:31.73+00:00"}, {"condition": "Near Mint", "variant": "Normal", "language": "English", "quantity": 1, "title": "Silver Scrutiny (Extended Art)", "listingType": "ListingWithoutPhotos", "customListingId": "", "purchasePrice": 0.35, "shippingPrice": 0.99, "orderDate": "2023-03-14T05:19:31.7+00:00"}, {"condition": "Near Mint", "variant": "Foil", "language": "English", "quantity": 1, "title": "Silver Scrutiny (Extended Art)", "listingType": "ListingWithoutPhotos", "customListingId": "", "purchasePrice": 0.75, "shippingPrice": 0.0, "orderDate": "2023-03-13T21:23:11.16+00:00"}, {"condition": "Near Mint", "variant": "Foil", "language": "English", "quantity": 1, "title": "Silver Scrutiny (Extended Art)", "listingType": "ListingWithoutPhotos", "customListingId": "", "purchasePrice": 0.74, "shippingPrice": 0.0, "orderDate": "2023-03-13T21:23:11.113+00:00"}, {"condition": "Moderately Played", "variant": "Foil", "language": "English", "quantity": 1, "title": "Silver Scrutiny (Extended Art)", "listingType": "ListingWithoutPhotos", "customListingId": "", "purchasePrice": 0.38, "shippingPrice": 0.0, "orderDate": "2023-03-13T15:01:29+00:00"}, {"condition": "Near Mint", "variant": "Foil", "language": "English", "quantity": 1, "title": "Silver Scrutiny (Extended Art)", "listingType": "ListingWithoutPhotos", "customListingId": "", "purchasePrice": 0.53, "shippingPrice": 0.0, "orderDate": "2023-03-13T15:01:29+00:00"}, {"condition": "Near Mint", "variant": "Foil", "language": "English", "quantity": 2, "title": "Silver Scrutiny (Extended Art)", "listingType": "ListingWithoutPhotos", "customListingId": "", "purchasePrice": 0.55, "shippingPrice": 0.0, "orderDate": "2023-03-13T06:33:41.426+00:00"}, {"condition": "Near Mint", "variant": "Foil", "language": "English", "quantity": 1, "title": "Silver Scrutiny (Extended Art)", "listingType": "ListingWithoutPhotos", "customListingId": "", "purchasePrice": 0.3, "shippingPrice": 0.99, "orderDate": "2023-03-12T15:57:23.913+00:00"}, {"condition": "Lightly Played", "variant": "Foil", "language": "English", "quantity": 1, "title": "Silver Scrutiny (Extended Art)", "listingType": "ListingWithoutPhotos", "customListingId": "", "purchasePrice": 0.25, "shippingPrice": 0.0, "orderDate": "2023-03-12T01:18:11.933+00:00"}, {"condition": "Lightly Played", "variant": "Foil", "language": "English", "quantity": 2, "title": "Silver Scrutiny (Extended Art)", "listingType": "ListingWithoutPhotos", "customListingId": "", "purchasePrice": 0.5, "shippingPrice": 0.99, "orderDate": "2023-03-12T01:18:11.9+00:00"}, {"condition": "Near Mint", "variant": "Foil", "language": "English", "quantity": 3, "title": "Silver Scrutiny (Extended Art)", "listingType": "ListingWithoutPhotos", "customListingId": "", "purchasePrice": 0.49, "shippingPrice": 0.99, "orderDate": "2023-03-11T05:37:01.793+00:00"}, {"condition": "Near Mint", "variant": "Normal", "language": "English", "quantity": 1, "title": "Silver Scrutiny (Extended Art)", "listingType": "ListingWithoutPhotos", "customListingId": "", "purchasePrice": 0.35, "shippingPrice": 0.0, "orderDate": "2023-03-11T05:35:19.6+00:00"}, {"condition": "Near Mint", "variant": "Normal", "language": "English", "quantity": 1, "title": "Silver Scrutiny (Extended Art)", "listingType": "ListingWithoutPhotos", "customListingId": "", "purchasePrice": 1.0, "shippingPrice": 0.0, "orderDate": "2023-03-10T22:42:51.123+00:00"}, {"condition": "Near Mint", "variant": "Normal", "language": "English", "quantity": 1, "title": "Silver Scrutiny (Extended Art)", "listingType": "ListingWithoutPhotos", "customListingId": "", "purchasePrice": 0.9, "shippingPrice": 0.0, "orderDate": "2023-03-10T22:42:51.123+00:00"}, {"condition": "Near Mint", "variant": "Normal", "language": "English", "quantity": 1, "title": "Silver Scrutiny (Extended Art)", "listingType": "ListingWithoutPhotos", "customListingId": "", "purchasePrice": 0.85, "shippingPrice": 0.0, "orderDate": "2023-03-10T22:42:51.093+00:00"}, {"condition": "Near Mint", "variant": "Normal", "language": "English", "quantity": 1, "title": "Silver Scrutiny (Extended Art)", "listingType": "ListingWithoutPhotos", "customListingId": "", "purchasePrice": 0.75, "shippingPrice": 0.0, "orderDate": "2023-03-10T22:42:51.076+00:00"}, {"condition": "Near Mint", "variant": "Normal", "language": "English", "quantity": 1, "title": "Silver Scrutiny (Extended Art)", "listingType": "ListingWithoutPhotos", "customListingId": "", "purchasePrice": 0.74, "shippingPrice": 0.0, "orderDate": "2023-03-10T20:36:43.366+00:00"}, {"condition": "Near Mint", "variant": "Normal", "language": "English", "quantity": 1, "title": "Silver Scrutiny (Extended Art)", "listingType": "ListingWithoutPhotos", "customListingId": "", "purchasePrice": 0.7, "shippingPrice": 0.0, "orderDate": "2023-03-10T05:53:42.826+00:00"}, {"condition": "Lightly Played", "variant": "Foil", "language": "English", "quantity": 1, "title": "Silver Scrutiny (Extended Art)", "listingType": "ListingWithoutPhotos", "customListingId": "", "purchasePrice": 0.37, "shippingPrice": 0.99, "orderDate": "2023-03-10T05:13:41.046+00:00"}, {"condition": "Near Mint", "variant": "Normal", "language": "English", "quantity": 1, "title": "Silver Scrutiny (Extended Art)", "listingType": "ListingWithoutPhotos", "customListingId": "", "purchasePrice": 0.59, "shippingPrice": 0.0, "orderDate": "2023-03-10T01:36:13.356+00:00"}, {"condition": "Near Mint", "variant": "Normal", "language": "English", "quantity": 1, "title": "Silver Scrutiny (Extended Art)", "listingType": "ListingWithoutPhotos", "customListingId": "", "purchasePrice": 0.58, "shippingPrice": 0.0, "orderDate": "2023-03-10T01:36:13.35+00:00"}, {"condition": "Near Mint", "variant": "Foil", "language": "English", "quantity": 2, "title": "Silver Scrutiny (Extended Art)", "listingType": "ListingWithoutPhotos", "customListingId": "", "purchasePrice": 0.7, "shippingPrice": 0.0, "orderDate": "2023-03-10T01:36:13.343+00:00"}, {"condition": "Near Mint", "variant": "Foil", "language": "English", "quantity": 1, "title": "Silver Scrutiny (Extended Art)", "listingType": "ListingWithoutPhotos", "customListingId": "", "purchasePrice": 0.69, "shippingPrice": 0.0, "orderDate": "2023-03-10T01:36:13.333+00:00"}, {"condition": "Near Mint", "variant": "Normal", "language": "English", "quantity": 1, "title": "Silver Scrutiny (Extended Art)", "listingType": "ListingWithoutPhotos", "customListingId": "", "purchasePrice": 0.69, "shippingPrice": 0.0, "orderDate": "2023-03-10T01:36:13.333+00:00"}, {"condition": "Near Mint", "variant": "Foil", "language": "English", "quantity": 1, "title": "Silver Scrutiny (Extended Art)", "listingType": "ListingWithoutPhotos", "customListingId": "", "purchasePrice": 0.68, "shippingPrice": 0.0, "orderDate": "2023-03-10T01:36:13.316+00:00"}, {"condition": "Near Mint", "variant": "Foil", "language": "English", "quantity": 1, "title": "Silver Scrutiny (Extended Art)", "listingType": "ListingWithoutPhotos", "customListingId": "", "purchasePrice": 0.56, "shippingPrice": 0.0, "orderDate": "2023-03-10T01:36:13.316+00:00"}, {"condition": "Near Mint", "variant": "Foil", "language": "English", "quantity": 1, "title": "Silver Scrutiny (Extended Art)", "listingType": "ListingWithoutPhotos", "customListingId": "", "purchasePrice": 0.51, "shippingPrice": 0.0, "orderDate": "2023-03-10T01:36:13.306+00:00"}, {"condition": "Near Mint", "variant": "Foil", "language": "English", "quantity": 1, "title": "Silver Scrutiny (Extended Art)", "listingType": "ListingWithoutPhotos", "customListingId": "", "purchasePrice": 0.52, "shippingPrice": 0.0, "orderDate": "2023-03-10T01:36:13.226+00:00"}, {"condition": "Near Mint", "variant": "Normal", "language": "English", "quantity": 1, "title": "Silver Scrutiny (Extended Art)", "listingType": "ListingWithoutPhotos", "customListingId": "", "purchasePrice": 0.49, "shippingPrice": 0.0, "orderDate": "2023-03-09T22:21:49.476+00:00"}, {"condition": "Near Mint", "variant": "Foil", "language": "English", "quantity": 1, "title": "Silver Scrutiny (Extended Art)", "listingType": "ListingWithoutPhotos", "customListingId": "", "purchasePrice": 0.43, "shippingPrice": 0.0, "orderDate": "2023-03-09T13:33:26.94+00:00"}, {"condition": "Near Mint", "variant": "Foil", "language": "English", "quantity": 1, "title": "Silver Scrutiny (Extended Art)", "listingType": "ListingWithoutPhotos", "customListingId": "", "purchasePrice": 0.24, "shippingPrice": 1.0, "orderDate": "2023-03-08T21:05:53.553+00:00"}, {"condition": "Near Mint", "variant": "Foil", "language": "English", "quantity": 4, "title": "Silver Scrutiny (Extended Art)", "listingType": "ListingWithoutPhotos", "customListingId": "", "purchasePrice": 0.49, "shippingPrice": 1.25, "orderDate": "2023-03-08T21:05:53.53+00:00"}, {"condition": "Near Mint", "variant": "Foil", "language": "English", "quantity": 1, "title": "Silver Scrutiny (Extended Art)", "listingType": "ListingWithoutPhotos", "customListingId": "", "purchasePrice": 0.44, "shippingPrice": 0.0, "orderDate": "2023-03-06T20:22:12.946+00:00"}, {"condition": "Near Mint", "variant": "Normal", "language": "English", "quantity": 1, "title": "Silver Scrutiny (Extended Art)", "listingType": "ListingWithoutPhotos", "customListingId": "", "purchasePrice": 0.37, "shippingPrice": 0.0, "orderDate": "2023-03-06T16:48:33.473+00:00"}, {"condition": "Near Mint", "variant": "Normal", "language": "English", "quantity": 1, "title": "Silver Scrutiny (Extended Art)", "listingType": "ListingWithoutPhotos", "customListingId": "", "purchasePrice": 0.5, "shippingPrice": 0.0, "orderDate": "2023-03-05T05:04:38.793+00:00"}, {"condition": "Lightly Played", "variant": "Normal", "language": "English", "quantity": 1, "title": "Silver Scrutiny (Extended Art)", "listingType": "ListingWithoutPhotos", "customListingId": "", "purchasePrice": 0.46, "shippingPrice": 0.99, "orderDate": "2023-03-04T19:45:40.513+00:00"}, {"condition": "Near Mint", "variant": "Foil", "language": "English", "quantity": 1, "title": "Silver Scrutiny (Extended Art)", "listingType": "ListingWithoutPhotos", "customListingId": "", "purchasePrice": 0.5, "shippingPrice": 0.99, "orderDate": "2023-03-04T06:15:21.12+00:00"}, {"condition": "Near Mint", "variant": "Normal", "language": "English", "quantity": 1, "title": "Silver Scrutiny (Extended Art)", "listingType": "ListingWithoutPhotos", "customListingId": "", "purchasePrice": 0.37, "shippingPrice": 0.0, "orderDate": "2023-03-04T02:39:00.69+00:00"}, {"condition": "Lightly Played", "variant": "Foil", "language": "English", "quantity": 4, "title": "Silver Scrutiny (Extended Art)", "listingType": "ListingWithoutPhotos", "customListingId": "", "purchasePrice": 0.7, "shippingPrice": 0.99, "orderDate": "2023-03-04T00:14:12.456+00:00"}, {"condition": "Lightly Played", "variant": "Normal", "language": "English", "quantity": 1, "title": "Silver Scrutiny (Extended Art)", "listingType": "ListingWithoutPhotos", "customListingId": "", "purchasePrice": 0.32, "shippingPrice": 0.0, "orderDate": "2023-03-03T21:40:13.39+00:00"}, {"condition": "Near Mint", "variant": "Foil", "language": "English", "quantity": 1, "title": "Silver Scrutiny (Extended Art)", "listingType": "ListingWithoutPhotos", "customListingId": "", "purchasePrice": 0.48, "shippingPrice": 0.0, "orderDate": "2023-03-03T16:37:13.5+00:00"}, {"condition": "Near Mint", "variant": "Normal", "language": "English", "quantity": 1, "title": "Silver Scrutiny (Extended Art)", "listingType": "ListingWithoutPhotos", "customListingId": "", "purchasePrice": 0.3, "shippingPrice": 0.99, "orderDate": "2023-03-03T09:58:50.38+00:00"}, {"condition": "Near Mint", "variant": "Foil", "language": "English", "quantity": 1, "title": "Silver Scrutiny (Extended Art)", "listingType": "ListingWithoutPhotos", "customListingId": "", "purchasePrice": 0.47, "shippingPrice": 0.0, "orderDate": "2023-03-02T21:07:29.503+00:00"}, {"condition": "Near Mint", "variant": "Foil", "language": "English", "quantity": 1, "title": "Silver Scrutiny (Extended Art)", "listingType": "ListingWithoutPhotos", "customListingId": "", "purchasePrice": 0.26, "shippingPrice": 0.0, "orderDate": "2023-03-02T21:07:29.463+00:00"}, {"condition": "Near Mint", "variant": "Foil", "language": "English", "quantity": 2, "title": "Silver Scrutiny (Extended Art)", "listingType": "ListingWithoutPhotos", "customListingId": "", "purchasePrice": 0.26, "shippingPrice": 1.15, "orderDate": "2023-03-02T21:07:29.446+00:00"}, {"condition": "Near Mint", "variant": "Normal", "language": "English", "quantity": 1, "title": "Silver Scrutiny (Extended Art)", "listingType": "ListingWithoutPhotos", "customListingId": "", "purchasePrice": 0.69, "shippingPrice": 0.0, "orderDate": "2023-03-01T21:07:23.78+00:00"}, {"condition": "Near Mint", "variant": "Normal", "language": "English", "quantity": 1, "title": "Silver Scrutiny (Extended Art)", "listingType": "ListingWithoutPhotos", "customListingId": "", "purchasePrice": 0.5, "shippingPrice": 0.0, "orderDate": "2023-03-01T21:07:23.766+00:00"}, {"condition": "Near Mint", "variant": "Foil", "language": "English", "quantity": 1, "title": "Silver Scrutiny (Extended Art)", "listingType": "ListingWithoutPhotos", "customListingId": "", "purchasePrice": 0.26, "shippingPrice": 0.0, "orderDate": "2023-03-01T06:30:19.603+00:00"}, {"condition": "Near Mint", "variant": "Foil", "language": "English", "quantity": 1, "title": "Silver Scrutiny (Extended Art)", "listingType": "ListingWithoutPhotos", "customListingId": "", "purchasePrice": 0.26, "shippingPrice": 0.0, "orderDate": "2023-02-28T21:24:38.97+00:00"}, {"condition": "Lightly Played", "variant": "Normal", "language": "English", "quantity": 1, "title": "Silver Scrutiny (Extended Art)", "listingType": "ListingWithoutPhotos", "customListingId": "", "purchasePrice": 0.4, "shippingPrice": 0.99, "orderDate": "2023-02-28T17:43:25.51+00:00"}, {"condition": "Near Mint", "variant": "Foil", "language": "English", "quantity": 1, "title": "Silver Scrutiny (Extended Art)", "listingType": "ListingWithoutPhotos", "customListingId": "", "purchasePrice": 0.26, "shippingPrice": 0.0, "orderDate": "2023-02-28T07:50:07.49+00:00"}, {"condition": "Near Mint", "variant": "Foil", "language": "English", "quantity": 1, "title": "Silver Scrutiny (Extended Art)", "listingType": "ListingWithoutPhotos", "customListingId": "", "purchasePrice": 0.5, "shippingPrice": 0.0, "orderDate": "2023-02-27T23:03:19+00:00"}, {"condition": "Near Mint", "variant": "Foil", "language": "English", "quantity": 1, "title": "Silver Scrutiny (Extended Art)", "listingType": "ListingWithoutPhotos", "customListingId": "", "purchasePrice": 0.45, "shippingPrice": 0.0, "orderDate": "2023-02-27T08:21:15.51+00:00"}, {"condition": "Lightly Played", "variant": "Foil", "language": "English", "quantity": 1, "title": "Silver Scrutiny (Extended Art)", "listingType": "ListingWithoutPhotos", "customListingId": "", "purchasePrice": 0.25, "shippingPrice": 2.99, "orderDate": "2023-02-25T21:37:02.506+00:00"}, {"condition": "Near Mint", "variant": "Normal", "language": "English", "quantity": 3, "title": "Silver Scrutiny (Extended Art)", "listingType": "ListingWithoutPhotos", "customListingId": "", "purchasePrice": 0.34, "shippingPrice": 0.0, "orderDate": "2023-02-25T02:49:45.853+00:00"}, {"condition": "Near Mint", "variant": "Normal", "language": "English", "quantity": 1, "title": "Silver Scrutiny (Extended Art)", "listingType": "ListingWithoutPhotos", "customListingId": "", "purchasePrice": 0.19, "shippingPrice": 0.0, "orderDate": "2023-02-25T00:58:09.003+00:00"}, {"condition": "Near Mint", "variant": "Normal", "language": "English", "quantity": 1, "title": "Silver Scrutiny (Extended Art)", "listingType": "ListingWithoutPhotos", "customListingId": "", "purchasePrice": 0.3, "shippingPrice": 0.99, "orderDate": "2023-02-24T18:56:32.44+00:00"}, {"condition": "Near Mint", "variant": "Normal", "language": "English", "quantity": 1, "title": "Silver Scrutiny (Extended Art)", "listingType": "ListingWithoutPhotos", "customListingId": "", "purchasePrice": 0.55, "shippingPrice": 0.0, "orderDate": "2023-02-23T09:46:41.34+00:00"}, {"condition": "Near Mint", "variant": "Normal", "language": "English", "quantity": 2, "title": "Silver Scrutiny (Extended Art)", "listingType": "ListingWithoutPhotos", "customListingId": "", "purchasePrice": 0.5, "shippingPrice": 0.0, "orderDate": "2023-02-23T09:46:41.306+00:00"}, {"condition": "Lightly Played", "variant": "Foil", "language": "English", "quantity": 1, "title": "Silver Scrutiny (Extended Art)", "listingType": "ListingWithoutPhotos", "customListingId": "", "purchasePrice": 0.42, "shippingPrice": 0.0, "orderDate": "2023-02-23T03:05:18.26+00:00"}, {"condition": "Near Mint", "variant": "Foil", "language": "English", "quantity": 4, "title": "Silver Scrutiny (Extended Art)", "listingType": "ListingWithoutPhotos", "customListingId": "", "purchasePrice": 0.71, "shippingPrice": 0.0, "orderDate": "2023-02-23T02:17:46.386+00:00"}, {"condition": "Near Mint", "variant": "Foil", "language": "English", "quantity": 1, "title": "Silver Scrutiny (Extended Art)", "listingType": "ListingWithoutPhotos", "customListingId": "", "purchasePrice": 0.47, "shippingPrice": 0.0, "orderDate": "2023-02-22T15:12:03.916+00:00"}, {"condition": "Near Mint", "variant": "Normal", "language": "English", "quantity": 1, "title": "Silver Scrutiny (Extended Art)", "listingType": "ListingWithoutPhotos", "customListingId": "", "purchasePrice": 0.47, "shippingPrice": 0.0, "orderDate": "2023-02-22T02:07:27.68+00:00"}, {"condition": "Near Mint", "variant": "Normal", "language": "English", "quantity": 1, "title": "Silver Scrutiny (Extended Art)", "listingType": "ListingWithoutPhotos", "customListingId": "", "purchasePrice": 0.35, "shippingPrice": 0.0, "orderDate": "2023-02-22T02:07:27.62+00:00"}, {"condition": "Lightly Played", "variant": "Normal", "language": "English", "quantity": 2, "title": "Silver Scrutiny (Extended Art)", "listingType": "ListingWithoutPhotos", "customListingId": "", "purchasePrice": 0.45, "shippingPrice": 1.49, "orderDate": "2023-02-22T02:07:27.553+00:00"}, {"condition": "Near Mint", "variant": "Foil", "language": "English", "quantity": 1, "title": "Silver Scrutiny (Extended Art)", "listingType": "ListingWithoutPhotos", "customListingId": "", "purchasePrice": 0.43, "shippingPrice": 0.0, "orderDate": "2023-02-22T01:33:31.536+00:00"}, {"condition": "Near Mint", "variant": "Foil", "language": "English", "quantity": 4, "title": "Silver Scrutiny (Extended Art)", "listingType": "ListingWithoutPhotos", "customListingId": "", "purchasePrice": 0.74, "shippingPrice": 0.99, "orderDate": "2023-02-20T21:18:35.23+00:00"}, {"condition": "Near Mint", "variant": "Normal", "language": "English", "quantity": 2, "title": "Silver Scrutiny (Extended Art)", "listingType": "ListingWithoutPhotos", "customListingId": "", "purchasePrice": 0.35, "shippingPrice": 0.0, "orderDate": "2023-02-20T08:08:45.81+00:00"}, {"condition": "Near Mint", "variant": "Normal", "language": "English", "quantity": 1, "title": "Silver Scrutiny (Extended Art)", "listingType": "ListingWithoutPhotos", "customListingId": "", "purchasePrice": 0.4, "shippingPrice": 0.0, "orderDate": "2023-02-19T22:21:43.973+00:00"}, {"condition": "Near Mint", "variant": "Normal", "language": "English", "quantity": 1, "title": "Silver Scrutiny (Extended Art)", "listingType": "ListingWithoutPhotos", "customListingId": "", "purchasePrice": 0.39, "shippingPrice": 0.0, "orderDate": "2023-02-19T22:21:43.956+00:00"}, {"condition": "Near Mint", "variant": "Normal", "language": "English", "quantity": 2, "title": "Silver Scrutiny (Extended Art)", "listingType": "ListingWithoutPhotos", "customListingId": "", "purchasePrice": 0.39, "shippingPrice": 0.0, "orderDate": "2023-02-19T22:21:43.926+00:00"}, {"condition": "Lightly Played", "variant": "Foil", "language": "English", "quantity": 1, "title": "Silver Scrutiny (Extended Art)", "listingType": "ListingWithoutPhotos", "customListingId": "", "purchasePrice": 0.24, "shippingPrice": 0.0, "orderDate": "2023-02-19T18:55:58.536+00:00"}, {"condition": "Near Mint", "variant": "Normal", "language": "English", "quantity": 2, "title": "Silver Scrutiny (Extended Art)", "listingType": "ListingWithoutPhotos", "customListingId": "", "purchasePrice": 0.39, "shippingPrice": 0.0, "orderDate": "2023-02-19T17:25:47.79+00:00"}, {"condition": "Near Mint", "variant": "Normal", "language": "English", "quantity": 4, "title": "Silver Scrutiny (Extended Art)", "listingType": "ListingWithoutPhotos", "customListingId": "", "purchasePrice": 0.25, "shippingPrice": 1.99, "orderDate": "2023-02-18T11:36:46.47+00:00"}, {"condition": "Near Mint", "variant": "Normal", "language": "English", "quantity": 1, "title": "Silver Scrutiny (Extended Art)", "listingType": "ListingWithoutPhotos", "customListingId": "", "purchasePrice": 0.35, "shippingPrice": 0.0, "orderDate": "2023-02-17T15:21:34.52+00:00"}, {"condition": "Near Mint", "variant": "Normal", "language": "English", "quantity": 1, "title": "Silver Scrutiny (Extended Art)", "listingType": "ListingWithoutPhotos", "customListingId": "", "purchasePrice": 0.35, "shippingPrice": 0.0, "orderDate": "2023-02-15T23:51:51.363+00:00"}, {"condition": "Near Mint", "variant": "Normal", "language": "English", "quantity": 1, "title": "Silver Scrutiny (Extended Art)", "listingType": "ListingWithoutPhotos", "customListingId": "", "purchasePrice": 0.35, "shippingPrice": 0.0, "orderDate": "2023-02-15T22:56:07.45+00:00"}, {"condition": "Near Mint", "variant": "Normal", "language": "English", "quantity": 1, "title": "Silver Scrutiny (Extended Art)", "listingType": "ListingWithoutPhotos", "customListingId": "", "purchasePrice": 0.34, "shippingPrice": 0.0, "orderDate": "2023-02-15T22:56:07.423+00:00"}, {"condition": "Near Mint", "variant": "Foil", "language": "English", "quantity": 1, "title": "Silver Scrutiny (Extended Art)", "listingType": "ListingWithoutPhotos", "customListingId": "", "purchasePrice": 0.47, "shippingPrice": 0.0, "orderDate": "2023-02-15T05:45:03.653+00:00"}, {"condition": "Near Mint", "variant": "Foil", "language": "English", "quantity": 2, "title": "Silver Scrutiny (Extended Art)", "listingType": "ListingWithoutPhotos", "customListingId": "", "purchasePrice": 0.47, "shippingPrice": 0.0, "orderDate": "2023-02-15T05:45:03.64+00:00"}, {"condition": "Near Mint", "variant": "Foil", "language": "English", "quantity": 1, "title": "Silver Scrutiny (Extended Art)", "listingType": "ListingWithoutPhotos", "customListingId": "", "purchasePrice": 0.4, "shippingPrice": 0.0, "orderDate": "2023-02-15T05:45:03.623+00:00"}, {"condition": "Near Mint", "variant": "Normal", "language": "English", "quantity": 1, "title": "Silver Scrutiny (Extended Art)", "listingType": "ListingWithoutPhotos", "customListingId": "", "purchasePrice": 0.35, "shippingPrice": 0.0, "orderDate": "2023-02-14T23:43:59.08+00:00"}, {"condition": "Near Mint", "variant": "Foil", "language": "English", "quantity": 1, "title": "Silver Scrutiny (Extended Art)", "listingType": "ListingWithoutPhotos", "customListingId": "", "purchasePrice": 0.39, "shippingPrice": 0.0, "orderDate": "2023-02-14T21:40:52.733+00:00"}, {"condition": "Near Mint", "variant": "Normal", "language": "English", "quantity": 1, "title": "Silver Scrutiny (Extended Art)", "listingType": "ListingWithoutPhotos", "customListingId": "", "purchasePrice": 0.35, "shippingPrice": 0.0, "orderDate": "2023-02-13T22:22:19.61+00:00"}, {"condition": "Near Mint", "variant": "Normal", "language": "English", "quantity": 1, "title": "Silver Scrutiny (Extended Art)", "listingType": "ListingWithoutPhotos", "customListingId": "", "purchasePrice": 0.34, "shippingPrice": 0.0, "orderDate": "2023-02-13T05:57:10.3+00:00"}, {"condition": "Near Mint", "variant": "Normal", "language": "English", "quantity": 1, "title": "Silver Scrutiny (Extended Art)", "listingType": "ListingWithoutPhotos", "customListingId": "", "purchasePrice": 0.19, "shippingPrice": 0.99, "orderDate": "2023-02-11T21:42:59.373+00:00"}, {"condition": "Near Mint", "variant": "Foil", "language": "English", "quantity": 1, "title": "Silver Scrutiny (Extended Art)", "listingType": "ListingWithoutPhotos", "customListingId": "", "purchasePrice": 0.39, "shippingPrice": 0.0, "orderDate": "2023-02-11T19:56:36.94+00:00"}, {"condition": "Near Mint", "variant": "Normal", "language": "English", "quantity": 1, "title": "Silver Scrutiny (Extended Art)", "listingType": "ListingWithoutPhotos", "customListingId": "", "purchasePrice": 0.34, "shippingPrice": 0.0, "orderDate": "2023-02-11T13:40:20.06+00:00"}, {"condition": "Near Mint", "variant": "Normal", "language": "English", "quantity": 1, "title": "Silver Scrutiny (Extended Art)", "listingType": "ListingWithoutPhotos", "customListingId": "", "purchasePrice": 0.35, "shippingPrice": 0.0, "orderDate": "2023-02-11T13:40:20.06+00:00"}, {"condition": "Near Mint", "variant": "Normal", "language": "English", "quantity": 1, "title": "Silver Scrutiny (Extended Art)", "listingType": "ListingWithoutPhotos", "customListingId": "", "purchasePrice": 0.39, "shippingPrice": 0.0, "orderDate": "2023-02-11T13:40:20.06+00:00"}, {"condition": "Near Mint", "variant": "Normal", "language": "English", "quantity": 1, "title": "Silver Scrutiny (Extended Art)", "listingType": "ListingWithoutPhotos", "customListingId": "", "purchasePrice": 0.34, "shippingPrice": 0.0, "orderDate": "2023-02-11T13:40:20.026+00:00"}, {"condition": "Lightly Played", "variant": "Foil", "language": "English", "quantity": 1, "title": "Silver Scrutiny (Extended Art)", "listingType": "ListingWithoutPhotos", "customListingId": "", "purchasePrice": 0.25, "shippingPrice": 0.0, "orderDate": "2023-02-11T08:07:18.063+00:00"}, {"condition": "Near Mint", "variant": "Foil", "language": "English", "quantity": 3, "title": "Silver Scrutiny (Extended Art)", "listingType": "ListingWithoutPhotos", "customListingId": "", "purchasePrice": 0.41, "shippingPrice": 0.99, "orderDate": "2023-02-11T03:08:26.923+00:00"}, {"condition": "Near Mint", "variant": "Normal", "language": "English", "quantity": 4, "title": "Silver Scrutiny (Extended Art)", "listingType": "ListingWithoutPhotos", "customListingId": "", "purchasePrice": 0.5, "shippingPrice": 0.99, "orderDate": "2023-02-11T00:15:35.3+00:00"}, {"condition": "Near Mint", "variant": "Foil", "language": "English", "quantity": 3, "title": "Silver Scrutiny (Extended Art)", "listingType": "ListingWithoutPhotos", "customListingId": "", "purchasePrice": 0.4, "shippingPrice": 0.99, "orderDate": "2023-02-10T23:28:52.033+00:00"}, {"condition": "Lightly Played", "variant": "Foil", "language": "English", "quantity": 4, "title": "Silver Scrutiny (Extended Art)", "listingType": "ListingWithoutPhotos", "customListingId": "", "purchasePrice": 0.5, "shippingPrice": 0.0, "orderDate": "2023-02-10T19:29:39.903+00:00"}, {"condition": "Near Mint", "variant": "Normal", "language": "English", "quantity": 1, "title": "Silver Scrutiny (Extended Art)", "listingType": "ListingWithoutPhotos", "customListingId": "", "purchasePrice": 0.35, "shippingPrice": 0.0, "orderDate": "2023-02-10T03:33:04.41+00:00"}, {"condition": "Near Mint", "variant": "Foil", "language": "English", "quantity": 1, "title": "Silver Scrutiny (Extended Art)", "listingType": "ListingWithoutPhotos", "customListingId": "", "purchasePrice": 0.45, "shippingPrice": 0.0, "orderDate": "2023-02-09T19:40:42.233+00:00"}, {"condition": "Near Mint", "variant": "Normal", "language": "English", "quantity": 1, "title": "Silver Scrutiny (Extended Art)", "listingType": "ListingWithoutPhotos", "customListingId": "", "purchasePrice": 0.34, "shippingPrice": 0.0, "orderDate": "2023-02-09T19:40:42.203+00:00"}, {"condition": "Near Mint", "variant": "Normal", "language": "English", "quantity": 2, "title": "Silver Scrutiny (Extended Art)", "listingType": "ListingWithoutPhotos", "customListingId": "", "purchasePrice": 0.18, "shippingPrice": 0.0, "orderDate": "2023-02-09T19:40:42.17+00:00"}, {"condition": "Near Mint", "variant": "Foil", "language": "English", "quantity": 2, "title": "Silver Scrutiny (Extended Art)", "listingType": "ListingWithoutPhotos", "customListingId": "", "purchasePrice": 0.42, "shippingPrice": 0.0, "orderDate": "2023-02-09T19:40:42.17+00:00"}, {"condition": "Near Mint", "variant": "Normal", "language": "English", "quantity": 1, "title": "Silver Scrutiny (Extended Art)", "listingType": "ListingWithoutPhotos", "customListingId": "", "purchasePrice": 0.18, "shippingPrice": 0.0, "orderDate": "2023-02-09T19:40:42.17+00:00"}, {"condition": "Near Mint", "variant": "Normal", "language": "English", "quantity": 1, "title": "Silver Scrutiny (Extended Art)", "listingType": "ListingWithoutPhotos", "customListingId": "", "purchasePrice": 0.18, "shippingPrice": 0.0, "orderDate": "2023-02-09T13:54:38.553+00:00"}, {"condition": "Near Mint", "variant": "Normal", "language": "English", "quantity": 1, "title": "Silver Scrutiny (Extended Art)", "listingType": "ListingWithoutPhotos", "customListingId": "", "purchasePrice": 0.54, "shippingPrice": 0.0, "orderDate": "2023-02-08T03:26:08.123+00:00"}, {"condition": "Near Mint", "variant": "Normal", "language": "English", "quantity": 1, "title": "Silver Scrutiny (Extended Art)", "listingType": "ListingWithoutPhotos", "customListingId": "", "purchasePrice": 0.19, "shippingPrice": 0.0, "orderDate": "2023-02-08T01:19:58.233+00:00"}, {"condition": "Near Mint", "variant": "Normal", "language": "English", "quantity": 2, "title": "Silver Scrutiny (Extended Art)", "listingType": "ListingWithoutPhotos", "customListingId": "", "purchasePrice": 0.19, "shippingPrice": 0.0, "orderDate": "2023-02-07T22:44:01.516+00:00"}, {"condition": "Near Mint", "variant": "Normal", "language": "English", "quantity": 1, "title": "Silver Scrutiny (Extended Art)", "listingType": "ListingWithoutPhotos", "customListingId": "", "purchasePrice": 0.39, "shippingPrice": 1.29, "orderDate": "2023-02-07T15:10:12.366+00:00"}, {"condition": "Near Mint", "variant": "Normal", "language": "English", "quantity": 1, "title": "Silver Scrutiny (Extended Art)", "listingType": "ListingWithoutPhotos", "customListingId": "", "purchasePrice": 0.19, "shippingPrice": 0.0, "orderDate": "2023-02-05T09:38:57.33+00:00"}, {"condition": "Near Mint", "variant": "Normal", "language": "English", "quantity": 1, "title": "Silver Scrutiny (Extended Art)", "listingType": "ListingWithoutPhotos", "customListingId": "", "purchasePrice": 0.5, "shippingPrice": 0.0, "orderDate": "2023-02-05T03:18:17.543+00:00"}, {"condition": "Near Mint", "variant": "Foil", "language": "English", "quantity": 1, "title": "Silver Scrutiny (Extended Art)", "listingType": "ListingWithoutPhotos", "customListingId": "", "purchasePrice": 0.5, "shippingPrice": 0.0, "orderDate": "2023-02-04T22:58:50+00:00"}, {"condition": "Near Mint", "variant": "Foil", "language": "English", "quantity": 1, "title": "Silver Scrutiny (Extended Art)", "listingType": "ListingWithoutPhotos", "customListingId": "", "purchasePrice": 0.46, "shippingPrice": 0.0, "orderDate": "2023-02-04T03:56:54.71+00:00"}, {"condition": "Near Mint", "variant": "Foil", "language": "English", "quantity": 1, "title": "Silver Scrutiny (Extended Art)", "listingType": "ListingWithoutPhotos", "customListingId": "", "purchasePrice": 0.49, "shippingPrice": 0.99, "orderDate": "2023-02-03T21:33:16.306+00:00"}, {"condition": "Near Mint", "variant": "Normal", "language": "English", "quantity": 1, "title": "Silver Scrutiny (Extended Art)", "listingType": "ListingWithoutPhotos", "customListingId": "", "purchasePrice": 0.49, "shippingPrice": 0.99, "orderDate": "2023-02-03T19:23:05.283+00:00"}, {"condition": "Near Mint", "variant": "Foil", "language": "English", "quantity": 2, "title": "Silver Scrutiny (Extended Art)", "listingType": "ListingWithoutPhotos", "customListingId": "", "purchasePrice": 0.3, "shippingPrice": 0.99, "orderDate": "2023-02-03T19:14:54.526+00:00"}, {"condition": "Near Mint", "variant": "Foil", "language": "English", "quantity": 1, "title": "Silver Scrutiny (Extended Art)", "listingType": "ListingWithoutPhotos", "customListingId": "", "purchasePrice": 0.44, "shippingPrice": 0.0, "orderDate": "2023-02-03T19:14:54.416+00:00"}, {"condition": "Near Mint", "variant": "Foil", "language": "English", "quantity": 1, "title": "Silver Scrutiny (Extended Art)", "listingType": "ListingWithoutPhotos", "customListingId": "", "purchasePrice": 0.3, "shippingPrice": 0.99, "orderDate": "2023-01-30T02:43:14.123+00:00"}, {"condition": "Near Mint", "variant": "Foil", "language": "English", "quantity": 1, "title": "Silver Scrutiny (Extended Art)", "listingType": "ListingWithoutPhotos", "customListingId": "", "purchasePrice": 0.46, "shippingPrice": 0.0, "orderDate": "2023-01-29T19:13:48.836+00:00"}, {"condition": "Near Mint", "variant": "Normal", "language": "English", "quantity": 1, "title": "Silver Scrutiny (Extended Art)", "listingType": "ListingWithoutPhotos", "customListingId": "", "purchasePrice": 0.52, "shippingPrice": 0.0, "orderDate": "2023-01-28T23:42:33.723+00:00"}, {"condition": "Near Mint", "variant": "Foil", "language": "English", "quantity": 1, "title": "Silver Scrutiny (Extended Art)", "listingType": "ListingWithoutPhotos", "customListingId": "", "purchasePrice": 0.5, "shippingPrice": 1.25, "orderDate": "2023-01-25T03:41:26.35+00:00"}, {"condition": "Near Mint", "variant": "Foil", "language": "English", "quantity": 1, "title": "Silver Scrutiny (Extended Art)", "listingType": "ListingWithoutPhotos", "customListingId": "", "purchasePrice": 0.55, "shippingPrice": 0.0, "orderDate": "2023-01-24T22:57:18.356+00:00"}, {"condition": "Near Mint", "variant": "Normal", "language": "English", "quantity": 1, "title": "Silver Scrutiny (Extended Art)", "listingType": "ListingWithoutPhotos", "customListingId": "", "purchasePrice": 0.56, "shippingPrice": 0.0, "orderDate": "2023-01-24T18:48:19.103+00:00"}, {"condition": "Lightly Played", "variant": "Foil", "language": "English", "quantity": 2, "title": "Silver Scrutiny (Extended Art)", "listingType": "ListingWithoutPhotos", "customListingId": "", "purchasePrice": 0.28, "shippingPrice": 0.99, "orderDate": "2023-01-23T18:10:32.28+00:00"}, {"condition": "Near Mint", "variant": "Normal", "language": "English", "quantity": 1, "title": "Silver Scrutiny (Extended Art)", "listingType": "ListingWithoutPhotos", "customListingId": "", "purchasePrice": 0.26, "shippingPrice": 0.0, "orderDate": "2023-01-23T18:10:32.22+00:00"}, {"condition": "Near Mint", "variant": "Normal", "language": "English", "quantity": 1, "title": "Silver Scrutiny (Extended Art)", "listingType": "ListingWithoutPhotos", "customListingId": "", "purchasePrice": 0.45, "shippingPrice": 1.05, "orderDate": "2023-01-23T18:10:32.203+00:00"}, {"condition": "Near Mint", "variant": "Normal", "language": "English", "quantity": 2, "title": "Silver Scrutiny (Extended Art)", "listingType": "ListingWithoutPhotos", "customListingId": "", "purchasePrice": 0.3, "shippingPrice": 0.0, "orderDate": "2023-01-23T16:51:42.973+00:00"}, {"condition": "Near Mint", "variant": "Normal", "language": "English", "quantity": 3, "title": "Silver Scrutiny (Extended Art)", "listingType": "ListingWithoutPhotos", "customListingId": "", "purchasePrice": 0.26, "shippingPrice": 0.0, "orderDate": "2023-01-23T14:09:04.93+00:00"}, {"condition": "Near Mint", "variant": "Normal", "language": "English", "quantity": 1, "title": "Silver Scrutiny (Extended Art)", "listingType": "ListingWithoutPhotos", "customListingId": "", "purchasePrice": 0.26, "shippingPrice": 0.0, "orderDate": "2023-01-23T03:08:13.096+00:00"}, {"condition": "Lightly Played", "variant": "Foil", "language": "English", "quantity": 1, "title": "Silver Scrutiny (Extended Art)", "listingType": "ListingWithoutPhotos", "customListingId": "", "purchasePrice": 0.28, "shippingPrice": 0.0, "orderDate": "2023-01-23T00:23:03.956+00:00"}, {"condition": "Near Mint", "variant": "Foil", "language": "English", "quantity": 1, "title": "Silver Scrutiny (Extended Art)", "listingType": "ListingWithoutPhotos", "customListingId": "", "purchasePrice": 0.51, "shippingPrice": 0.0, "orderDate": "2023-01-21T22:23:54.21+00:00"}, {"condition": "Near Mint", "variant": "Foil", "language": "English", "quantity": 1, "title": "Silver Scrutiny (Extended Art)", "listingType": "ListingWithoutPhotos", "customListingId": "", "purchasePrice": 0.5, "shippingPrice": 0.0, "orderDate": "2023-01-21T19:51:45.93+00:00"}, {"condition": "Near Mint", "variant": "Normal", "language": "English", "quantity": 1, "title": "Silver Scrutiny (Extended Art)", "listingType": "ListingWithoutPhotos", "customListingId": "", "purchasePrice": 0.65, "shippingPrice": 0.0, "orderDate": "2023-01-21T03:25:12.193+00:00"}, {"condition": "Near Mint", "variant": "Normal", "language": "English", "quantity": 1, "title": "Silver Scrutiny (Extended Art)", "listingType": "ListingWithoutPhotos", "customListingId": "", "purchasePrice": 0.19, "shippingPrice": 0.99, "orderDate": "2023-01-20T21:06:45.473+00:00"}, {"condition": "Near Mint", "variant": "Foil", "language": "English", "quantity": 1, "title": "Silver Scrutiny (Extended Art)", "listingType": "ListingWithoutPhotos", "customListingId": "", "purchasePrice": 0.12, "shippingPrice": 0.99, "orderDate": "2023-01-20T21:06:45.023+00:00"}, {"condition": "Near Mint", "variant": "Foil", "language": "English", "quantity": 1, "title": "Silver Scrutiny (Extended Art)", "listingType": "ListingWithoutPhotos", "customListingId": "", "purchasePrice": 0.62, "shippingPrice": 0.0, "orderDate": "2023-01-20T05:42:30.443+00:00"}, {"condition": "Near Mint", "variant": "Foil", "language": "English", "quantity": 1, "title": "Silver Scrutiny (Extended Art)", "listingType": "ListingWithoutPhotos", "customListingId": "", "purchasePrice": 0.17, "shippingPrice": 0.0, "orderDate": "2023-01-19T06:04:21.333+00:00"}, {"condition": "Near Mint", "variant": "Foil", "language": "English", "quantity": 1, "title": "Silver Scrutiny (Extended Art)", "listingType": "ListingWithoutPhotos", "customListingId": "", "purchasePrice": 0.17, "shippingPrice": 0.0, "orderDate": "2023-01-19T06:01:49.003+00:00"}, {"condition": "Near Mint", "variant": "Foil", "language": "English", "quantity": 1, "title": "Silver Scrutiny (Extended Art)", "listingType": "ListingWithoutPhotos", "customListingId": "", "purchasePrice": 0.15, "shippingPrice": 0.0, "orderDate": "2023-01-19T02:40:41.093+00:00"}, {"condition": "Near Mint", "variant": "Normal", "language": "English", "quantity": 1, "title": "Silver Scrutiny (Extended Art)", "listingType": "ListingWithoutPhotos", "customListingId": "", "purchasePrice": 0.19, "shippingPrice": 0.99, "orderDate": "2023-01-18T09:31:19.356+00:00"}, {"condition": "Lightly Played", "variant": "Foil", "language": "English", "quantity": 1, "title": "Silver Scrutiny (Extended Art)", "listingType": "ListingWithoutPhotos", "customListingId": "", "purchasePrice": 0.5, "shippingPrice": 0.0, "orderDate": "2023-01-16T00:07:47.23+00:00"}, {"condition": "Near Mint", "variant": "Foil", "language": "English", "quantity": 1, "title": "Silver Scrutiny (Extended Art)", "listingType": "ListingWithoutPhotos", "customListingId": "", "purchasePrice": 0.49, "shippingPrice": 0.0, "orderDate": "2023-01-15T20:28:31.3+00:00"}, {"condition": "Lightly Played", "variant": "Normal", "language": "English", "quantity": 1, "title": "Silver Scrutiny (Extended Art)", "listingType": "ListingWithoutPhotos", "customListingId": "", "purchasePrice": 0.41, "shippingPrice": 0.0, "orderDate": "2023-01-15T19:41:44.646+00:00"}, {"condition": "Near Mint", "variant": "Normal", "language": "English", "quantity": 3, "title": "Silver Scrutiny (Extended Art)", "listingType": "ListingWithoutPhotos", "customListingId": "", "purchasePrice": 0.47, "shippingPrice": 0.99, "orderDate": "2023-01-14T04:48:10.803+00:00"}, {"condition": "Near Mint", "variant": "Normal", "language": "English", "quantity": 1, "title": "Silver Scrutiny (Extended Art)", "listingType": "ListingWithoutPhotos", "customListingId": "", "purchasePrice": 0.47, "shippingPrice": 0.99, "orderDate": "2023-01-13T15:42:52.096+00:00"}, {"condition": "Near Mint", "variant": "Foil", "language": "English", "quantity": 1, "title": "Silver Scrutiny (Extended Art)", "listingType": "ListingWithoutPhotos", "customListingId": "", "purchasePrice": 0.36, "shippingPrice": 0.99, "orderDate": "2023-01-13T14:53:38.39+00:00"}, {"condition": "Lightly Played", "variant": "Normal", "language": "English", "quantity": 1, "title": "Silver Scrutiny (Extended Art)", "listingType": "ListingWithoutPhotos", "customListingId": "", "purchasePrice": 0.4, "shippingPrice": 0.0, "orderDate": "2023-01-12T23:35:00.466+00:00"}, {"condition": "Near Mint", "variant": "Foil", "language": "English", "quantity": 1, "title": "Silver Scrutiny (Extended Art)", "listingType": "ListingWithoutPhotos", "customListingId": "", "purchasePrice": 0.3, "shippingPrice": 0.0, "orderDate": "2023-01-12T19:15:05.03+00:00"}, {"condition": "Near Mint", "variant": "Normal", "language": "English", "quantity": 2, "title": "Silver Scrutiny (Extended Art)", "listingType": "ListingWithoutPhotos", "customListingId": "", "purchasePrice": 0.18, "shippingPrice": 1.0, "orderDate": "2023-01-12T08:54:53.683+00:00"}, {"condition": "Near Mint", "variant": "Foil", "language": "English", "quantity": 1, "title": "Silver Scrutiny (Extended Art)", "listingType": "ListingWithoutPhotos", "customListingId": "", "purchasePrice": 0.49, "shippingPrice": 0.0, "orderDate": "2023-01-11T23:25:03.41+00:00"}, {"condition": "Near Mint", "variant": "Foil", "language": "English", "quantity": 2, "title": "Silver Scrutiny (Extended Art)", "listingType": "ListingWithoutPhotos", "customListingId": "", "purchasePrice": 0.49, "shippingPrice": 0.0, "orderDate": "2023-01-11T10:24:13.46+00:00"}, {"condition": "Near Mint", "variant": "Foil", "language": "English", "quantity": 1, "title": "Silver Scrutiny (Extended Art)", "listingType": "ListingWithoutPhotos", "customListingId": "", "purchasePrice": 0.46, "shippingPrice": 0.99, "orderDate": "2023-01-11T10:24:12.85+00:00"}, {"condition": "Near Mint", "variant": "Normal", "language": "English", "quantity": 1, "title": "Silver Scrutiny (Extended Art)", "listingType": "ListingWithoutPhotos", "customListingId": "", "purchasePrice": 0.85, "shippingPrice": 0.0, "orderDate": "2023-01-11T04:47:44.156+00:00"}, {"condition": "Near Mint", "variant": "Foil", "language": "English", "quantity": 1, "title": "Silver Scrutiny (Extended Art)", "listingType": "ListingWithoutPhotos", "customListingId": "", "purchasePrice": 0.47, "shippingPrice": 0.0, "orderDate": "2023-01-11T02:54:34.333+00:00"}, {"condition": "Near Mint", "variant": "Normal", "language": "English", "quantity": 3, "title": "Silver Scrutiny (Extended Art)", "listingType": "ListingWithoutPhotos", "customListingId": "", "purchasePrice": 0.65, "shippingPrice": 0.0, "orderDate": "2023-01-09T05:21:33.883+00:00"}, {"condition": "Near Mint", "variant": "Normal", "language": "English", "quantity": 1, "title": "Silver Scrutiny (Extended Art)", "listingType": "ListingWithoutPhotos", "customListingId": "", "purchasePrice": 0.6, "shippingPrice": 0.0, "orderDate": "2023-01-07T16:09:33.02+00:00"}, {"condition": "Near Mint", "variant": "Normal", "language": "English", "quantity": 1, "title": "Silver Scrutiny (Extended Art)", "listingType": "ListingWithoutPhotos", "customListingId": "", "purchasePrice": 0.49, "shippingPrice": 0.99, "orderDate": "2023-01-07T11:21:11.43+00:00"}, {"condition": "Near Mint", "variant": "Normal", "language": "English", "quantity": 1, "title": "Silver Scrutiny (Extended Art)", "listingType": "ListingWithoutPhotos", "customListingId": "", "purchasePrice": 0.5, "shippingPrice": 0.0, "orderDate": "2023-01-07T11:21:11.41+00:00"}, {"condition": "Near Mint", "variant": "Normal", "language": "English", "quantity": 2, "title": "Silver Scrutiny (Extended Art)", "listingType": "ListingWithoutPhotos", "customListingId": "", "purchasePrice": 0.42, "shippingPrice": 0.99, "orderDate": "2023-01-07T11:21:11.36+00:00"}, {"condition": "Lightly Played", "variant": "Foil", "language": "English", "quantity": 1, "title": "Silver Scrutiny (Extended Art)", "listingType": "ListingWithoutPhotos", "customListingId": "", "purchasePrice": 0.24, "shippingPrice": 0.0, "orderDate": "2023-01-07T09:08:30.38+00:00"}, {"condition": "Near Mint", "variant": "Normal", "language": "English", "quantity": 1, "title": "Silver Scrutiny (Extended Art)", "listingType": "ListingWithoutPhotos", "customListingId": "", "purchasePrice": 1.17, "shippingPrice": 0.0, "orderDate": "2023-01-06T21:14:54.013+00:00"}, {"condition": "Near Mint", "variant": "Normal", "language": "English", "quantity": 1, "title": "Silver Scrutiny (Extended Art)", "listingType": "ListingWithoutPhotos", "customListingId": "", "purchasePrice": 0.54, "shippingPrice": 0.0, "orderDate": "2023-01-06T21:14:53.84+00:00"}, {"condition": "Near Mint", "variant": "Foil", "language": "English", "quantity": 1, "title": "Silver Scrutiny (Extended Art)", "listingType": "ListingWithoutPhotos", "customListingId": "", "purchasePrice": 0.35, "shippingPrice": 0.0, "orderDate": "2023-01-06T15:02:41.46+00:00"}, {"condition": "Near Mint", "variant": "Normal", "language": "English", "quantity": 2, "title": "Silver Scrutiny (Extended Art)", "listingType": "ListingWithoutPhotos", "customListingId": "", "purchasePrice": 0.49, "shippingPrice": 0.99, "orderDate": "2023-01-05T11:49:22.513+00:00"}, {"condition": "Near Mint", "variant": "Normal", "language": "English", "quantity": 1, "title": "Silver Scrutiny (Extended Art)", "listingType": "ListingWithoutPhotos", "customListingId": "", "purchasePrice": 0.54, "shippingPrice": 0.0, "orderDate": "2023-01-05T00:20:14.86+00:00"}, {"condition": "Near Mint", "variant": "Normal", "language": "English", "quantity": 1, "title": "Silver Scrutiny (Extended Art)", "listingType": "ListingWithoutPhotos", "customListingId": "", "purchasePrice": 0.54, "shippingPrice": 0.0, "orderDate": "2023-01-04T21:07:05.553+00:00"}, {"condition": "Near Mint", "variant": "Foil", "language": "English", "quantity": 1, "title": "Silver Scrutiny (Extended Art)", "listingType": "ListingWithoutPhotos", "customListingId": "", "purchasePrice": 0.62, "shippingPrice": 0.0, "orderDate": "2023-01-04T09:56:59.51+00:00"}, {"condition": "Near Mint", "variant": "Normal", "language": "English", "quantity": 1, "title": "Silver Scrutiny (Extended Art)", "listingType": "ListingWithoutPhotos", "customListingId": "", "purchasePrice": 0.3, "shippingPrice": 0.0, "orderDate": "2023-01-03T22:23:15.753+00:00"}, {"condition": "Lightly Played", "variant": "Normal", "language": "English", "quantity": 1, "title": "Silver Scrutiny (Extended Art)", "listingType": "ListingWithoutPhotos", "customListingId": "", "purchasePrice": 0.5, "shippingPrice": 0.0, "orderDate": "2023-01-03T03:37:36.176+00:00"}, {"condition": "Near Mint", "variant": "Normal", "language": "English", "quantity": 1, "title": "Silver Scrutiny (Extended Art)", "listingType": "ListingWithoutPhotos", "customListingId": "", "purchasePrice": 0.54, "shippingPrice": 0.0, "orderDate": "2023-01-02T04:39:37.953+00:00"}, {"condition": "Near Mint", "variant": "Normal", "language": "English", "quantity": 1, "title": "Silver Scrutiny (Extended Art)", "listingType": "ListingWithoutPhotos", "customListingId": "", "purchasePrice": 0.42, "shippingPrice": 0.99, "orderDate": "2023-01-01T23:39:15.02+00:00"}, {"condition": "Near Mint", "variant": "Normal", "language": "English", "quantity": 1, "title": "Silver Scrutiny (Extended Art)", "listingType": "ListingWithoutPhotos", "customListingId": "", "purchasePrice": 0.51, "shippingPrice": 0.0, "orderDate": "2022-12-31T22:04:42.52+00:00"}, {"condition": "Near Mint", "variant": "Normal", "language": "English", "quantity": 1, "title": "Silver Scrutiny (Extended Art)", "listingType": "ListingWithoutPhotos", "customListingId": "", "purchasePrice": 0.51, "shippingPrice": 0.0, "orderDate": "2022-12-31T00:49:51.973+00:00"}, {"condition": "Near Mint", "variant": "Normal", "language": "English", "quantity": 1, "title": "Silver Scrutiny (Extended Art)", "listingType": "ListingWithoutPhotos", "customListingId": "", "purchasePrice": 0.5, "shippingPrice": 0.0, "orderDate": "2022-12-30T09:39:54.48+00:00"}, {"condition": "Near Mint", "variant": "Normal", "language": "English", "quantity": 1, "title": "Silver Scrutiny (Extended Art)", "listingType": "ListingWithoutPhotos", "customListingId": "", "purchasePrice": 0.5, "shippingPrice": 0.0, "orderDate": "2022-12-29T19:45:24.35+00:00"}, {"condition": "Near Mint", "variant": "Normal", "language": "English", "quantity": 1, "title": "Silver Scrutiny (Extended Art)", "listingType": "ListingWithoutPhotos", "customListingId": "", "purchasePrice": 0.5, "shippingPrice": 0.0, "orderDate": "2022-12-29T19:45:24.35+00:00"}, {"condition": "Near Mint", "variant": "Normal", "language": "English", "quantity": 1, "title": "Silver Scrutiny (Extended Art)", "listingType": "ListingWithoutPhotos", "customListingId": "", "purchasePrice": 0.45, "shippingPrice": 0.0, "orderDate": "2022-12-29T19:45:24.333+00:00"}, {"condition": "Near Mint", "variant": "Foil", "language": "English", "quantity": 1, "title": "Silver Scrutiny (Extended Art)", "listingType": "ListingWithoutPhotos", "customListingId": "", "purchasePrice": 0.61, "shippingPrice": 0.0, "orderDate": "2022-12-29T15:02:58.933+00:00"}, {"condition": "Near Mint", "variant": "Normal", "language": "English", "quantity": 1, "title": "Silver Scrutiny (Extended Art)", "listingType": "ListingWithoutPhotos", "customListingId": "", "purchasePrice": 0.44, "shippingPrice": 0.0, "orderDate": "2022-12-29T15:02:58.903+00:00"}, {"condition": "Near Mint", "variant": "Normal", "language": "English", "quantity": 1, "title": "Silver Scrutiny (Extended Art)", "listingType": "ListingWithoutPhotos", "customListingId": "", "purchasePrice": 0.44, "shippingPrice": 0.0, "orderDate": "2022-12-28T18:52:18.916+00:00"}, {"condition": "Lightly Played", "variant": "Foil", "language": "English", "quantity": 1, "title": "Silver Scrutiny (Extended Art)", "listingType": "ListingWithoutPhotos", "customListingId": "", "purchasePrice": 0.24, "shippingPrice": 0.0, "orderDate": "2022-12-28T17:14:37.033+00:00"}, {"condition": "Lightly Played", "variant": "Foil", "language": "English", "quantity": 1, "title": "Silver Scrutiny (Extended Art)", "listingType": "ListingWithoutPhotos", "customListingId": "", "purchasePrice": 0.94, "shippingPrice": 1.2, "orderDate": "2022-12-27T22:51:09.383+00:00"}, {"condition": "Near Mint", "variant": "Normal", "language": "English", "quantity": 1, "title": "Silver Scrutiny (Extended Art)", "listingType": "ListingWithoutPhotos", "customListingId": "", "purchasePrice": 0.5, "shippingPrice": 0.0, "orderDate": "2022-12-27T18:19:22.013+00:00"}]