[{"condition": "Near Mint", "variant": "Normal", "language": "English", "quantity": 1, "title": "Thopter Architect", "listingType": "ListingWithoutPhotos", "customListingId": "", "purchasePrice": 0.01, "shippingPrice": 0.0, "orderDate": "2023-04-21T15:26:16.436+00:00"}, {"condition": "Near Mint", "variant": "Normal", "language": "English", "quantity": 2, "title": "Thopter Architect", "listingType": "ListingWithoutPhotos", "customListingId": "", "purchasePrice": 0.01, "shippingPrice": 0.0, "orderDate": "2023-04-19T02:48:21.663+00:00"}, {"condition": "Near Mint", "variant": "Normal", "language": "English", "quantity": 1, "title": "Thopter Architect", "listingType": "ListingWithoutPhotos", "customListingId": "", "purchasePrice": 0.01, "shippingPrice": 1.99, "orderDate": "2023-04-15T12:36:23.18+00:00"}, {"condition": "Near Mint", "variant": "Normal", "language": "English", "quantity": 1, "title": "Thopter Architect", "listingType": "ListingWithoutPhotos", "customListingId": "", "purchasePrice": 0.02, "shippingPrice": 0.0, "orderDate": "2023-04-13T23:45:08.226+00:00"}, {"condition": "Near Mint", "variant": "Normal", "language": "English", "quantity": 1, "title": "Thopter Architect", "listingType": "ListingWithoutPhotos", "customListingId": "", "purchasePrice": 0.01, "shippingPrice": 0.0, "orderDate": "2023-04-13T03:35:34.123+00:00"}, {"condition": "Near Mint", "variant": "Foil", "language": "English", "quantity": 1, "title": "Thopter Architect", "listingType": "ListingWithoutPhotos", "customListingId": "", "purchasePrice": 0.04, "shippingPrice": 0.0, "orderDate": "2023-04-12T12:10:29.993+00:00"}, {"condition": "Near Mint", "variant": "Foil", "language": "English", "quantity": 1, "title": "Thopter Architect", "listingType": "ListingWithoutPhotos", "customListingId": "", "purchasePrice": 0.03, "shippingPrice": 0.0, "orderDate": "2023-04-12T12:10:29.993+00:00"}, {"condition": "Near Mint", "variant": "Normal", "language": "English", "quantity": 1, "title": "Thopter Architect", "listingType": "ListingWithoutPhotos", "customListingId": "", "purchasePrice": 0.01, "shippingPrice": 0.0, "orderDate": "2023-04-10T22:11:08.733+00:00"}, {"condition": "Near Mint", "variant": "Foil", "language": "English", "quantity": 1, "title": "Thopter Architect", "listingType": "ListingWithoutPhotos", "customListingId": "", "purchasePrice": 0.05, "shippingPrice": 2.09, "orderDate": "2023-04-05T02:17:01.61+00:00"}, {"condition": "Near Mint", "variant": "Normal", "language": "English", "quantity": 1, "title": "Thopter Architect", "listingType": "ListingWithoutPhotos", "customListingId": "", "purchasePrice": 0.01, "shippingPrice": 0.0, "orderDate": "2023-04-04T04:23:15.483+00:00"}, {"condition": "Near Mint", "variant": "Normal", "language": "English", "quantity": 1, "title": "Thopter Architect", "listingType": "ListingWithoutPhotos", "customListingId": "", "purchasePrice": 0.01, "shippingPrice": 0.0, "orderDate": "2023-04-02T17:16:39.416+00:00"}, {"condition": "Near Mint", "variant": "Normal", "language": "English", "quantity": 2, "title": "Thopter Architect", "listingType": "ListingWithoutPhotos", "customListingId": "", "purchasePrice": 0.01, "shippingPrice": 0.99, "orderDate": "2023-04-02T16:22:07.646+00:00"}, {"condition": "Near Mint", "variant": "Normal", "language": "English", "quantity": 1, "title": "Thopter Architect", "listingType": "ListingWithoutPhotos", "customListingId": "", "purchasePrice": 0.01, "shippingPrice": 0.0, "orderDate": "2023-03-31T04:27:55.046+00:00"}, {"condition": "Near Mint", "variant": "Normal", "language": "English", "quantity": 1, "title": "Thopter Architect", "listingType": "ListingWithoutPhotos", "customListingId": "", "purchasePrice": 0.14, "shippingPrice": 0.0, "orderDate": "2023-03-28T02:57:34.47+00:00"}, {"condition": "Near Mint", "variant": "Normal", "language": "English", "quantity": 1, "title": "Thopter Architect", "listingType": "ListingWithoutPhotos", "customListingId": "", "purchasePrice": 0.01, "shippingPrice": 0.0, "orderDate": "2023-03-27T22:24:12.436+00:00"}, {"condition": "Near Mint", "variant": "Normal", "language": "English", "quantity": 1, "title": "Thopter Architect", "listingType": "ListingWithoutPhotos", "customListingId": "", "purchasePrice": 0.01, "shippingPrice": 0.0, "orderDate": "2023-03-26T01:44:45.166+00:00"}, {"condition": "Near Mint", "variant": "Normal", "language": "English", "quantity": 1, "title": "Thopter Architect", "listingType": "ListingWithoutPhotos", "customListingId": "", "purchasePrice": 0.01, "shippingPrice": 0.0, "orderDate": "2023-03-25T18:34:08.456+00:00"}, {"condition": "Near Mint", "variant": "Normal", "language": "English", "quantity": 1, "title": "Thopter Architect", "listingType": "ListingWithoutPhotos", "customListingId": "", "purchasePrice": 0.01, "shippingPrice": 0.0, "orderDate": "2023-03-24T05:09:58.88+00:00"}, {"condition": "Lightly Played", "variant": "Foil", "language": "English", "quantity": 1, "title": "Thopter Architect", "listingType": "ListingWithoutPhotos", "customListingId": "", "purchasePrice": 0.05, "shippingPrice": 8.99, "orderDate": "2023-03-23T16:03:08.973+00:00"}, {"condition": "Near Mint", "variant": "Normal", "language": "English", "quantity": 4, "title": "Thopter Architect", "listingType": "ListingWithoutPhotos", "customListingId": "", "purchasePrice": 0.02, "shippingPrice": 0.0, "orderDate": "2023-03-23T02:50:38.106+00:00"}, {"condition": "Near Mint", "variant": "Foil", "language": "English", "quantity": 1, "title": "Thopter Architect", "listingType": "ListingWithoutPhotos", "customListingId": "", "purchasePrice": 0.06, "shippingPrice": 0.0, "orderDate": "2023-03-20T12:08:42.1+00:00"}, {"condition": "Near Mint", "variant": "Normal", "language": "English", "quantity": 1, "title": "Thopter Architect", "listingType": "ListingWithoutPhotos", "customListingId": "", "purchasePrice": 0.04, "shippingPrice": 1.04, "orderDate": "2023-03-20T07:18:38.06+00:00"}, {"condition": "Near Mint", "variant": "Foil", "language": "English", "quantity": 1, "title": "Thopter Architect", "listingType": "ListingWithoutPhotos", "customListingId": "", "purchasePrice": 0.01, "shippingPrice": 0.0, "orderDate": "2023-03-19T23:55:19.98+00:00"}, {"condition": "Near Mint", "variant": "Normal", "language": "English", "quantity": 2, "title": "Thopter Architect", "listingType": "ListingWithoutPhotos", "customListingId": "", "purchasePrice": 0.05, "shippingPrice": 0.0, "orderDate": "2023-03-15T21:55:49.063+00:00"}, {"condition": "Near Mint", "variant": "Normal", "language": "English", "quantity": 1, "title": "Thopter Architect", "listingType": "ListingWithoutPhotos", "customListingId": "", "purchasePrice": 0.03, "shippingPrice": 0.99, "orderDate": "2023-03-15T05:22:59.06+00:00"}, {"condition": "Near Mint", "variant": "Normal", "language": "English", "quantity": 1, "title": "Thopter Architect", "listingType": "ListingWithoutPhotos", "customListingId": "", "purchasePrice": 0.01, "shippingPrice": 0.0, "orderDate": "2023-03-13T23:42:15.316+00:00"}, {"condition": "Near Mint", "variant": "Normal", "language": "English", "quantity": 1, "title": "Thopter Architect", "listingType": "ListingWithoutPhotos", "customListingId": "", "purchasePrice": 0.01, "shippingPrice": 0.0, "orderDate": "2023-03-13T01:45:54.793+00:00"}, {"condition": "Near Mint", "variant": "Foil", "language": "English", "quantity": 2, "title": "Thopter Architect", "listingType": "ListingWithoutPhotos", "customListingId": "", "purchasePrice": 0.01, "shippingPrice": 0.0, "orderDate": "2023-03-12T06:51:05.236+00:00"}, {"condition": "Near Mint", "variant": "Normal", "language": "English", "quantity": 1, "title": "Thopter Architect", "listingType": "ListingWithoutPhotos", "customListingId": "", "purchasePrice": 0.01, "shippingPrice": 0.0, "orderDate": "2023-03-11T14:42:04.04+00:00"}, {"condition": "Near Mint", "variant": "Normal", "language": "English", "quantity": 1, "title": "Thopter Architect", "listingType": "ListingWithoutPhotos", "customListingId": "", "purchasePrice": 0.01, "shippingPrice": 0.0, "orderDate": "2023-03-08T19:24:32.95+00:00"}, {"condition": "Near Mint", "variant": "Normal", "language": "English", "quantity": 2, "title": "Thopter Architect", "listingType": "ListingWithoutPhotos", "customListingId": "", "purchasePrice": 0.06, "shippingPrice": 0.99, "orderDate": "2023-03-07T06:17:47.666+00:00"}, {"condition": "Near Mint", "variant": "Normal", "language": "English", "quantity": 1, "title": "Thopter Architect", "listingType": "ListingWithoutPhotos", "customListingId": "", "purchasePrice": 0.01, "shippingPrice": 0.0, "orderDate": "2023-03-07T03:47:32.053+00:00"}, {"condition": "Near Mint", "variant": "Foil", "language": "English", "quantity": 4, "title": "Thopter Architect", "listingType": "ListingWithoutPhotos", "customListingId": "", "purchasePrice": 0.04, "shippingPrice": 0.0, "orderDate": "2023-03-06T09:30:27.026+00:00"}, {"condition": "Near Mint", "variant": "Normal", "language": "English", "quantity": 1, "title": "Thopter Architect", "listingType": "ListingWithoutPhotos", "customListingId": "", "purchasePrice": 0.01, "shippingPrice": 0.0, "orderDate": "2023-03-04T18:29:12.243+00:00"}, {"condition": "Near Mint", "variant": "Normal", "language": "English", "quantity": 1, "title": "Thopter Architect", "listingType": "ListingWithoutPhotos", "customListingId": "", "purchasePrice": 0.01, "shippingPrice": 0.0, "orderDate": "2023-03-03T23:39:40.476+00:00"}, {"condition": "Near Mint", "variant": "Normal", "language": "English", "quantity": 1, "title": "Thopter Architect", "listingType": "ListingWithoutPhotos", "customListingId": "", "purchasePrice": 0.01, "shippingPrice": 1.99, "orderDate": "2023-03-01T19:16:04.6+00:00"}, {"condition": "Near Mint", "variant": "Normal", "language": "English", "quantity": 4, "title": "Thopter Architect", "listingType": "ListingWithoutPhotos", "customListingId": "", "purchasePrice": 0.01, "shippingPrice": 0.0, "orderDate": "2023-03-01T15:52:49.776+00:00"}, {"condition": "Near Mint", "variant": "Normal", "language": "English", "quantity": 1, "title": "Thopter Architect", "listingType": "ListingWithoutPhotos", "customListingId": "", "purchasePrice": 0.01, "shippingPrice": 0.0, "orderDate": "2023-03-01T13:51:43.223+00:00"}, {"condition": "Near Mint", "variant": "Normal", "language": "English", "quantity": 1, "title": "Thopter Architect", "listingType": "ListingWithoutPhotos", "customListingId": "", "purchasePrice": 0.01, "shippingPrice": 0.0, "orderDate": "2023-03-01T01:48:13.073+00:00"}, {"condition": "Near Mint", "variant": "Normal", "language": "English", "quantity": 1, "title": "Thopter Architect", "listingType": "ListingWithoutPhotos", "customListingId": "", "purchasePrice": 0.01, "shippingPrice": 0.0, "orderDate": "2023-03-01T00:17:31.646+00:00"}, {"condition": "Near Mint", "variant": "Foil", "language": "English", "quantity": 1, "title": "Thopter Architect", "listingType": "ListingWithoutPhotos", "customListingId": "", "purchasePrice": 0.01, "shippingPrice": 0.99, "orderDate": "2023-02-28T02:39:15.716+00:00"}, {"condition": "Near Mint", "variant": "Normal", "language": "English", "quantity": 1, "title": "Thopter Architect", "listingType": "ListingWithoutPhotos", "customListingId": "", "purchasePrice": 0.01, "shippingPrice": 0.0, "orderDate": "2023-02-27T02:07:59.726+00:00"}, {"condition": "Near Mint", "variant": "Normal", "language": "English", "quantity": 1, "title": "Thopter Architect", "listingType": "ListingWithoutPhotos", "customListingId": "", "purchasePrice": 0.01, "shippingPrice": 0.0, "orderDate": "2023-02-25T21:41:48.296+00:00"}, {"condition": "Lightly Played", "variant": "Normal", "language": "English", "quantity": 1, "title": "Thopter Architect", "listingType": "ListingWithoutPhotos", "customListingId": "", "purchasePrice": 0.01, "shippingPrice": 1.49, "orderDate": "2023-02-25T10:32:27.563+00:00"}, {"condition": "Near Mint", "variant": "Normal", "language": "English", "quantity": 1, "title": "Thopter Architect", "listingType": "ListingWithoutPhotos", "customListingId": "", "purchasePrice": 0.01, "shippingPrice": 0.0, "orderDate": "2023-02-25T04:07:25.42+00:00"}, {"condition": "Near Mint", "variant": "Normal", "language": "English", "quantity": 4, "title": "Thopter Architect", "listingType": "ListingWithoutPhotos", "customListingId": "", "purchasePrice": 0.01, "shippingPrice": 0.0, "orderDate": "2023-02-25T00:00:54.596+00:00"}, {"condition": "Near Mint", "variant": "Normal", "language": "English", "quantity": 2, "title": "Thopter Architect", "listingType": "ListingWithoutPhotos", "customListingId": "", "purchasePrice": 0.01, "shippingPrice": 0.0, "orderDate": "2023-02-24T05:39:05.97+00:00"}, {"condition": "Near Mint", "variant": "Normal", "language": "English", "quantity": 8, "title": "Thopter Architect", "listingType": "ListingWithoutPhotos", "customListingId": "", "purchasePrice": 0.02, "shippingPrice": 0.0, "orderDate": "2023-02-24T03:52:11.946+00:00"}, {"condition": "Near Mint", "variant": "Normal", "language": "English", "quantity": 1, "title": "Thopter Architect", "listingType": "ListingWithoutPhotos", "customListingId": "", "purchasePrice": 0.01, "shippingPrice": 0.0, "orderDate": "2023-02-23T07:18:19.686+00:00"}, {"condition": "Near Mint", "variant": "Foil", "language": "English", "quantity": 1, "title": "Thopter Architect", "listingType": "ListingWithoutPhotos", "customListingId": "", "purchasePrice": 0.01, "shippingPrice": 0.0, "orderDate": "2023-02-23T07:08:12.053+00:00"}, {"condition": "Near Mint", "variant": "Foil", "language": "English", "quantity": 1, "title": "Thopter Architect", "listingType": "ListingWithoutPhotos", "customListingId": "", "purchasePrice": 0.01, "shippingPrice": 0.0, "orderDate": "2023-02-23T02:58:20.706+00:00"}, {"condition": "Near Mint", "variant": "Normal", "language": "English", "quantity": 1, "title": "Thopter Architect", "listingType": "ListingWithoutPhotos", "customListingId": "", "purchasePrice": 0.01, "shippingPrice": 0.0, "orderDate": "2023-02-21T05:43:48.32+00:00"}, {"condition": "Near Mint", "variant": "Foil", "language": "English", "quantity": 2, "title": "Thopter Architect", "listingType": "ListingWithoutPhotos", "customListingId": "", "purchasePrice": 0.01, "shippingPrice": 0.0, "orderDate": "2023-02-21T03:07:48.6+00:00"}, {"condition": "Near Mint", "variant": "Foil", "language": "English", "quantity": 3, "title": "Thopter Architect", "listingType": "ListingWithoutPhotos", "customListingId": "", "purchasePrice": 0.01, "shippingPrice": 0.0, "orderDate": "2023-02-18T21:15:58.113+00:00"}, {"condition": "Near Mint", "variant": "Normal", "language": "English", "quantity": 3, "title": "Thopter Architect", "listingType": "ListingWithoutPhotos", "customListingId": "", "purchasePrice": 0.02, "shippingPrice": 0.0, "orderDate": "2023-02-18T15:43:03.983+00:00"}, {"condition": "Near Mint", "variant": "Normal", "language": "English", "quantity": 1, "title": "Thopter Architect", "listingType": "ListingWithoutPhotos", "customListingId": "", "purchasePrice": 0.01, "shippingPrice": 0.0, "orderDate": "2023-02-12T00:53:13.656+00:00"}, {"condition": "Near Mint", "variant": "Normal", "language": "English", "quantity": 2, "title": "Thopter Architect", "listingType": "ListingWithoutPhotos", "customListingId": "", "purchasePrice": 0.1, "shippingPrice": 0.0, "orderDate": "2023-02-11T17:33:04.133+00:00"}, {"condition": "Near Mint", "variant": "Normal", "language": "English", "quantity": 2, "title": "Thopter Architect", "listingType": "ListingWithoutPhotos", "customListingId": "", "purchasePrice": 0.01, "shippingPrice": 3.49, "orderDate": "2023-02-11T15:42:12.69+00:00"}, {"condition": "Near Mint", "variant": "Normal", "language": "English", "quantity": 1, "title": "Thopter Architect", "listingType": "ListingWithoutPhotos", "customListingId": "", "purchasePrice": 0.01, "shippingPrice": 0.0, "orderDate": "2023-02-10T05:49:58.046+00:00"}, {"condition": "Near Mint", "variant": "Normal", "language": "English", "quantity": 1, "title": "Thopter Architect", "listingType": "ListingWithoutPhotos", "customListingId": "", "purchasePrice": 0.02, "shippingPrice": 0.0, "orderDate": "2023-02-09T21:42:22.153+00:00"}, {"condition": "Near Mint", "variant": "Normal", "language": "English", "quantity": 2, "title": "Thopter Architect", "listingType": "ListingWithoutPhotos", "customListingId": "", "purchasePrice": 0.02, "shippingPrice": 0.0, "orderDate": "2023-02-09T00:26:48.403+00:00"}, {"condition": "Near Mint", "variant": "Normal", "language": "English", "quantity": 1, "title": "Thopter Architect", "listingType": "ListingWithoutPhotos", "customListingId": "", "purchasePrice": 0.02, "shippingPrice": 0.0, "orderDate": "2023-02-08T02:47:03.456+00:00"}, {"condition": "Near Mint", "variant": "Normal", "language": "English", "quantity": 1, "title": "Thopter Architect", "listingType": "ListingWithoutPhotos", "customListingId": "", "purchasePrice": 0.01, "shippingPrice": 0.0, "orderDate": "2023-02-08T01:17:13.91+00:00"}, {"condition": "Near Mint", "variant": "Normal", "language": "English", "quantity": 1, "title": "Thopter Architect", "listingType": "ListingWithoutPhotos", "customListingId": "", "purchasePrice": 0.01, "shippingPrice": 0.0, "orderDate": "2023-02-03T11:32:30.73+00:00"}, {"condition": "Near Mint", "variant": "Normal", "language": "English", "quantity": 1, "title": "Thopter Architect", "listingType": "ListingWithoutPhotos", "customListingId": "", "purchasePrice": 0.01, "shippingPrice": 0.0, "orderDate": "2023-02-01T06:32:33.76+00:00"}, {"condition": "Near Mint", "variant": "Normal", "language": "English", "quantity": 1, "title": "Thopter Architect", "listingType": "ListingWithoutPhotos", "customListingId": "", "purchasePrice": 0.02, "shippingPrice": 0.0, "orderDate": "2023-01-31T07:18:06.853+00:00"}, {"condition": "Near Mint", "variant": "Foil", "language": "English", "quantity": 1, "title": "Thopter Architect", "listingType": "ListingWithoutPhotos", "customListingId": "", "purchasePrice": 0.01, "shippingPrice": 0.0, "orderDate": "2023-01-30T17:33:58.286+00:00"}, {"condition": "Near Mint", "variant": "Normal", "language": "English", "quantity": 1, "title": "Thopter Architect", "listingType": "ListingWithoutPhotos", "customListingId": "", "purchasePrice": 0.01, "shippingPrice": 0.0, "orderDate": "2023-01-30T17:33:58.286+00:00"}, {"condition": "Near Mint", "variant": "Normal", "language": "English", "quantity": 2, "title": "Thopter Architect", "listingType": "ListingWithoutPhotos", "customListingId": "", "purchasePrice": 0.04, "shippingPrice": 1.59, "orderDate": "2023-01-30T08:53:49.19+00:00"}, {"condition": "Near Mint", "variant": "Normal", "language": "English", "quantity": 1, "title": "Thopter Architect", "listingType": "ListingWithoutPhotos", "customListingId": "", "purchasePrice": 0.01, "shippingPrice": 1.19, "orderDate": "2023-01-30T05:35:39.61+00:00"}, {"condition": "Near Mint", "variant": "Normal", "language": "English", "quantity": 1, "title": "Thopter Architect", "listingType": "ListingWithoutPhotos", "customListingId": "", "purchasePrice": 0.01, "shippingPrice": 0.99, "orderDate": "2023-01-28T18:27:28.92+00:00"}, {"condition": "Lightly Played", "variant": "Normal", "language": "English", "quantity": 1, "title": "Thopter Architect", "listingType": "ListingWithoutPhotos", "customListingId": "", "purchasePrice": 0.01, "shippingPrice": 0.0, "orderDate": "2023-01-27T00:43:26.39+00:00"}, {"condition": "Near Mint", "variant": "Normal", "language": "English", "quantity": 1, "title": "Thopter Architect", "listingType": "ListingWithoutPhotos", "customListingId": "", "purchasePrice": 0.01, "shippingPrice": 0.99, "orderDate": "2023-01-26T18:35:17.203+00:00"}, {"condition": "Near Mint", "variant": "Normal", "language": "English", "quantity": 1, "title": "Thopter Architect", "listingType": "ListingWithoutPhotos", "customListingId": "", "purchasePrice": 0.02, "shippingPrice": 0.99, "orderDate": "2023-01-25T07:35:13.713+00:00"}, {"condition": "Near Mint", "variant": "Normal", "language": "English", "quantity": 1, "title": "Thopter Architect", "listingType": "ListingWithoutPhotos", "customListingId": "", "purchasePrice": 0.1, "shippingPrice": 0.0, "orderDate": "2023-01-25T02:16:18.706+00:00"}, {"condition": "Near Mint", "variant": "Normal", "language": "English", "quantity": 1, "title": "Thopter Architect", "listingType": "ListingWithoutPhotos", "customListingId": "", "purchasePrice": 0.01, "shippingPrice": 0.99, "orderDate": "2023-01-24T05:48:11.716+00:00"}, {"condition": "Near Mint", "variant": "Foil", "language": "English", "quantity": 1, "title": "Thopter Architect", "listingType": "ListingWithoutPhotos", "customListingId": "", "purchasePrice": 0.1, "shippingPrice": 0.0, "orderDate": "2023-01-24T00:17:47.4+00:00"}, {"condition": "Near Mint", "variant": "Normal", "language": "English", "quantity": 2, "title": "Thopter Architect", "listingType": "ListingWithoutPhotos", "customListingId": "", "purchasePrice": 0.05, "shippingPrice": 0.0, "orderDate": "2023-01-22T02:32:28.833+00:00"}, {"condition": "Near Mint", "variant": "Normal", "language": "English", "quantity": 1, "title": "Thopter Architect", "listingType": "ListingWithoutPhotos", "customListingId": "", "purchasePrice": 0.02, "shippingPrice": 0.0, "orderDate": "2023-01-21T22:10:04.573+00:00"}, {"condition": "Near Mint", "variant": "Foil", "language": "English", "quantity": 1, "title": "Thopter Architect", "listingType": "ListingWithoutPhotos", "customListingId": "", "purchasePrice": 0.06, "shippingPrice": 0.0, "orderDate": "2023-01-19T21:10:37.82+00:00"}, {"condition": "Near Mint", "variant": "Normal", "language": "English", "quantity": 1, "title": "Thopter Architect", "listingType": "ListingWithoutPhotos", "customListingId": "", "purchasePrice": 0.02, "shippingPrice": 0.0, "orderDate": "2023-01-19T04:06:53.906+00:00"}, {"condition": "Near Mint", "variant": "Normal", "language": "English", "quantity": 1, "title": "Thopter Architect", "listingType": "ListingWithoutPhotos", "customListingId": "", "purchasePrice": 0.03, "shippingPrice": 0.0, "orderDate": "2023-01-15T16:45:09.616+00:00"}, {"condition": "Near Mint", "variant": "Normal", "language": "English", "quantity": 1, "title": "Thopter Architect", "listingType": "ListingWithPhotos", "customListingId": "BLmu9xHt8o41", "purchasePrice": 0.01, "shippingPrice": 0.0, "orderDate": "2023-01-12T16:52:04.243+00:00"}, {"condition": "Lightly Played", "variant": "Normal", "language": "English", "quantity": 2, "title": "Thopter Architect", "listingType": "ListingWithoutPhotos", "customListingId": "", "purchasePrice": 0.01, "shippingPrice": 0.99, "orderDate": "2023-01-08T22:23:51.8+00:00"}, {"condition": "Near Mint", "variant": "Normal", "language": "English", "quantity": 3, "title": "Thopter Architect", "listingType": "ListingWithoutPhotos", "customListingId": "", "purchasePrice": 0.02, "shippingPrice": 0.0, "orderDate": "2023-01-08T04:34:25.123+00:00"}, {"condition": "Near Mint", "variant": "Normal", "language": "English", "quantity": 1, "title": "Thopter Architect", "listingType": "ListingWithoutPhotos", "customListingId": "", "purchasePrice": 0.02, "shippingPrice": 1.99, "orderDate": "2023-01-08T04:34:24.776+00:00"}, {"condition": "Near Mint", "variant": "Normal", "language": "English", "quantity": 2, "title": "Thopter Architect", "listingType": "ListingWithoutPhotos", "customListingId": "", "purchasePrice": 0.01, "shippingPrice": 4.99, "orderDate": "2023-01-08T04:34:22.7+00:00"}, {"condition": "Near Mint", "variant": "Normal", "language": "English", "quantity": 1, "title": "Thopter Architect", "listingType": "ListingWithoutPhotos", "customListingId": "", "purchasePrice": 0.13, "shippingPrice": 0.0, "orderDate": "2023-01-06T03:58:04.833+00:00"}, {"condition": "Near Mint", "variant": "Normal", "language": "English", "quantity": 1, "title": "Thopter Architect", "listingType": "ListingWithoutPhotos", "customListingId": "", "purchasePrice": 0.02, "shippingPrice": 0.0, "orderDate": "2023-01-06T03:07:51.296+00:00"}, {"condition": "Near Mint", "variant": "Normal", "language": "English", "quantity": 1, "title": "Thopter Architect", "listingType": "ListingWithoutPhotos", "customListingId": "", "purchasePrice": 0.01, "shippingPrice": 0.0, "orderDate": "2023-01-04T15:38:43.106+00:00"}, {"condition": "Near Mint", "variant": "Normal", "language": "English", "quantity": 1, "title": "Thopter Architect", "listingType": "ListingWithoutPhotos", "customListingId": "", "purchasePrice": 0.05, "shippingPrice": 0.0, "orderDate": "2023-01-04T07:37:20.91+00:00"}, {"condition": "Near Mint", "variant": "Normal", "language": "English", "quantity": 1, "title": "Thopter Architect", "listingType": "ListingWithoutPhotos", "customListingId": "", "purchasePrice": 0.02, "shippingPrice": 0.0, "orderDate": "2023-01-03T04:08:40.04+00:00"}, {"condition": "Near Mint", "variant": "Foil", "language": "English", "quantity": 1, "title": "Thopter Architect", "listingType": "ListingWithoutPhotos", "customListingId": "", "purchasePrice": 0.04, "shippingPrice": 0.0, "orderDate": "2023-01-02T23:38:57.72+00:00"}, {"condition": "Near Mint", "variant": "Normal", "language": "English", "quantity": 1, "title": "Thopter Architect", "listingType": "ListingWithoutPhotos", "customListingId": "", "purchasePrice": 0.02, "shippingPrice": 0.0, "orderDate": "2023-01-01T22:29:15.206+00:00"}, {"condition": "Near Mint", "variant": "Foil", "language": "English", "quantity": 1, "title": "Thopter Architect", "listingType": "ListingWithoutPhotos", "customListingId": "", "purchasePrice": 0.04, "shippingPrice": 0.0, "orderDate": "2023-01-01T01:24:42.02+00:00"}, {"condition": "Near Mint", "variant": "Normal", "language": "English", "quantity": 1, "title": "Thopter Architect", "listingType": "ListingWithoutPhotos", "customListingId": "", "purchasePrice": 0.02, "shippingPrice": 0.0, "orderDate": "2022-12-31T14:10:29.093+00:00"}, {"condition": "Near Mint", "variant": "Foil", "language": "English", "quantity": 2, "title": "Thopter Architect", "listingType": "ListingWithoutPhotos", "customListingId": "", "purchasePrice": 0.04, "shippingPrice": 0.0, "orderDate": "2022-12-31T03:55:31.17+00:00"}, {"condition": "Near Mint", "variant": "Foil", "language": "English", "quantity": 1, "title": "Thopter Architect", "listingType": "ListingWithoutPhotos", "customListingId": "", "purchasePrice": 0.01, "shippingPrice": 0.99, "orderDate": "2022-12-31T03:55:31.14+00:00"}, {"condition": "Near Mint", "variant": "Foil", "language": "English", "quantity": 1, "title": "Thopter Architect", "listingType": "ListingWithoutPhotos", "customListingId": "", "purchasePrice": 0.01, "shippingPrice": 0.0, "orderDate": "2022-12-31T03:55:31.093+00:00"}, {"condition": "Near Mint", "variant": "Foil", "language": "English", "quantity": 1, "title": "Thopter Architect", "listingType": "ListingWithoutPhotos", "customListingId": "", "purchasePrice": 0.01, "shippingPrice": 0.78, "orderDate": "2022-12-31T01:36:20.3+00:00"}, {"condition": "Near Mint", "variant": "Foil", "language": "English", "quantity": 1, "title": "Thopter Architect", "listingType": "ListingWithoutPhotos", "customListingId": "", "purchasePrice": 0.01, "shippingPrice": 0.99, "orderDate": "2022-12-29T05:19:25.783+00:00"}]