[{"condition": "Near Mint", "variant": "Normal", "language": "English", "quantity": 1, "title": "Gilded Pinions", "listingType": "ListingWithoutPhotos", "customListingId": "", "purchasePrice": 0.05, "shippingPrice": 0.99, "orderDate": "2023-04-26T10:23:52.966+00:00"}, {"condition": "Near Mint", "variant": "Normal", "language": "English", "quantity": 4, "title": "Gilded Pinions", "listingType": "ListingWithoutPhotos", "customListingId": "", "purchasePrice": 0.05, "shippingPrice": 0.0, "orderDate": "2023-04-26T03:33:57.54+00:00"}, {"condition": "Lightly Played", "variant": "Normal", "language": "English", "quantity": 1, "title": "Gilded Pinions", "listingType": "ListingWithoutPhotos", "customListingId": "", "purchasePrice": 0.04, "shippingPrice": 0.0, "orderDate": "2023-04-26T03:33:57.523+00:00"}, {"condition": "Near Mint", "variant": "Normal", "language": "English", "quantity": 1, "title": "Gilded Pinions", "listingType": "ListingWithoutPhotos", "customListingId": "", "purchasePrice": 0.04, "shippingPrice": 0.0, "orderDate": "2023-04-25T21:39:40.986+00:00"}, {"condition": "Near Mint", "variant": "Normal", "language": "English", "quantity": 2, "title": "Gilded Pinions", "listingType": "ListingWithoutPhotos", "customListingId": "", "purchasePrice": 0.05, "shippingPrice": 0.0, "orderDate": "2023-04-25T06:03:51.88+00:00"}, {"condition": "Near Mint", "variant": "Normal", "language": "English", "quantity": 1, "title": "Gilded Pinions", "listingType": "ListingWithoutPhotos", "customListingId": "", "purchasePrice": 0.05, "shippingPrice": 0.0, "orderDate": "2023-04-24T21:48:19.036+00:00"}, {"condition": "Near Mint", "variant": "Normal", "language": "English", "quantity": 1, "title": "Gilded Pinions", "listingType": "ListingWithoutPhotos", "customListingId": "", "purchasePrice": 0.05, "shippingPrice": 0.0, "orderDate": "2023-04-24T18:32:03.226+00:00"}, {"condition": "Near Mint", "variant": "Normal", "language": "English", "quantity": 1, "title": "Gilded Pinions", "listingType": "ListingWithoutPhotos", "customListingId": "", "purchasePrice": 0.02, "shippingPrice": 0.99, "orderDate": "2023-04-24T17:50:50.33+00:00"}, {"condition": "Near Mint", "variant": "Foil", "language": "English", "quantity": 1, "title": "Gilded Pinions", "listingType": "ListingWithoutPhotos", "customListingId": "", "purchasePrice": 0.04, "shippingPrice": 0.0, "orderDate": "2023-04-24T14:00:00.363+00:00"}, {"condition": "Near Mint", "variant": "Normal", "language": "English", "quantity": 1, "title": "Gilded Pinions", "listingType": "ListingWithoutPhotos", "customListingId": "", "purchasePrice": 0.07, "shippingPrice": 3.99, "orderDate": "2023-04-23T17:59:51.566+00:00"}, {"condition": "Lightly Played", "variant": "Normal", "language": "English", "quantity": 1, "title": "Gilded Pinions", "listingType": "ListingWithoutPhotos", "customListingId": "", "purchasePrice": 0.04, "shippingPrice": 0.0, "orderDate": "2023-04-23T10:49:33+00:00"}, {"condition": "Lightly Played", "variant": "Normal", "language": "English", "quantity": 1, "title": "Gilded Pinions", "listingType": "ListingWithoutPhotos", "customListingId": "", "purchasePrice": 0.04, "shippingPrice": 0.0, "orderDate": "2023-04-23T00:56:26.806+00:00"}, {"condition": "Near Mint", "variant": "Normal", "language": "English", "quantity": 1, "title": "Gilded Pinions", "listingType": "ListingWithoutPhotos", "customListingId": "", "purchasePrice": 0.09, "shippingPrice": 1.35, "orderDate": "2023-04-22T19:58:18.223+00:00"}, {"condition": "Near Mint", "variant": "Foil", "language": "English", "quantity": 1, "title": "Gilded Pinions", "listingType": "ListingWithoutPhotos", "customListingId": "", "purchasePrice": 0.04, "shippingPrice": 0.0, "orderDate": "2023-04-22T17:50:51.95+00:00"}, {"condition": "Lightly Played", "variant": "Normal", "language": "English", "quantity": 1, "title": "Gilded Pinions", "listingType": "ListingWithoutPhotos", "customListingId": "", "purchasePrice": 0.2, "shippingPrice": 1.28, "orderDate": "2023-04-22T01:32:53.65+00:00"}, {"condition": "Near Mint", "variant": "Normal", "language": "English", "quantity": 3, "title": "Gilded Pinions", "listingType": "ListingWithoutPhotos", "customListingId": "", "purchasePrice": 0.05, "shippingPrice": 0.0, "orderDate": "2023-04-20T22:42:25.306+00:00"}, {"condition": "Near Mint", "variant": "Normal", "language": "English", "quantity": 1, "title": "Gilded Pinions", "listingType": "ListingWithoutPhotos", "customListingId": "", "purchasePrice": 0.05, "shippingPrice": 0.0, "orderDate": "2023-04-20T22:42:25.29+00:00"}, {"condition": "Near Mint", "variant": "Normal", "language": "English", "quantity": 1, "title": "Gilded Pinions", "listingType": "ListingWithoutPhotos", "customListingId": "", "purchasePrice": 0.01, "shippingPrice": 0.99, "orderDate": "2023-04-20T22:22:18.64+00:00"}, {"condition": "Lightly Played", "variant": "Normal", "language": "English", "quantity": 1, "title": "Gilded Pinions", "listingType": "ListingWithoutPhotos", "customListingId": "", "purchasePrice": 0.05, "shippingPrice": 0.0, "orderDate": "2023-04-20T21:41:53.96+00:00"}, {"condition": "Near Mint", "variant": "Normal", "language": "English", "quantity": 1, "title": "Gilded Pinions", "listingType": "ListingWithoutPhotos", "customListingId": "", "purchasePrice": 0.05, "shippingPrice": 0.0, "orderDate": "2023-04-20T17:06:33.63+00:00"}, {"condition": "Lightly Played", "variant": "Normal", "language": "English", "quantity": 1, "title": "Gilded Pinions", "listingType": "ListingWithoutPhotos", "customListingId": "", "purchasePrice": 0.05, "shippingPrice": 0.0, "orderDate": "2023-04-19T01:27:40.186+00:00"}, {"condition": "Near Mint", "variant": "Foil", "language": "English", "quantity": 1, "title": "Gilded Pinions", "listingType": "ListingWithoutPhotos", "customListingId": "", "purchasePrice": 0.04, "shippingPrice": 0.0, "orderDate": "2023-04-18T22:54:38.98+00:00"}, {"condition": "Near Mint", "variant": "Foil", "language": "English", "quantity": 1, "title": "Gilded Pinions", "listingType": "ListingWithoutPhotos", "customListingId": "", "purchasePrice": 0.05, "shippingPrice": 0.0, "orderDate": "2023-04-18T04:41:00.583+00:00"}, {"condition": "Near Mint", "variant": "Normal", "language": "English", "quantity": 1, "title": "Gilded Pinions", "listingType": "ListingWithoutPhotos", "customListingId": "", "purchasePrice": 0.05, "shippingPrice": 0.0, "orderDate": "2023-04-17T22:30:32.563+00:00"}, {"condition": "Near Mint", "variant": "Foil", "language": "English", "quantity": 1, "title": "Gilded Pinions", "listingType": "ListingWithoutPhotos", "customListingId": "", "purchasePrice": 0.05, "shippingPrice": 0.0, "orderDate": "2023-04-17T16:37:17.1+00:00"}, {"condition": "Lightly Played", "variant": "Normal", "language": "English", "quantity": 1, "title": "Gilded Pinions", "listingType": "ListingWithoutPhotos", "customListingId": "", "purchasePrice": 0.05, "shippingPrice": 0.0, "orderDate": "2023-04-16T03:48:55.893+00:00"}, {"condition": "Near Mint", "variant": "Normal", "language": "English", "quantity": 1, "title": "Gilded Pinions", "listingType": "ListingWithoutPhotos", "customListingId": "", "purchasePrice": 0.05, "shippingPrice": 0.0, "orderDate": "2023-04-16T02:19:08.293+00:00"}, {"condition": "Lightly Played", "variant": "Normal", "language": "English", "quantity": 1, "title": "Gilded Pinions", "listingType": "ListingWithoutPhotos", "customListingId": "", "purchasePrice": 0.05, "shippingPrice": 0.0, "orderDate": "2023-04-15T21:46:12.826+00:00"}, {"condition": "Near Mint", "variant": "Foil", "language": "English", "quantity": 1, "title": "Gilded Pinions", "listingType": "ListingWithoutPhotos", "customListingId": "", "purchasePrice": 0.04, "shippingPrice": 0.0, "orderDate": "2023-04-15T16:27:07.04+00:00"}, {"condition": "Lightly Played", "variant": "Normal", "language": "English", "quantity": 1, "title": "Gilded Pinions", "listingType": "ListingWithoutPhotos", "customListingId": "", "purchasePrice": 0.1, "shippingPrice": 0.0, "orderDate": "2023-04-15T02:10:15.983+00:00"}, {"condition": "Near Mint", "variant": "Foil", "language": "English", "quantity": 1, "title": "Gilded Pinions", "listingType": "ListingWithoutPhotos", "customListingId": "", "purchasePrice": 0.04, "shippingPrice": 0.0, "orderDate": "2023-04-14T15:34:22.263+00:00"}, {"condition": "Lightly Played", "variant": "Normal", "language": "English", "quantity": 1, "title": "Gilded Pinions", "listingType": "ListingWithoutPhotos", "customListingId": "", "purchasePrice": 0.05, "shippingPrice": 0.0, "orderDate": "2023-04-13T21:53:14.54+00:00"}, {"condition": "Near Mint", "variant": "Normal", "language": "English", "quantity": 1, "title": "Gilded Pinions", "listingType": "ListingWithoutPhotos", "customListingId": "", "purchasePrice": 0.14, "shippingPrice": 0.0, "orderDate": "2023-04-13T16:02:47.826+00:00"}, {"condition": "Lightly Played", "variant": "Normal", "language": "English", "quantity": 1, "title": "Gilded Pinions", "listingType": "ListingWithoutPhotos", "customListingId": "", "purchasePrice": 0.05, "shippingPrice": 0.0, "orderDate": "2023-04-13T02:26:47.15+00:00"}, {"condition": "Near Mint", "variant": "Normal", "language": "English", "quantity": 1, "title": "Gilded Pinions", "listingType": "ListingWithoutPhotos", "customListingId": "", "purchasePrice": 0.15, "shippingPrice": 0.0, "orderDate": "2023-04-12T21:28:14.066+00:00"}, {"condition": "Near Mint", "variant": "Normal", "language": "English", "quantity": 1, "title": "Gilded Pinions", "listingType": "ListingWithoutPhotos", "customListingId": "", "purchasePrice": 0.05, "shippingPrice": 0.0, "orderDate": "2023-04-12T12:36:40.03+00:00"}, {"condition": "Lightly Played", "variant": "Normal", "language": "English", "quantity": 1, "title": "Gilded Pinions", "listingType": "ListingWithoutPhotos", "customListingId": "", "purchasePrice": 0.05, "shippingPrice": 0.0, "orderDate": "2023-04-12T03:20:40.56+00:00"}, {"condition": "Near Mint", "variant": "Foil", "language": "English", "quantity": 1, "title": "Gilded Pinions", "listingType": "ListingWithoutPhotos", "customListingId": "", "purchasePrice": 0.07, "shippingPrice": 0.0, "orderDate": "2023-04-12T02:56:05.583+00:00"}, {"condition": "Near Mint", "variant": "Normal", "language": "English", "quantity": 1, "title": "Gilded Pinions", "listingType": "ListingWithoutPhotos", "customListingId": "", "purchasePrice": 0.05, "shippingPrice": 0.0, "orderDate": "2023-04-11T23:24:12.06+00:00"}, {"condition": "Near Mint", "variant": "Normal", "language": "English", "quantity": 1, "title": "Gilded Pinions", "listingType": "ListingWithoutPhotos", "customListingId": "", "purchasePrice": 0.05, "shippingPrice": 0.0, "orderDate": "2023-04-11T08:11:04.003+00:00"}, {"condition": "Lightly Played", "variant": "Normal", "language": "English", "quantity": 2, "title": "Gilded Pinions", "listingType": "ListingWithoutPhotos", "customListingId": "", "purchasePrice": 0.05, "shippingPrice": 0.0, "orderDate": "2023-04-11T01:01:35.306+00:00"}, {"condition": "Near Mint", "variant": "Normal", "language": "English", "quantity": 2, "title": "Gilded Pinions", "listingType": "ListingWithoutPhotos", "customListingId": "", "purchasePrice": 0.04, "shippingPrice": 0.0, "orderDate": "2023-04-11T01:01:35.293+00:00"}, {"condition": "Near Mint", "variant": "Normal", "language": "English", "quantity": 2, "title": "Gilded Pinions", "listingType": "ListingWithoutPhotos", "customListingId": "", "purchasePrice": 0.04, "shippingPrice": 0.0, "orderDate": "2023-04-10T22:27:12.23+00:00"}, {"condition": "Near Mint", "variant": "Normal", "language": "English", "quantity": 1, "title": "Gilded Pinions", "listingType": "ListingWithoutPhotos", "customListingId": "", "purchasePrice": 0.14, "shippingPrice": 0.0, "orderDate": "2023-04-10T13:15:14.696+00:00"}, {"condition": "Near Mint", "variant": "Normal", "language": "English", "quantity": 1, "title": "Gilded Pinions", "listingType": "ListingWithoutPhotos", "customListingId": "", "purchasePrice": 0.02, "shippingPrice": 0.0, "orderDate": "2023-04-10T12:55:41.59+00:00"}, {"condition": "Near Mint", "variant": "Normal", "language": "English", "quantity": 1, "title": "Gilded Pinions", "listingType": "ListingWithoutPhotos", "customListingId": "", "purchasePrice": 0.03, "shippingPrice": 0.0, "orderDate": "2023-04-10T04:23:10.333+00:00"}, {"condition": "Near Mint", "variant": "Foil", "language": "English", "quantity": 1, "title": "Gilded Pinions", "listingType": "ListingWithoutPhotos", "customListingId": "", "purchasePrice": 0.12, "shippingPrice": 0.0, "orderDate": "2023-04-10T03:45:51.183+00:00"}, {"condition": "Near Mint", "variant": "Normal", "language": "English", "quantity": 1, "title": "Gilded Pinions", "listingType": "ListingWithoutPhotos", "customListingId": "", "purchasePrice": 0.03, "shippingPrice": 0.0, "orderDate": "2023-04-10T00:13:24.333+00:00"}, {"condition": "Near Mint", "variant": "Foil", "language": "English", "quantity": 1, "title": "Gilded Pinions", "listingType": "ListingWithoutPhotos", "customListingId": "", "purchasePrice": 0.08, "shippingPrice": 0.0, "orderDate": "2023-04-09T09:07:24.61+00:00"}, {"condition": "Near Mint", "variant": "Normal", "language": "English", "quantity": 1, "title": "Gilded Pinions", "listingType": "ListingWithoutPhotos", "customListingId": "", "purchasePrice": 0.03, "shippingPrice": 0.0, "orderDate": "2023-04-09T03:35:57.89+00:00"}, {"condition": "Near Mint", "variant": "Normal", "language": "English", "quantity": 1, "title": "Gilded Pinions", "listingType": "ListingWithoutPhotos", "customListingId": "", "purchasePrice": 0.03, "shippingPrice": 0.0, "orderDate": "2023-04-08T21:15:37.643+00:00"}, {"condition": "Near Mint", "variant": "Normal", "language": "English", "quantity": 1, "title": "Gilded Pinions", "listingType": "ListingWithoutPhotos", "customListingId": "", "purchasePrice": 0.03, "shippingPrice": 0.0, "orderDate": "2023-04-08T15:49:16.2+00:00"}, {"condition": "Near Mint", "variant": "Normal", "language": "English", "quantity": 1, "title": "Gilded Pinions", "listingType": "ListingWithoutPhotos", "customListingId": "", "purchasePrice": 0.03, "shippingPrice": 0.0, "orderDate": "2023-04-08T14:59:28.03+00:00"}, {"condition": "Near Mint", "variant": "Normal", "language": "English", "quantity": 1, "title": "Gilded Pinions", "listingType": "ListingWithoutPhotos", "customListingId": "", "purchasePrice": 0.03, "shippingPrice": 0.0, "orderDate": "2023-04-08T07:18:55.4+00:00"}, {"condition": "Near Mint", "variant": "Normal", "language": "English", "quantity": 1, "title": "Gilded Pinions", "listingType": "ListingWithoutPhotos", "customListingId": "", "purchasePrice": 0.1, "shippingPrice": 1.99, "orderDate": "2023-04-08T06:22:00.42+00:00"}, {"condition": "Near Mint", "variant": "Normal", "language": "English", "quantity": 1, "title": "Gilded Pinions", "listingType": "ListingWithoutPhotos", "customListingId": "", "purchasePrice": 0.03, "shippingPrice": 0.0, "orderDate": "2023-04-08T02:56:54.01+00:00"}, {"condition": "Near Mint", "variant": "Normal", "language": "English", "quantity": 1, "title": "Gilded Pinions", "listingType": "ListingWithoutPhotos", "customListingId": "", "purchasePrice": 0.04, "shippingPrice": 0.0, "orderDate": "2023-04-06T22:59:01.583+00:00"}, {"condition": "Near Mint", "variant": "Normal", "language": "English", "quantity": 1, "title": "Gilded Pinions", "listingType": "ListingWithoutPhotos", "customListingId": "", "purchasePrice": 0.04, "shippingPrice": 0.0, "orderDate": "2023-04-06T03:36:30.356+00:00"}, {"condition": "Near Mint", "variant": "Normal", "language": "English", "quantity": 1, "title": "Gilded Pinions", "listingType": "ListingWithoutPhotos", "customListingId": "", "purchasePrice": 0.04, "shippingPrice": 0.0, "orderDate": "2023-04-05T19:02:38.39+00:00"}, {"condition": "Near Mint", "variant": "Foil", "language": "English", "quantity": 1, "title": "Gilded Pinions", "listingType": "ListingWithoutPhotos", "customListingId": "", "purchasePrice": 0.1, "shippingPrice": 0.0, "orderDate": "2023-04-05T07:49:16.286+00:00"}, {"condition": "Near Mint", "variant": "Normal", "language": "English", "quantity": 1, "title": "Gilded Pinions", "listingType": "ListingWithoutPhotos", "customListingId": "", "purchasePrice": 0.04, "shippingPrice": 0.0, "orderDate": "2023-04-05T04:18:48.39+00:00"}, {"condition": "Near Mint", "variant": "Normal", "language": "English", "quantity": 1, "title": "Gilded Pinions", "listingType": "ListingWithoutPhotos", "customListingId": "", "purchasePrice": 0.05, "shippingPrice": 4.99, "orderDate": "2023-04-05T02:10:28.293+00:00"}, {"condition": "Near Mint", "variant": "Normal", "language": "English", "quantity": 1, "title": "Gilded Pinions", "listingType": "ListingWithoutPhotos", "customListingId": "", "purchasePrice": 0.04, "shippingPrice": 0.0, "orderDate": "2023-04-04T23:58:12.79+00:00"}, {"condition": "Near Mint", "variant": "Normal", "language": "English", "quantity": 1, "title": "Gilded Pinions", "listingType": "ListingWithoutPhotos", "customListingId": "", "purchasePrice": 0.04, "shippingPrice": 0.0, "orderDate": "2023-04-04T21:30:25.646+00:00"}, {"condition": "Near Mint", "variant": "Normal", "language": "English", "quantity": 1, "title": "Gilded Pinions", "listingType": "ListingWithoutPhotos", "customListingId": "", "purchasePrice": 0.04, "shippingPrice": 0.0, "orderDate": "2023-04-04T03:53:59.29+00:00"}, {"condition": "Near Mint", "variant": "Normal", "language": "English", "quantity": 1, "title": "Gilded Pinions", "listingType": "ListingWithoutPhotos", "customListingId": "", "purchasePrice": 0.1, "shippingPrice": 0.0, "orderDate": "2023-04-04T01:25:53.14+00:00"}, {"condition": "Lightly Played", "variant": "Normal", "language": "English", "quantity": 3, "title": "Gilded Pinions", "listingType": "ListingWithoutPhotos", "customListingId": "", "purchasePrice": 0.05, "shippingPrice": 0.0, "orderDate": "2023-04-03T08:37:21.12+00:00"}, {"condition": "Near Mint", "variant": "Foil", "language": "English", "quantity": 1, "title": "Gilded Pinions", "listingType": "ListingWithoutPhotos", "customListingId": "", "purchasePrice": 0.12, "shippingPrice": 0.0, "orderDate": "2023-04-03T08:37:18.09+00:00"}, {"condition": "Near Mint", "variant": "Normal", "language": "English", "quantity": 1, "title": "Gilded Pinions", "listingType": "ListingWithoutPhotos", "customListingId": "", "purchasePrice": 0.04, "shippingPrice": 0.0, "orderDate": "2023-04-02T22:06:44.866+00:00"}, {"condition": "Near Mint", "variant": "Normal", "language": "English", "quantity": 2, "title": "Gilded Pinions", "listingType": "ListingWithoutPhotos", "customListingId": "", "purchasePrice": 0.03, "shippingPrice": 0.99, "orderDate": "2023-04-02T20:06:55.67+00:00"}, {"condition": "Near Mint", "variant": "Normal", "language": "English", "quantity": 2, "title": "Gilded Pinions", "listingType": "ListingWithoutPhotos", "customListingId": "", "purchasePrice": 0.05, "shippingPrice": 0.99, "orderDate": "2023-04-02T20:06:55.56+00:00"}, {"condition": "Near Mint", "variant": "Normal", "language": "English", "quantity": 1, "title": "Gilded Pinions", "listingType": "ListingWithoutPhotos", "customListingId": "", "purchasePrice": 0.04, "shippingPrice": 0.0, "orderDate": "2023-04-02T19:52:30.15+00:00"}, {"condition": "Near Mint", "variant": "Normal", "language": "English", "quantity": 1, "title": "Gilded Pinions", "listingType": "ListingWithoutPhotos", "customListingId": "", "purchasePrice": 0.04, "shippingPrice": 0.0, "orderDate": "2023-04-02T05:54:02.01+00:00"}, {"condition": "Near Mint", "variant": "Normal", "language": "English", "quantity": 1, "title": "Gilded Pinions", "listingType": "ListingWithoutPhotos", "customListingId": "", "purchasePrice": 0.04, "shippingPrice": 0.0, "orderDate": "2023-04-01T19:55:51.456+00:00"}, {"condition": "Near Mint", "variant": "Normal", "language": "English", "quantity": 1, "title": "Gilded Pinions", "listingType": "ListingWithoutPhotos", "customListingId": "", "purchasePrice": 0.01, "shippingPrice": 0.99, "orderDate": "2023-04-01T18:05:46.59+00:00"}, {"condition": "Near Mint", "variant": "Normal", "language": "English", "quantity": 1, "title": "Gilded Pinions", "listingType": "ListingWithoutPhotos", "customListingId": "", "purchasePrice": 0.01, "shippingPrice": 0.99, "orderDate": "2023-04-01T17:09:51.35+00:00"}, {"condition": "Near Mint", "variant": "Normal", "language": "English", "quantity": 2, "title": "Gilded Pinions", "listingType": "ListingWithoutPhotos", "customListingId": "", "purchasePrice": 0.04, "shippingPrice": 0.0, "orderDate": "2023-04-01T07:01:50.913+00:00"}, {"condition": "Near Mint", "variant": "Normal", "language": "English", "quantity": 1, "title": "Gilded Pinions", "listingType": "ListingWithoutPhotos", "customListingId": "", "purchasePrice": 0.25, "shippingPrice": 0.0, "orderDate": "2023-04-01T01:05:54.513+00:00"}, {"condition": "Lightly Played", "variant": "Normal", "language": "English", "quantity": 2, "title": "Gilded Pinions", "listingType": "ListingWithoutPhotos", "customListingId": "", "purchasePrice": 0.05, "shippingPrice": 0.0, "orderDate": "2023-03-31T15:17:54.743+00:00"}, {"condition": "Near Mint", "variant": "Normal", "language": "English", "quantity": 1, "title": "Gilded Pinions", "listingType": "ListingWithoutPhotos", "customListingId": "", "purchasePrice": 0.05, "shippingPrice": 0.0, "orderDate": "2023-03-31T04:27:55.046+00:00"}, {"condition": "Near Mint", "variant": "Normal", "language": "English", "quantity": 1, "title": "Gilded Pinions", "listingType": "ListingWithoutPhotos", "customListingId": "", "purchasePrice": 0.01, "shippingPrice": 0.99, "orderDate": "2023-03-30T12:26:29.04+00:00"}, {"condition": "Lightly Played", "variant": "Normal", "language": "English", "quantity": 1, "title": "Gilded Pinions", "listingType": "ListingWithoutPhotos", "customListingId": "", "purchasePrice": 0.05, "shippingPrice": 0.0, "orderDate": "2023-03-30T06:09:27.706+00:00"}, {"condition": "Near Mint", "variant": "Normal", "language": "English", "quantity": 1, "title": "Gilded Pinions", "listingType": "ListingWithoutPhotos", "customListingId": "", "purchasePrice": 0.05, "shippingPrice": 0.0, "orderDate": "2023-03-29T04:30:57.386+00:00"}, {"condition": "Near Mint", "variant": "Normal", "language": "English", "quantity": 1, "title": "Gilded Pinions", "listingType": "ListingWithoutPhotos", "customListingId": "", "purchasePrice": 0.05, "shippingPrice": 0.99, "orderDate": "2023-03-29T03:56:59.183+00:00"}, {"condition": "Near Mint", "variant": "Normal", "language": "English", "quantity": 1, "title": "Gilded Pinions", "listingType": "ListingWithoutPhotos", "customListingId": "", "purchasePrice": 0.04, "shippingPrice": 1.15, "orderDate": "2023-03-27T20:40:20.15+00:00"}, {"condition": "Near Mint", "variant": "Foil", "language": "English", "quantity": 8, "title": "Gilded Pinions", "listingType": "ListingWithoutPhotos", "customListingId": "", "purchasePrice": 0.1, "shippingPrice": 0.0, "orderDate": "2023-03-27T17:27:29.246+00:00"}, {"condition": "Near Mint", "variant": "Foil", "language": "English", "quantity": 1, "title": "Gilded Pinions", "listingType": "ListingWithoutPhotos", "customListingId": "", "purchasePrice": 0.1, "shippingPrice": 0.0, "orderDate": "2023-03-27T07:28:59.543+00:00"}, {"condition": "Near Mint", "variant": "Foil", "language": "English", "quantity": 1, "title": "Gilded Pinions", "listingType": "ListingWithoutPhotos", "customListingId": "", "purchasePrice": 0.07, "shippingPrice": 0.99, "orderDate": "2023-03-27T05:04:44.39+00:00"}, {"condition": "Near Mint", "variant": "Normal", "language": "English", "quantity": 1, "title": "Gilded Pinions", "listingType": "ListingWithoutPhotos", "customListingId": "", "purchasePrice": 0.05, "shippingPrice": 0.0, "orderDate": "2023-03-26T08:59:10.2+00:00"}, {"condition": "Near Mint", "variant": "Normal", "language": "English", "quantity": 1, "title": "Gilded Pinions", "listingType": "ListingWithoutPhotos", "customListingId": "", "purchasePrice": 0.05, "shippingPrice": 0.0, "orderDate": "2023-03-25T18:42:50.13+00:00"}, {"condition": "Near Mint", "variant": "Normal", "language": "English", "quantity": 1, "title": "Gilded Pinions", "listingType": "ListingWithoutPhotos", "customListingId": "", "purchasePrice": 0.05, "shippingPrice": 0.0, "orderDate": "2023-03-25T16:40:35.653+00:00"}, {"condition": "Near Mint", "variant": "Normal", "language": "English", "quantity": 1, "title": "Gilded Pinions", "listingType": "ListingWithoutPhotos", "customListingId": "", "purchasePrice": 0.05, "shippingPrice": 0.0, "orderDate": "2023-03-25T01:02:05.613+00:00"}, {"condition": "Near Mint", "variant": "Normal", "language": "English", "quantity": 1, "title": "Gilded Pinions", "listingType": "ListingWithoutPhotos", "customListingId": "", "purchasePrice": 0.05, "shippingPrice": 0.0, "orderDate": "2023-03-24T21:13:28.29+00:00"}, {"condition": "Near Mint", "variant": "Normal", "language": "English", "quantity": 1, "title": "Gilded Pinions", "listingType": "ListingWithoutPhotos", "customListingId": "", "purchasePrice": 0.05, "shippingPrice": 0.0, "orderDate": "2023-03-24T09:57:32.813+00:00"}, {"condition": "Near Mint", "variant": "Normal", "language": "English", "quantity": 1, "title": "Gilded Pinions", "listingType": "ListingWithoutPhotos", "customListingId": "", "purchasePrice": 0.05, "shippingPrice": 0.0, "orderDate": "2023-03-24T00:53:07.923+00:00"}, {"condition": "Lightly Played", "variant": "Foil", "language": "English", "quantity": 1, "title": "Gilded Pinions", "listingType": "ListingWithoutPhotos", "customListingId": "", "purchasePrice": 0.14, "shippingPrice": 8.99, "orderDate": "2023-03-23T16:03:08.973+00:00"}, {"condition": "Near Mint", "variant": "Normal", "language": "English", "quantity": 1, "title": "Gilded Pinions", "listingType": "ListingWithoutPhotos", "customListingId": "", "purchasePrice": 0.01, "shippingPrice": 0.99, "orderDate": "2023-03-23T13:53:14.726+00:00"}, {"condition": "Near Mint", "variant": "Normal", "language": "English", "quantity": 1, "title": "Gilded Pinions", "listingType": "ListingWithoutPhotos", "customListingId": "", "purchasePrice": 0.05, "shippingPrice": 0.0, "orderDate": "2023-03-23T01:09:07.09+00:00"}, {"condition": "Near Mint", "variant": "Normal", "language": "English", "quantity": 1, "title": "Gilded Pinions", "listingType": "ListingWithoutPhotos", "customListingId": "", "purchasePrice": 0.05, "shippingPrice": 0.0, "orderDate": "2023-03-22T14:50:41.75+00:00"}, {"condition": "Lightly Played", "variant": "Foil", "language": "English", "quantity": 2, "title": "Gilded pinions foil", "listingType": "ListingWithPhotos", "customListingId": "c2i7HK5KZik1", "purchasePrice": 0.07, "shippingPrice": 0.99, "orderDate": "2023-03-22T04:58:31.396+00:00"}, {"condition": "Near Mint", "variant": "Normal", "language": "English", "quantity": 1, "title": "Gilded Pinions", "listingType": "ListingWithoutPhotos", "customListingId": "", "purchasePrice": 0.05, "shippingPrice": 0.0, "orderDate": "2023-03-21T23:22:40.753+00:00"}, {"condition": "Near Mint", "variant": "Normal", "language": "English", "quantity": 1, "title": "Gilded Pinions", "listingType": "ListingWithoutPhotos", "customListingId": "", "purchasePrice": 0.05, "shippingPrice": 0.0, "orderDate": "2023-03-21T14:30:04.376+00:00"}, {"condition": "Lightly Played", "variant": "Normal", "language": "English", "quantity": 1, "title": "Gilded Pinions", "listingType": "ListingWithoutPhotos", "customListingId": "", "purchasePrice": 0.05, "shippingPrice": 0.0, "orderDate": "2023-03-20T23:37:48.48+00:00"}, {"condition": "Near Mint", "variant": "Normal", "language": "English", "quantity": 1, "title": "Gilded Pinions", "listingType": "ListingWithoutPhotos", "customListingId": "", "purchasePrice": 0.05, "shippingPrice": 0.0, "orderDate": "2023-03-20T23:37:48.416+00:00"}, {"condition": "Near Mint", "variant": "Normal", "language": "English", "quantity": 1, "title": "Gilded Pinions", "listingType": "ListingWithoutPhotos", "customListingId": "", "purchasePrice": 1.0, "shippingPrice": 0.0, "orderDate": "2023-03-20T15:09:25.886+00:00"}, {"condition": "Near Mint", "variant": "Normal", "language": "English", "quantity": 1, "title": "Gilded Pinions", "listingType": "ListingWithoutPhotos", "customListingId": "", "purchasePrice": 0.05, "shippingPrice": 0.0, "orderDate": "2023-03-20T07:23:47.483+00:00"}, {"condition": "Near Mint", "variant": "Normal", "language": "English", "quantity": 1, "title": "Gilded Pinions", "listingType": "ListingWithoutPhotos", "customListingId": "", "purchasePrice": 0.08, "shippingPrice": 0.0, "orderDate": "2023-03-19T20:53:10.98+00:00"}, {"condition": "Near Mint", "variant": "Normal", "language": "English", "quantity": 2, "title": "Gilded Pinions", "listingType": "ListingWithoutPhotos", "customListingId": "", "purchasePrice": 0.08, "shippingPrice": 1.99, "orderDate": "2023-03-19T12:58:22.333+00:00"}, {"condition": "Near Mint", "variant": "Normal", "language": "English", "quantity": 1, "title": "Gilded Pinions", "listingType": "ListingWithoutPhotos", "customListingId": "", "purchasePrice": 0.05, "shippingPrice": 0.0, "orderDate": "2023-03-18T17:15:11.543+00:00"}, {"condition": "Near Mint", "variant": "Normal", "language": "English", "quantity": 1, "title": "Gilded Pinions", "listingType": "ListingWithoutPhotos", "customListingId": "", "purchasePrice": 0.05, "shippingPrice": 0.0, "orderDate": "2023-03-18T07:29:28.723+00:00"}, {"condition": "Near Mint", "variant": "Normal", "language": "English", "quantity": 1, "title": "Gilded Pinions", "listingType": "ListingWithoutPhotos", "customListingId": "", "purchasePrice": 0.05, "shippingPrice": 0.0, "orderDate": "2023-03-18T05:38:17.106+00:00"}, {"condition": "Near Mint", "variant": "Normal", "language": "English", "quantity": 1, "title": "Gilded Pinions", "listingType": "ListingWithoutPhotos", "customListingId": "", "purchasePrice": 0.05, "shippingPrice": 0.0, "orderDate": "2023-03-17T03:50:16.733+00:00"}, {"condition": "Near Mint", "variant": "Normal", "language": "English", "quantity": 2, "title": "Gilded Pinions", "listingType": "ListingWithoutPhotos", "customListingId": "", "purchasePrice": 0.05, "shippingPrice": 0.0, "orderDate": "2023-03-17T02:33:58.94+00:00"}, {"condition": "Lightly Played", "variant": "Normal", "language": "English", "quantity": 2, "title": "Gilded Pinions", "listingType": "ListingWithoutPhotos", "customListingId": "", "purchasePrice": 0.05, "shippingPrice": 0.0, "orderDate": "2023-03-17T02:33:58.926+00:00"}, {"condition": "Near Mint", "variant": "Normal", "language": "English", "quantity": 1, "title": "Gilded Pinions", "listingType": "ListingWithoutPhotos", "customListingId": "", "purchasePrice": 0.04, "shippingPrice": 0.0, "orderDate": "2023-03-16T06:40:36.1+00:00"}, {"condition": "Lightly Played", "variant": "Foil", "language": "English", "quantity": 1, "title": "Gilded Pinions", "listingType": "ListingWithoutPhotos", "customListingId": "", "purchasePrice": 0.25, "shippingPrice": 0.99, "orderDate": "2023-03-14T04:00:04.28+00:00"}, {"condition": "Lightly Played", "variant": "Normal", "language": "English", "quantity": 1, "title": "Gilded Pinions", "listingType": "ListingWithoutPhotos", "customListingId": "", "purchasePrice": 0.05, "shippingPrice": 2.49, "orderDate": "2023-03-13T20:22:20.08+00:00"}, {"condition": "Near Mint", "variant": "Foil", "language": "English", "quantity": 1, "title": "Gilded Pinions", "listingType": "ListingWithoutPhotos", "customListingId": "", "purchasePrice": 0.16, "shippingPrice": 1.15, "orderDate": "2023-03-13T02:44:08.143+00:00"}, {"condition": "Near Mint", "variant": "Foil", "language": "English", "quantity": 1, "title": "Gilded Pinions", "listingType": "ListingWithoutPhotos", "customListingId": "", "purchasePrice": 0.1, "shippingPrice": 0.0, "orderDate": "2023-03-11T21:17:46.03+00:00"}, {"condition": "Near Mint", "variant": "Foil", "language": "English", "quantity": 1, "title": "Gilded Pinions", "listingType": "ListingWithoutPhotos", "customListingId": "", "purchasePrice": 0.1, "shippingPrice": 0.0, "orderDate": "2023-03-11T05:15:35.13+00:00"}, {"condition": "Near Mint", "variant": "Foil", "language": "English", "quantity": 1, "title": "Gilded Pinions", "listingType": "ListingWithoutPhotos", "customListingId": "", "purchasePrice": 0.1, "shippingPrice": 0.0, "orderDate": "2023-03-11T01:03:35.01+00:00"}, {"condition": "Lightly Played", "variant": "Normal", "language": "English", "quantity": 1, "title": "Gilded Pinions", "listingType": "ListingWithoutPhotos", "customListingId": "", "purchasePrice": 0.05, "shippingPrice": 0.0, "orderDate": "2023-03-10T03:03:03.686+00:00"}, {"condition": "Lightly Played", "variant": "Normal", "language": "English", "quantity": 1, "title": "Gilded Pinions", "listingType": "ListingWithoutPhotos", "customListingId": "", "purchasePrice": 0.05, "shippingPrice": 0.0, "orderDate": "2023-03-10T03:03:03.653+00:00"}, {"condition": "Near Mint", "variant": "Normal", "language": "English", "quantity": 1, "title": "Gilded Pinions", "listingType": "ListingWithoutPhotos", "customListingId": "", "purchasePrice": 0.05, "shippingPrice": 0.0, "orderDate": "2023-03-10T03:03:03.64+00:00"}, {"condition": "Near Mint", "variant": "Normal", "language": "English", "quantity": 1, "title": "Gilded Pinions", "listingType": "ListingWithoutPhotos", "customListingId": "", "purchasePrice": 0.05, "shippingPrice": 0.0, "orderDate": "2023-03-10T03:03:03.576+00:00"}, {"condition": "Lightly Played", "variant": "Normal", "language": "English", "quantity": 4, "title": "Gilded Pinions", "listingType": "ListingWithoutPhotos", "customListingId": "", "purchasePrice": 0.05, "shippingPrice": 0.0, "orderDate": "2023-03-10T02:50:46.643+00:00"}, {"condition": "Lightly Played", "variant": "Normal", "language": "English", "quantity": 1, "title": "Gilded Pinions", "listingType": "ListingWithoutPhotos", "customListingId": "", "purchasePrice": 0.05, "shippingPrice": 1.75, "orderDate": "2023-03-09T21:42:06.09+00:00"}, {"condition": "Near Mint", "variant": "Normal", "language": "English", "quantity": 1, "title": "Gilded Pinions", "listingType": "ListingWithoutPhotos", "customListingId": "", "purchasePrice": 0.05, "shippingPrice": 0.0, "orderDate": "2023-03-09T20:45:48.8+00:00"}, {"condition": "Near Mint", "variant": "Normal", "language": "English", "quantity": 36, "title": "Gilded Pinions", "listingType": "ListingWithoutPhotos", "customListingId": "", "purchasePrice": 0.06, "shippingPrice": 0.0, "orderDate": "2023-03-09T17:21:58.436+00:00"}, {"condition": "Lightly Played", "variant": "Foil", "language": "English", "quantity": 1, "title": "Gilded Pinions", "listingType": "ListingWithoutPhotos", "customListingId": "", "purchasePrice": 0.12, "shippingPrice": 3.99, "orderDate": "2023-03-09T04:58:30.723+00:00"}, {"condition": "Near Mint", "variant": "Normal", "language": "English", "quantity": 1, "title": "Gilded Pinions", "listingType": "ListingWithoutPhotos", "customListingId": "", "purchasePrice": 0.05, "shippingPrice": 0.0, "orderDate": "2023-03-09T00:58:27.433+00:00"}, {"condition": "Near Mint", "variant": "Normal", "language": "English", "quantity": 1, "title": "Gilded Pinions", "listingType": "ListingWithoutPhotos", "customListingId": "", "purchasePrice": 0.04, "shippingPrice": 0.0, "orderDate": "2023-03-08T09:17:43.76+00:00"}, {"condition": "Near Mint", "variant": "Normal", "language": "English", "quantity": 1, "title": "Gilded Pinions", "listingType": "ListingWithoutPhotos", "customListingId": "", "purchasePrice": 0.04, "shippingPrice": 0.0, "orderDate": "2023-03-07T20:52:11.95+00:00"}, {"condition": "Near Mint", "variant": "Normal", "language": "English", "quantity": 1, "title": "Gilded Pinions", "listingType": "ListingWithoutPhotos", "customListingId": "", "purchasePrice": 0.04, "shippingPrice": 0.0, "orderDate": "2023-03-07T06:29:27.633+00:00"}, {"condition": "Near Mint", "variant": "Normal", "language": "English", "quantity": 1, "title": "Gilded Pinions", "listingType": "ListingWithoutPhotos", "customListingId": "", "purchasePrice": 0.04, "shippingPrice": 0.0, "orderDate": "2023-03-06T00:58:11.6+00:00"}, {"condition": "Lightly Played", "variant": "Normal", "language": "English", "quantity": 1, "title": "Gilded Pinions", "listingType": "ListingWithoutPhotos", "customListingId": "", "purchasePrice": 0.05, "shippingPrice": 0.0, "orderDate": "2023-03-05T09:10:10.906+00:00"}, {"condition": "Lightly Played", "variant": "Normal", "language": "English", "quantity": 1, "title": "Gilded Pinions", "listingType": "ListingWithoutPhotos", "customListingId": "", "purchasePrice": 0.05, "shippingPrice": 0.0, "orderDate": "2023-03-04T00:15:02.446+00:00"}, {"condition": "Lightly Played", "variant": "Normal", "language": "English", "quantity": 1, "title": "Gilded Pinions", "listingType": "ListingWithoutPhotos", "customListingId": "", "purchasePrice": 0.05, "shippingPrice": 0.0, "orderDate": "2023-03-03T17:00:25.74+00:00"}, {"condition": "Near Mint", "variant": "Normal", "language": "English", "quantity": 1, "title": "Gilded Pinions", "listingType": "ListingWithoutPhotos", "customListingId": "", "purchasePrice": 0.07, "shippingPrice": 2.09, "orderDate": "2023-03-03T04:30:00.223+00:00"}, {"condition": "Near Mint", "variant": "Normal", "language": "English", "quantity": 1, "title": "Gilded Pinions", "listingType": "ListingWithoutPhotos", "customListingId": "", "purchasePrice": 0.05, "shippingPrice": 0.0, "orderDate": "2023-03-02T20:37:13.11+00:00"}, {"condition": "Near Mint", "variant": "Normal", "language": "English", "quantity": 4, "title": "Gilded Pinions", "listingType": "ListingWithoutPhotos", "customListingId": "", "purchasePrice": 0.05, "shippingPrice": 0.99, "orderDate": "2023-03-02T01:18:18.126+00:00"}, {"condition": "Near Mint", "variant": "Foil", "language": "English", "quantity": 1, "title": "Gilded Pinions", "listingType": "ListingWithoutPhotos", "customListingId": "", "purchasePrice": 0.1, "shippingPrice": 0.0, "orderDate": "2023-02-28T18:41:27.856+00:00"}, {"condition": "Near Mint", "variant": "Normal", "language": "English", "quantity": 1, "title": "Gilded Pinions", "listingType": "ListingWithoutPhotos", "customListingId": "", "purchasePrice": 0.05, "shippingPrice": 0.0, "orderDate": "2023-02-28T11:59:34.156+00:00"}, {"condition": "Lightly Played", "variant": "Normal", "language": "English", "quantity": 1, "title": "Gilded Pinions", "listingType": "ListingWithoutPhotos", "customListingId": "", "purchasePrice": 0.05, "shippingPrice": 0.0, "orderDate": "2023-02-28T09:18:19.753+00:00"}, {"condition": "Near Mint", "variant": "Normal", "language": "English", "quantity": 8, "title": "Gilded Pinions", "listingType": "ListingWithoutPhotos", "customListingId": "", "purchasePrice": 0.1, "shippingPrice": 0.0, "orderDate": "2023-02-28T06:04:10.833+00:00"}, {"condition": "Near Mint", "variant": "Normal", "language": "English", "quantity": 1, "title": "Gilded Pinions", "listingType": "ListingWithoutPhotos", "customListingId": "", "purchasePrice": 0.01, "shippingPrice": 0.99, "orderDate": "2023-02-28T05:20:13.703+00:00"}, {"condition": "Near Mint", "variant": "Normal", "language": "English", "quantity": 1, "title": "Gilded Pinions", "listingType": "ListingWithoutPhotos", "customListingId": "", "purchasePrice": 0.2, "shippingPrice": 0.0, "orderDate": "2023-02-28T04:52:20.656+00:00"}, {"condition": "Lightly Played", "variant": "Normal", "language": "English", "quantity": 1, "title": "Gilded Pinions", "listingType": "ListingWithoutPhotos", "customListingId": "", "purchasePrice": 0.05, "shippingPrice": 0.99, "orderDate": "2023-02-28T00:31:55.44+00:00"}, {"condition": "Near Mint", "variant": "Normal", "language": "English", "quantity": 1, "title": "Gilded Pinions", "listingType": "ListingWithoutPhotos", "customListingId": "", "purchasePrice": 0.05, "shippingPrice": 0.0, "orderDate": "2023-02-28T00:29:31.46+00:00"}, {"condition": "Near Mint", "variant": "Normal", "language": "English", "quantity": 1, "title": "Gilded Pinions", "listingType": "ListingWithoutPhotos", "customListingId": "", "purchasePrice": 0.05, "shippingPrice": 0.0, "orderDate": "2023-02-27T18:10:57.673+00:00"}, {"condition": "Near Mint", "variant": "Normal", "language": "English", "quantity": 6, "title": "Gilded Pinions", "listingType": "ListingWithoutPhotos", "customListingId": "", "purchasePrice": 0.05, "shippingPrice": 0.0, "orderDate": "2023-02-27T18:10:57.666+00:00"}, {"condition": "Near Mint", "variant": "Normal", "language": "English", "quantity": 3, "title": "Gilded Pinions", "listingType": "ListingWithoutPhotos", "customListingId": "", "purchasePrice": 0.05, "shippingPrice": 0.0, "orderDate": "2023-02-27T18:10:57.656+00:00"}, {"condition": "Near Mint", "variant": "Normal", "language": "English", "quantity": 1, "title": "Gilded Pinions", "listingType": "ListingWithoutPhotos", "customListingId": "", "purchasePrice": 0.05, "shippingPrice": 0.0, "orderDate": "2023-02-27T18:10:57.646+00:00"}, {"condition": "Lightly Played", "variant": "Normal", "language": "English", "quantity": 1, "title": "Gilded Pinions", "listingType": "ListingWithoutPhotos", "customListingId": "", "purchasePrice": 0.05, "shippingPrice": 1.29, "orderDate": "2023-02-27T05:27:13.776+00:00"}, {"condition": "Near Mint", "variant": "Normal", "language": "English", "quantity": 1, "title": "Gilded Pinions", "listingType": "ListingWithoutPhotos", "customListingId": "", "purchasePrice": 0.05, "shippingPrice": 0.99, "orderDate": "2023-02-26T21:01:29.126+00:00"}, {"condition": "Near Mint", "variant": "Normal", "language": "English", "quantity": 1, "title": "Gilded Pinions", "listingType": "ListingWithoutPhotos", "customListingId": "", "purchasePrice": 0.05, "shippingPrice": 0.0, "orderDate": "2023-02-25T23:29:06.22+00:00"}, {"condition": "Lightly Played", "variant": "Normal", "language": "English", "quantity": 1, "title": "Gilded Pinions", "listingType": "ListingWithoutPhotos", "customListingId": "", "purchasePrice": 0.05, "shippingPrice": 0.0, "orderDate": "2023-02-25T22:25:02.403+00:00"}, {"condition": "Near Mint", "variant": "Normal", "language": "English", "quantity": 1, "title": "Gilded Pinions", "listingType": "ListingWithoutPhotos", "customListingId": "", "purchasePrice": 0.05, "shippingPrice": 0.0, "orderDate": "2023-02-25T08:50:51.616+00:00"}, {"condition": "Near Mint", "variant": "Normal", "language": "English", "quantity": 2, "title": "Gilded Pinions", "listingType": "ListingWithoutPhotos", "customListingId": "", "purchasePrice": 0.05, "shippingPrice": 0.0, "orderDate": "2023-02-24T23:02:49.27+00:00"}, {"condition": "Near Mint", "variant": "Normal", "language": "English", "quantity": 1, "title": "Gilded Pinions", "listingType": "ListingWithoutPhotos", "customListingId": "", "purchasePrice": 0.07, "shippingPrice": 0.99, "orderDate": "2023-02-24T00:10:50.886+00:00"}, {"condition": "Near Mint", "variant": "Normal", "language": "English", "quantity": 1, "title": "Gilded Pinions", "listingType": "ListingWithoutPhotos", "customListingId": "", "purchasePrice": 0.05, "shippingPrice": 0.0, "orderDate": "2023-02-23T22:28:28.33+00:00"}, {"condition": "Lightly Played", "variant": "Normal", "language": "English", "quantity": 1, "title": "Gilded Pinions", "listingType": "ListingWithoutPhotos", "customListingId": "", "purchasePrice": 0.05, "shippingPrice": 0.0, "orderDate": "2023-02-23T14:07:36.333+00:00"}, {"condition": "Near Mint", "variant": "Normal", "language": "English", "quantity": 4, "title": "Gilded Pinions", "listingType": "ListingWithoutPhotos", "customListingId": "", "purchasePrice": 0.05, "shippingPrice": 0.99, "orderDate": "2023-02-23T01:40:57.583+00:00"}, {"condition": "Near Mint", "variant": "Normal", "language": "English", "quantity": 1, "title": "Gilded Pinions", "listingType": "ListingWithoutPhotos", "customListingId": "", "purchasePrice": 0.05, "shippingPrice": 0.0, "orderDate": "2023-02-22T17:46:34.466+00:00"}, {"condition": "Near Mint", "variant": "Normal", "language": "English", "quantity": 2, "title": "Gilded Pinions", "listingType": "ListingWithoutPhotos", "customListingId": "", "purchasePrice": 0.05, "shippingPrice": 0.0, "orderDate": "2023-02-22T11:56:44.576+00:00"}, {"condition": "Lightly Played", "variant": "Normal", "language": "English", "quantity": 1, "title": "Gilded Pinions", "listingType": "ListingWithoutPhotos", "customListingId": "", "purchasePrice": 0.05, "shippingPrice": 0.0, "orderDate": "2023-02-21T23:00:51.983+00:00"}, {"condition": "Lightly Played", "variant": "Normal", "language": "English", "quantity": 2, "title": "Gilded Pinions", "listingType": "ListingWithoutPhotos", "customListingId": "", "purchasePrice": 0.06, "shippingPrice": 0.99, "orderDate": "2023-02-21T00:17:18.326+00:00"}, {"condition": "Near Mint", "variant": "Normal", "language": "English", "quantity": 1, "title": "Gilded Pinions", "listingType": "ListingWithoutPhotos", "customListingId": "", "purchasePrice": 0.05, "shippingPrice": 0.0, "orderDate": "2023-02-20T19:50:07.92+00:00"}, {"condition": "Near Mint", "variant": "Normal", "language": "English", "quantity": 1, "title": "Gilded Pinions", "listingType": "ListingWithoutPhotos", "customListingId": "", "purchasePrice": 0.05, "shippingPrice": 0.0, "orderDate": "2023-02-20T18:37:04.35+00:00"}, {"condition": "Lightly Played", "variant": "Normal", "language": "English", "quantity": 1, "title": "Gilded Pinions", "listingType": "ListingWithoutPhotos", "customListingId": "", "purchasePrice": 0.05, "shippingPrice": 0.0, "orderDate": "2023-02-20T15:57:46.43+00:00"}, {"condition": "Lightly Played", "variant": "Normal", "language": "English", "quantity": 1, "title": "Gilded Pinions", "listingType": "ListingWithoutPhotos", "customListingId": "", "purchasePrice": 0.05, "shippingPrice": 0.0, "orderDate": "2023-02-20T05:39:23.55+00:00"}, {"condition": "Near Mint", "variant": "Normal", "language": "English", "quantity": 1, "title": "Gilded Pinions", "listingType": "ListingWithoutPhotos", "customListingId": "", "purchasePrice": 0.05, "shippingPrice": 0.0, "orderDate": "2023-02-20T03:43:32.83+00:00"}, {"condition": "Near Mint", "variant": "Normal", "language": "English", "quantity": 4, "title": "Gilded Pinions", "listingType": "ListingWithoutPhotos", "customListingId": "", "purchasePrice": 0.05, "shippingPrice": 0.0, "orderDate": "2023-02-18T17:01:45.243+00:00"}, {"condition": "Near Mint", "variant": "Normal", "language": "English", "quantity": 2, "title": "Gilded Pinions", "listingType": "ListingWithoutPhotos", "customListingId": "", "purchasePrice": 0.05, "shippingPrice": 0.0, "orderDate": "2023-02-18T08:36:13.543+00:00"}, {"condition": "Near Mint", "variant": "Normal", "language": "English", "quantity": 1, "title": "Gilded Pinions", "listingType": "ListingWithoutPhotos", "customListingId": "", "purchasePrice": 0.01, "shippingPrice": 0.99, "orderDate": "2023-02-17T20:06:55.21+00:00"}, {"condition": "Near Mint", "variant": "Normal", "language": "English", "quantity": 1, "title": "Gilded Pinions", "listingType": "ListingWithoutPhotos", "customListingId": "", "purchasePrice": 0.05, "shippingPrice": 0.0, "orderDate": "2023-02-17T03:33:52.253+00:00"}, {"condition": "Near Mint", "variant": "Normal", "language": "English", "quantity": 1, "title": "Gilded Pinions", "listingType": "ListingWithoutPhotos", "customListingId": "", "purchasePrice": 0.06, "shippingPrice": 0.99, "orderDate": "2023-02-15T18:01:53.066+00:00"}, {"condition": "Near Mint", "variant": "Foil", "language": "English", "quantity": 1, "title": "Gilded Pinions", "listingType": "ListingWithoutPhotos", "customListingId": "", "purchasePrice": 0.11, "shippingPrice": 0.0, "orderDate": "2023-02-15T04:20:58.3+00:00"}, {"condition": "Near Mint", "variant": "Foil", "language": "English", "quantity": 3, "title": "Gilded Pinions", "listingType": "ListingWithoutPhotos", "customListingId": "", "purchasePrice": 0.11, "shippingPrice": 0.0, "orderDate": "2023-02-15T04:20:58.293+00:00"}, {"condition": "Near Mint", "variant": "Foil", "language": "English", "quantity": 3, "title": "Gilded Pinions", "listingType": "ListingWithoutPhotos", "customListingId": "", "purchasePrice": 0.11, "shippingPrice": 0.0, "orderDate": "2023-02-15T04:20:58.283+00:00"}, {"condition": "Near Mint", "variant": "Foil", "language": "English", "quantity": 1, "title": "Gilded Pinions", "listingType": "ListingWithoutPhotos", "customListingId": "", "purchasePrice": 0.1, "shippingPrice": 0.0, "orderDate": "2023-02-15T04:20:58.253+00:00"}, {"condition": "Near Mint", "variant": "Normal", "language": "English", "quantity": 1, "title": "Gilded Pinions", "listingType": "ListingWithoutPhotos", "customListingId": "", "purchasePrice": 0.05, "shippingPrice": 0.0, "orderDate": "2023-02-15T02:59:43.16+00:00"}, {"condition": "Near Mint", "variant": "Normal", "language": "English", "quantity": 2, "title": "Gilded Pinions", "listingType": "ListingWithoutPhotos", "customListingId": "", "purchasePrice": 0.05, "shippingPrice": 0.0, "orderDate": "2023-02-15T01:12:58.92+00:00"}, {"condition": "Near Mint", "variant": "Normal", "language": "English", "quantity": 1, "title": "Gilded Pinions", "listingType": "ListingWithoutPhotos", "customListingId": "", "purchasePrice": 0.05, "shippingPrice": 0.0, "orderDate": "2023-02-14T23:59:03.98+00:00"}, {"condition": "Near Mint", "variant": "Normal", "language": "English", "quantity": 1, "title": "Gilded Pinions", "listingType": "ListingWithoutPhotos", "customListingId": "", "purchasePrice": 0.16, "shippingPrice": 0.0, "orderDate": "2023-02-13T22:43:50.83+00:00"}, {"condition": "Near Mint", "variant": "Normal", "language": "English", "quantity": 1, "title": "Gilded Pinions", "listingType": "ListingWithoutPhotos", "customListingId": "", "purchasePrice": 0.05, "shippingPrice": 0.0, "orderDate": "2023-02-13T04:02:02.97+00:00"}, {"condition": "Near Mint", "variant": "Normal", "language": "English", "quantity": 1, "title": "Gilded Pinions", "listingType": "ListingWithoutPhotos", "customListingId": "", "purchasePrice": 0.01, "shippingPrice": 0.99, "orderDate": "2023-02-13T00:28:51.516+00:00"}, {"condition": "Near Mint", "variant": "Normal", "language": "English", "quantity": 1, "title": "Gilded Pinions", "listingType": "ListingWithoutPhotos", "customListingId": "", "purchasePrice": 0.05, "shippingPrice": 0.0, "orderDate": "2023-02-12T23:02:41.56+00:00"}, {"condition": "Near Mint", "variant": "Foil", "language": "English", "quantity": 1, "title": "Gilded Pinions", "listingType": "ListingWithoutPhotos", "customListingId": "", "purchasePrice": 0.1, "shippingPrice": 0.0, "orderDate": "2023-02-12T21:06:09.25+00:00"}, {"condition": "Lightly Played", "variant": "Normal", "language": "English", "quantity": 1, "title": "Gilded Pinions", "listingType": "ListingWithoutPhotos", "customListingId": "", "purchasePrice": 0.05, "shippingPrice": 0.0, "orderDate": "2023-02-10T16:00:09.723+00:00"}, {"condition": "Near Mint", "variant": "Normal", "language": "English", "quantity": 1, "title": "Gilded Pinions", "listingType": "ListingWithoutPhotos", "customListingId": "", "purchasePrice": 0.07, "shippingPrice": 3.99, "orderDate": "2023-02-10T03:33:33.403+00:00"}, {"condition": "Near Mint", "variant": "Foil", "language": "English", "quantity": 1, "title": "Gilded Pinions", "listingType": "ListingWithoutPhotos", "customListingId": "", "purchasePrice": 0.1, "shippingPrice": 0.0, "orderDate": "2023-02-09T07:27:47.976+00:00"}, {"condition": "Near Mint", "variant": "Normal", "language": "English", "quantity": 4, "title": "Gilded Pinions", "listingType": "ListingWithoutPhotos", "customListingId": "", "purchasePrice": 0.05, "shippingPrice": 0.0, "orderDate": "2023-02-09T06:43:00.153+00:00"}, {"condition": "Near Mint", "variant": "Normal", "language": "English", "quantity": 1, "title": "Gilded Pinions", "listingType": "ListingWithoutPhotos", "customListingId": "", "purchasePrice": 0.05, "shippingPrice": 0.0, "orderDate": "2023-02-09T02:50:35.85+00:00"}, {"condition": "Near Mint", "variant": "Normal", "language": "English", "quantity": 1, "title": "Gilded Pinions", "listingType": "ListingWithoutPhotos", "customListingId": "", "purchasePrice": 0.05, "shippingPrice": 0.0, "orderDate": "2023-02-08T21:51:47.973+00:00"}, {"condition": "Lightly Played", "variant": "Normal", "language": "English", "quantity": 1, "title": "Gilded Pinions", "listingType": "ListingWithoutPhotos", "customListingId": "", "purchasePrice": 0.06, "shippingPrice": 4.99, "orderDate": "2023-02-08T12:44:56.003+00:00"}, {"condition": "Near Mint", "variant": "Normal", "language": "English", "quantity": 1, "title": "Gilded Pinions", "listingType": "ListingWithoutPhotos", "customListingId": "", "purchasePrice": 0.05, "shippingPrice": 0.0, "orderDate": "2023-02-08T04:30:04.983+00:00"}, {"condition": "Lightly Played", "variant": "Normal", "language": "English", "quantity": 1, "title": "Gilded Pinions", "listingType": "ListingWithoutPhotos", "customListingId": "", "purchasePrice": 0.05, "shippingPrice": 0.0, "orderDate": "2023-02-08T02:45:09.533+00:00"}, {"condition": "Near Mint", "variant": "Normal", "language": "English", "quantity": 1, "title": "Gilded Pinions", "listingType": "ListingWithoutPhotos", "customListingId": "", "purchasePrice": 0.05, "shippingPrice": 0.0, "orderDate": "2023-02-08T01:39:52.153+00:00"}, {"condition": "Near Mint", "variant": "Normal", "language": "English", "quantity": 1, "title": "Gilded Pinions", "listingType": "ListingWithoutPhotos", "customListingId": "", "purchasePrice": 0.04, "shippingPrice": 0.0, "orderDate": "2023-02-07T18:50:23.12+00:00"}, {"condition": "Near Mint", "variant": "Normal", "language": "English", "quantity": 1, "title": "Gilded Pinions", "listingType": "ListingWithoutPhotos", "customListingId": "", "purchasePrice": 0.04, "shippingPrice": 0.0, "orderDate": "2023-02-07T11:22:18.9+00:00"}, {"condition": "Near Mint", "variant": "Normal", "language": "English", "quantity": 1, "title": "Gilded Pinions", "listingType": "ListingWithoutPhotos", "customListingId": "", "purchasePrice": 0.04, "shippingPrice": 0.0, "orderDate": "2023-02-07T07:07:35.986+00:00"}, {"condition": "Near Mint", "variant": "Normal", "language": "English", "quantity": 1, "title": "Gilded Pinions", "listingType": "ListingWithoutPhotos", "customListingId": "", "purchasePrice": 0.04, "shippingPrice": 0.0, "orderDate": "2023-02-07T05:42:50.973+00:00"}, {"condition": "Near Mint", "variant": "Foil", "language": "English", "quantity": 1, "title": "Gilded Pinions", "listingType": "ListingWithoutPhotos", "customListingId": "", "purchasePrice": 0.12, "shippingPrice": 0.0, "orderDate": "2023-02-07T02:38:17.32+00:00"}, {"condition": "Lightly Played", "variant": "Normal", "language": "English", "quantity": 1, "title": "Gilded Pinions", "listingType": "ListingWithoutPhotos", "customListingId": "", "purchasePrice": 0.01, "shippingPrice": 0.0, "orderDate": "2023-02-06T16:32:28.293+00:00"}, {"condition": "Lightly Played", "variant": "Normal", "language": "English", "quantity": 1, "title": "Gilded Pinions", "listingType": "ListingWithoutPhotos", "customListingId": "", "purchasePrice": 0.01, "shippingPrice": 0.99, "orderDate": "2023-02-06T08:06:44.663+00:00"}, {"condition": "Near Mint", "variant": "Foil", "language": "English", "quantity": 1, "title": "Gilded Pinions", "listingType": "ListingWithoutPhotos", "customListingId": "", "purchasePrice": 0.39, "shippingPrice": 0.99, "orderDate": "2023-02-06T01:31:50.033+00:00"}, {"condition": "Near Mint", "variant": "Normal", "language": "English", "quantity": 1, "title": "Gilded Pinions", "listingType": "ListingWithoutPhotos", "customListingId": "", "purchasePrice": 0.01, "shippingPrice": 0.99, "orderDate": "2023-02-05T07:10:45.69+00:00"}, {"condition": "Near Mint", "variant": "Foil", "language": "English", "quantity": 1, "title": "Gilded Pinions", "listingType": "ListingWithoutPhotos", "customListingId": "", "purchasePrice": 0.1, "shippingPrice": 0.0, "orderDate": "2023-02-03T18:34:02.203+00:00"}, {"condition": "Near Mint", "variant": "Normal", "language": "English", "quantity": 2, "title": "Gilded Pinions", "listingType": "ListingWithoutPhotos", "customListingId": "", "purchasePrice": 0.52, "shippingPrice": 0.0, "orderDate": "2023-02-03T10:44:10.66+00:00"}, {"condition": "Near Mint", "variant": "Normal", "language": "English", "quantity": 1, "title": "Gilded Pinions", "listingType": "ListingWithoutPhotos", "customListingId": "", "purchasePrice": 0.04, "shippingPrice": 0.0, "orderDate": "2023-02-03T04:27:38.116+00:00"}, {"condition": "Near Mint", "variant": "Normal", "language": "English", "quantity": 1, "title": "Gilded Pinions", "listingType": "ListingWithoutPhotos", "customListingId": "", "purchasePrice": 0.01, "shippingPrice": 0.99, "orderDate": "2023-02-02T23:00:44.23+00:00"}, {"condition": "Near Mint", "variant": "Normal", "language": "English", "quantity": 1, "title": "Gilded Pinions", "listingType": "ListingWithoutPhotos", "customListingId": "", "purchasePrice": 0.04, "shippingPrice": 0.0, "orderDate": "2023-02-02T09:24:13.546+00:00"}, {"condition": "Near Mint", "variant": "Normal", "language": "English", "quantity": 1, "title": "Gilded Pinions", "listingType": "ListingWithoutPhotos", "customListingId": "", "purchasePrice": 0.04, "shippingPrice": 0.0, "orderDate": "2023-02-02T04:01:37.05+00:00"}, {"condition": "Near Mint", "variant": "Normal", "language": "English", "quantity": 1, "title": "Gilded Pinions", "listingType": "ListingWithoutPhotos", "customListingId": "", "purchasePrice": 0.04, "shippingPrice": 0.0, "orderDate": "2023-02-02T02:35:50.02+00:00"}, {"condition": "Near Mint", "variant": "Normal", "language": "English", "quantity": 1, "title": "Gilded Pinions", "listingType": "ListingWithoutPhotos", "customListingId": "", "purchasePrice": 0.04, "shippingPrice": 0.0, "orderDate": "2023-02-01T23:46:40.216+00:00"}, {"condition": "Near Mint", "variant": "Normal", "language": "English", "quantity": 1, "title": "Gilded Pinions", "listingType": "ListingWithoutPhotos", "customListingId": "", "purchasePrice": 0.05, "shippingPrice": 0.0, "orderDate": "2023-02-01T19:23:20.463+00:00"}, {"condition": "Near Mint", "variant": "Normal", "language": "English", "quantity": 1, "title": "Gilded Pinions", "listingType": "ListingWithoutPhotos", "customListingId": "", "purchasePrice": 0.04, "shippingPrice": 0.0, "orderDate": "2023-02-01T02:28:11.39+00:00"}, {"condition": "Near Mint", "variant": "Normal", "language": "English", "quantity": 1, "title": "Gilded Pinions", "listingType": "ListingWithoutPhotos", "customListingId": "", "purchasePrice": 0.04, "shippingPrice": 0.0, "orderDate": "2023-01-31T23:45:36.37+00:00"}, {"condition": "Lightly Played", "variant": "Foil", "language": "English", "quantity": 1, "title": "Gilded Pinions", "listingType": "ListingWithoutPhotos", "customListingId": "", "purchasePrice": 0.12, "shippingPrice": 4.99, "orderDate": "2023-01-31T10:39:05.363+00:00"}, {"condition": "Near Mint", "variant": "Normal", "language": "English", "quantity": 1, "title": "Gilded Pinions", "listingType": "ListingWithoutPhotos", "customListingId": "", "purchasePrice": 0.04, "shippingPrice": 0.0, "orderDate": "2023-01-31T07:40:19.183+00:00"}, {"condition": "Near Mint", "variant": "Normal", "language": "English", "quantity": 1, "title": "Gilded Pinions", "listingType": "ListingWithoutPhotos", "customListingId": "", "purchasePrice": 0.04, "shippingPrice": 0.0, "orderDate": "2023-01-30T18:31:51.483+00:00"}, {"condition": "Near Mint", "variant": "Normal", "language": "English", "quantity": 1, "title": "Gilded Pinions", "listingType": "ListingWithoutPhotos", "customListingId": "", "purchasePrice": 0.01, "shippingPrice": 0.99, "orderDate": "2023-01-30T18:31:48.056+00:00"}, {"condition": "Lightly Played", "variant": "Normal", "language": "English", "quantity": 1, "title": "Gilded Pinions", "listingType": "ListingWithoutPhotos", "customListingId": "", "purchasePrice": 0.05, "shippingPrice": 3.0, "orderDate": "2023-01-30T05:42:05.346+00:00"}, {"condition": "Near Mint", "variant": "Normal", "language": "English", "quantity": 1, "title": "Gilded Pinions", "listingType": "ListingWithoutPhotos", "customListingId": "", "purchasePrice": 0.01, "shippingPrice": 0.99, "orderDate": "2023-01-29T02:06:39.07+00:00"}, {"condition": "Near Mint", "variant": "Normal", "language": "English", "quantity": 1, "title": "Gilded Pinions", "listingType": "ListingWithoutPhotos", "customListingId": "", "purchasePrice": 0.03, "shippingPrice": 1.39, "orderDate": "2023-01-28T17:21:43.376+00:00"}, {"condition": "Near Mint", "variant": "Normal", "language": "English", "quantity": 1, "title": "Gilded Pinions", "listingType": "ListingWithoutPhotos", "customListingId": "", "purchasePrice": 0.05, "shippingPrice": 0.0, "orderDate": "2023-01-27T20:47:37.726+00:00"}, {"condition": "Near Mint", "variant": "Normal", "language": "English", "quantity": 1, "title": "Gilded Pinions", "listingType": "ListingWithoutPhotos", "customListingId": "", "purchasePrice": 0.06, "shippingPrice": 0.0, "orderDate": "2023-01-27T02:14:20.693+00:00"}, {"condition": "Near Mint", "variant": "Normal", "language": "English", "quantity": 1, "title": "Gilded Pinions", "listingType": "ListingWithoutPhotos", "customListingId": "", "purchasePrice": 0.03, "shippingPrice": 0.0, "orderDate": "2023-01-27T00:30:56.403+00:00"}, {"condition": "Near Mint", "variant": "Normal", "language": "English", "quantity": 1, "title": "Gilded Pinions", "listingType": "ListingWithoutPhotos", "customListingId": "", "purchasePrice": 0.06, "shippingPrice": 0.0, "orderDate": "2023-01-27T00:30:56.403+00:00"}, {"condition": "Near Mint", "variant": "Normal", "language": "English", "quantity": 2, "title": "Gilded Pinions", "listingType": "ListingWithoutPhotos", "customListingId": "", "purchasePrice": 0.02, "shippingPrice": 0.0, "orderDate": "2023-01-27T00:30:56.383+00:00"}, {"condition": "Near Mint", "variant": "Normal", "language": "English", "quantity": 1, "title": "Gilded Pinions", "listingType": "ListingWithoutPhotos", "customListingId": "", "purchasePrice": 0.02, "shippingPrice": 0.0, "orderDate": "2023-01-27T00:12:05.9+00:00"}, {"condition": "Near Mint", "variant": "Normal", "language": "English", "quantity": 1, "title": "Gilded Pinions", "listingType": "ListingWithoutPhotos", "customListingId": "", "purchasePrice": 0.02, "shippingPrice": 0.0, "orderDate": "2023-01-26T05:24:16.056+00:00"}, {"condition": "Near Mint", "variant": "Normal", "language": "English", "quantity": 1, "title": "Gilded Pinions", "listingType": "ListingWithoutPhotos", "customListingId": "", "purchasePrice": 0.02, "shippingPrice": 0.0, "orderDate": "2023-01-26T04:36:28.996+00:00"}, {"condition": "Near Mint", "variant": "Normal", "language": "English", "quantity": 1, "title": "Gilded Pinions", "listingType": "ListingWithoutPhotos", "customListingId": "", "purchasePrice": 0.25, "shippingPrice": 1.25, "orderDate": "2023-01-25T18:19:55.423+00:00"}, {"condition": "Lightly Played", "variant": "Normal", "language": "English", "quantity": 4, "title": "Gilded Pinions", "listingType": "ListingWithoutPhotos", "customListingId": "", "purchasePrice": 0.04, "shippingPrice": 0.99, "orderDate": "2023-01-24T13:11:42.686+00:00"}, {"condition": "Near Mint", "variant": "Foil", "language": "English", "quantity": 1, "title": "Gilded Pinions", "listingType": "ListingWithoutPhotos", "customListingId": "", "purchasePrice": 0.11, "shippingPrice": 0.0, "orderDate": "2023-01-23T20:43:09.876+00:00"}, {"condition": "Near Mint", "variant": "Normal", "language": "English", "quantity": 1, "title": "Gilded Pinions", "listingType": "ListingWithoutPhotos", "customListingId": "", "purchasePrice": 0.06, "shippingPrice": 0.0, "orderDate": "2023-01-23T14:22:21.05+00:00"}, {"condition": "Near Mint", "variant": "Normal", "language": "English", "quantity": 1, "title": "Gilded Pinions", "listingType": "ListingWithoutPhotos", "customListingId": "", "purchasePrice": 0.08, "shippingPrice": 0.0, "orderDate": "2023-01-23T02:08:12.683+00:00"}, {"condition": "Near Mint", "variant": "Normal", "language": "English", "quantity": 1, "title": "Gilded Pinions", "listingType": "ListingWithoutPhotos", "customListingId": "", "purchasePrice": 0.1, "shippingPrice": 0.0, "orderDate": "2023-01-22T16:37:30.276+00:00"}, {"condition": "Near Mint", "variant": "Normal", "language": "English", "quantity": 1, "title": "Gilded Pinions", "listingType": "ListingWithoutPhotos", "customListingId": "", "purchasePrice": 0.06, "shippingPrice": 0.0, "orderDate": "2023-01-22T13:54:44.326+00:00"}, {"condition": "Near Mint", "variant": "Normal", "language": "English", "quantity": 1, "title": "Gilded Pinions", "listingType": "ListingWithoutPhotos", "customListingId": "", "purchasePrice": 0.06, "shippingPrice": 0.0, "orderDate": "2023-01-22T02:12:38.553+00:00"}, {"condition": "Near Mint", "variant": "Normal", "language": "English", "quantity": 1, "title": "Gilded Pinions", "listingType": "ListingWithoutPhotos", "customListingId": "", "purchasePrice": 0.08, "shippingPrice": 19.99, "orderDate": "2023-01-21T19:22:43.24+00:00"}, {"condition": "Near Mint", "variant": "Normal", "language": "English", "quantity": 1, "title": "Gilded Pinions", "listingType": "ListingWithoutPhotos", "customListingId": "", "purchasePrice": 0.06, "shippingPrice": 0.0, "orderDate": "2023-01-21T06:38:12.37+00:00"}, {"condition": "Near Mint", "variant": "Foil", "language": "English", "quantity": 3, "title": "Gilded Pinions", "listingType": "ListingWithoutPhotos", "customListingId": "", "purchasePrice": 0.1, "shippingPrice": 0.0, "orderDate": "2023-01-20T04:39:50.583+00:00"}, {"condition": "Near Mint", "variant": "Foil", "language": "English", "quantity": 1, "title": "Gilded Pinions", "listingType": "ListingWithoutPhotos", "customListingId": "", "purchasePrice": 0.25, "shippingPrice": 0.0, "orderDate": "2023-01-20T04:39:50.49+00:00"}, {"condition": "Near Mint", "variant": "Normal", "language": "English", "quantity": 1, "title": "Gilded Pinions", "listingType": "ListingWithoutPhotos", "customListingId": "", "purchasePrice": 0.06, "shippingPrice": 0.0, "orderDate": "2023-01-20T03:53:11.16+00:00"}, {"condition": "Lightly Played", "variant": "Normal", "language": "English", "quantity": 1, "title": "Gilded Pinions", "listingType": "ListingWithoutPhotos", "customListingId": "", "purchasePrice": 0.05, "shippingPrice": 0.0, "orderDate": "2023-01-19T00:56:46.773+00:00"}, {"condition": "Near Mint", "variant": "Foil", "language": "English", "quantity": 1, "title": "Gilded Pinions", "listingType": "ListingWithoutPhotos", "customListingId": "", "purchasePrice": 0.1, "shippingPrice": 0.0, "orderDate": "2023-01-18T21:14:00.303+00:00"}, {"condition": "Near Mint", "variant": "Normal", "language": "English", "quantity": 1, "title": "Gilded Pinions", "listingType": "ListingWithoutPhotos", "customListingId": "", "purchasePrice": 0.06, "shippingPrice": 0.0, "orderDate": "2023-01-18T16:58:38.136+00:00"}, {"condition": "Lightly Played", "variant": "Normal", "language": "English", "quantity": 1, "title": "Gilded Pinions", "listingType": "ListingWithoutPhotos", "customListingId": "", "purchasePrice": 0.05, "shippingPrice": 0.0, "orderDate": "2023-01-18T04:19:33.42+00:00"}, {"condition": "Near Mint", "variant": "Normal", "language": "English", "quantity": 1, "title": "Gilded Pinions", "listingType": "ListingWithoutPhotos", "customListingId": "", "purchasePrice": 0.02, "shippingPrice": 1.0, "orderDate": "2023-01-17T18:25:04.776+00:00"}, {"condition": "Near Mint", "variant": "Normal", "language": "English", "quantity": 1, "title": "Gilded Pinions", "listingType": "ListingWithoutPhotos", "customListingId": "", "purchasePrice": 0.01, "shippingPrice": 0.99, "orderDate": "2023-01-17T04:49:01.583+00:00"}, {"condition": "Near Mint", "variant": "Foil", "language": "English", "quantity": 1, "title": "Gilded Pinions", "listingType": "ListingWithoutPhotos", "customListingId": "", "purchasePrice": 0.1, "shippingPrice": 0.0, "orderDate": "2023-01-16T23:17:01.693+00:00"}, {"condition": "Near Mint", "variant": "Normal", "language": "English", "quantity": 1, "title": "Gilded Pinions", "listingType": "ListingWithoutPhotos", "customListingId": "", "purchasePrice": 0.06, "shippingPrice": 0.0, "orderDate": "2023-01-16T22:10:27.836+00:00"}, {"condition": "Near Mint", "variant": "Normal", "language": "English", "quantity": 1, "title": "Gilded Pinions", "listingType": "ListingWithoutPhotos", "customListingId": "", "purchasePrice": 0.06, "shippingPrice": 0.0, "orderDate": "2023-01-16T21:08:25.79+00:00"}, {"condition": "Lightly Played", "variant": "Normal", "language": "English", "quantity": 2, "title": "Gilded Pinions", "listingType": "ListingWithoutPhotos", "customListingId": "", "purchasePrice": 0.04, "shippingPrice": 0.0, "orderDate": "2023-01-16T07:50:57.436+00:00"}, {"condition": "Near Mint", "variant": "Normal", "language": "English", "quantity": 4, "title": "Gilded Pinions", "listingType": "ListingWithoutPhotos", "customListingId": "", "purchasePrice": 0.1, "shippingPrice": 0.0, "orderDate": "2023-01-16T03:42:27.083+00:00"}, {"condition": "Near Mint", "variant": "Normal", "language": "English", "quantity": 3, "title": "Gilded Pinions", "listingType": "ListingWithoutPhotos", "customListingId": "", "purchasePrice": 0.08, "shippingPrice": 0.99, "orderDate": "2023-01-15T07:12:54.18+00:00"}, {"condition": "Near Mint", "variant": "Normal", "language": "English", "quantity": 1, "title": "Gilded Pinions", "listingType": "ListingWithoutPhotos", "customListingId": "", "purchasePrice": 0.01, "shippingPrice": 0.99, "orderDate": "2023-01-14T17:26:20.633+00:00"}, {"condition": "Near Mint", "variant": "Normal", "language": "English", "quantity": 3, "title": "Gilded Pinions", "listingType": "ListingWithoutPhotos", "customListingId": "", "purchasePrice": 0.05, "shippingPrice": 0.99, "orderDate": "2023-01-13T06:44:53.123+00:00"}, {"condition": "Near Mint", "variant": "Normal", "language": "English", "quantity": 1, "title": "Gilded Pinions", "listingType": "ListingWithoutPhotos", "customListingId": "", "purchasePrice": 0.06, "shippingPrice": 0.0, "orderDate": "2023-01-12T21:01:10.97+00:00"}, {"condition": "Near Mint", "variant": "Normal", "language": "English", "quantity": 1, "title": "Gilded Pinions", "listingType": "ListingWithoutPhotos", "customListingId": "", "purchasePrice": 0.06, "shippingPrice": 0.0, "orderDate": "2023-01-12T20:10:49.066+00:00"}, {"condition": "Lightly Played", "variant": "Normal", "language": "English", "quantity": 1, "title": "Gilded Pinions", "listingType": "ListingWithoutPhotos", "customListingId": "", "purchasePrice": 0.05, "shippingPrice": 0.99, "orderDate": "2023-01-12T17:58:55.13+00:00"}, {"condition": "Lightly Played", "variant": "Normal", "language": "English", "quantity": 4, "title": "Gilded Pinions", "listingType": "ListingWithoutPhotos", "customListingId": "", "purchasePrice": 0.05, "shippingPrice": 2.99, "orderDate": "2023-01-12T08:51:58.96+00:00"}, {"condition": "Near Mint", "variant": "Normal", "language": "English", "quantity": 1, "title": "Gilded Pinions", "listingType": "ListingWithoutPhotos", "customListingId": "", "purchasePrice": 0.05, "shippingPrice": 0.99, "orderDate": "2023-01-12T05:16:40.363+00:00"}, {"condition": "Near Mint", "variant": "Normal", "language": "English", "quantity": 1, "title": "Gilded Pinions", "listingType": "ListingWithoutPhotos", "customListingId": "", "purchasePrice": 0.06, "shippingPrice": 0.0, "orderDate": "2023-01-12T01:20:18.706+00:00"}, {"condition": "Near Mint", "variant": "Normal", "language": "English", "quantity": 1, "title": "Gilded Pinions", "listingType": "ListingWithoutPhotos", "customListingId": "", "purchasePrice": 0.08, "shippingPrice": 0.99, "orderDate": "2023-01-11T07:06:23.12+00:00"}, {"condition": "Near Mint", "variant": "Normal", "language": "English", "quantity": 4, "title": "Gilded Pinions", "listingType": "ListingWithoutPhotos", "customListingId": "", "purchasePrice": 0.06, "shippingPrice": 0.99, "orderDate": "2023-01-10T21:28:49.53+00:00"}, {"condition": "Near Mint", "variant": "Normal", "language": "English", "quantity": 1, "title": "Gilded Pinions", "listingType": "ListingWithoutPhotos", "customListingId": "", "purchasePrice": 0.08, "shippingPrice": 0.0, "orderDate": "2023-01-10T20:34:52.723+00:00"}, {"condition": "Lightly Played", "variant": "Normal", "language": "English", "quantity": 1, "title": "Gilded Pinions", "listingType": "ListingWithoutPhotos", "customListingId": "", "purchasePrice": 0.15, "shippingPrice": 0.99, "orderDate": "2023-01-10T03:02:01.11+00:00"}, {"condition": "Near Mint", "variant": "Normal", "language": "English", "quantity": 1, "title": "Gilded Pinions", "listingType": "ListingWithoutPhotos", "customListingId": "", "purchasePrice": 0.06, "shippingPrice": 0.0, "orderDate": "2023-01-09T20:58:22.37+00:00"}, {"condition": "Near Mint", "variant": "Normal", "language": "English", "quantity": 1, "title": "Gilded Pinions", "listingType": "ListingWithoutPhotos", "customListingId": "", "purchasePrice": 0.06, "shippingPrice": 0.0, "orderDate": "2023-01-09T20:31:28.18+00:00"}, {"condition": "Lightly Played", "variant": "Normal", "language": "English", "quantity": 1, "title": "Gilded Pinions", "listingType": "ListingWithoutPhotos", "customListingId": "", "purchasePrice": 0.05, "shippingPrice": 3.99, "orderDate": "2023-01-09T19:27:25.61+00:00"}, {"condition": "Near Mint", "variant": "Normal", "language": "English", "quantity": 3, "title": "Gilded Pinions", "listingType": "ListingWithoutPhotos", "customListingId": "", "purchasePrice": 0.05, "shippingPrice": 0.0, "orderDate": "2023-01-09T19:15:28.303+00:00"}, {"condition": "Near Mint", "variant": "Normal", "language": "English", "quantity": 4, "title": "Gilded Pinions", "listingType": "ListingWithoutPhotos", "customListingId": "", "purchasePrice": 0.1, "shippingPrice": 0.0, "orderDate": "2023-01-09T16:50:20.976+00:00"}, {"condition": "Near Mint", "variant": "Normal", "language": "English", "quantity": 1, "title": "Gilded Pinions", "listingType": "ListingWithoutPhotos", "customListingId": "", "purchasePrice": 0.05, "shippingPrice": 0.0, "orderDate": "2023-01-09T16:11:48.613+00:00"}, {"condition": "Near Mint", "variant": "Normal", "language": "English", "quantity": 1, "title": "Gilded Pinions", "listingType": "ListingWithoutPhotos", "customListingId": "", "purchasePrice": 0.06, "shippingPrice": 0.0, "orderDate": "2023-01-09T10:46:40.403+00:00"}, {"condition": "Near Mint", "variant": "Normal", "language": "English", "quantity": 1, "title": "Gilded Pinions", "listingType": "ListingWithoutPhotos", "customListingId": "", "purchasePrice": 0.04, "shippingPrice": 0.99, "orderDate": "2023-01-08T19:28:14.29+00:00"}, {"condition": "Near Mint", "variant": "Normal", "language": "English", "quantity": 1, "title": "Gilded Pinions", "listingType": "ListingWithoutPhotos", "customListingId": "", "purchasePrice": 0.05, "shippingPrice": 0.99, "orderDate": "2023-01-08T07:58:37.016+00:00"}, {"condition": "Near Mint", "variant": "Foil", "language": "English", "quantity": 1, "title": "Gilded Pinions", "listingType": "ListingWithoutPhotos", "customListingId": "", "purchasePrice": 0.05, "shippingPrice": 0.99, "orderDate": "2023-01-08T07:10:51.053+00:00"}, {"condition": "Lightly Played", "variant": "Normal", "language": "English", "quantity": 1, "title": "Gilded Pinions", "listingType": "ListingWithoutPhotos", "customListingId": "", "purchasePrice": 0.05, "shippingPrice": 4.2, "orderDate": "2023-01-07T23:57:06.65+00:00"}, {"condition": "Near Mint", "variant": "Normal", "language": "English", "quantity": 1, "title": "Gilded Pinions", "listingType": "ListingWithoutPhotos", "customListingId": "", "purchasePrice": 0.05, "shippingPrice": 0.0, "orderDate": "2023-01-07T23:39:05.486+00:00"}, {"condition": "Near Mint", "variant": "Normal", "language": "English", "quantity": 2, "title": "Gilded Pinions", "listingType": "ListingWithoutPhotos", "customListingId": "", "purchasePrice": 0.05, "shippingPrice": 0.0, "orderDate": "2023-01-07T22:02:51.426+00:00"}, {"condition": "Near Mint", "variant": "Normal", "language": "English", "quantity": 1, "title": "Gilded Pinions", "listingType": "ListingWithoutPhotos", "customListingId": "", "purchasePrice": 0.02, "shippingPrice": 0.99, "orderDate": "2023-01-07T17:49:04.916+00:00"}, {"condition": "Lightly Played", "variant": "Normal", "language": "English", "quantity": 1, "title": "Gilded Pinions", "listingType": "ListingWithoutPhotos", "customListingId": "", "purchasePrice": 0.05, "shippingPrice": 0.99, "orderDate": "2023-01-07T17:12:35.14+00:00"}, {"condition": "Near Mint", "variant": "Normal", "language": "English", "quantity": 1, "title": "Gilded Pinions", "listingType": "ListingWithoutPhotos", "customListingId": "", "purchasePrice": 0.05, "shippingPrice": 0.0, "orderDate": "2023-01-07T05:36:31.223+00:00"}, {"condition": "Near Mint", "variant": "Normal", "language": "English", "quantity": 4, "title": "Gilded Pinions", "listingType": "ListingWithoutPhotos", "customListingId": "", "purchasePrice": 0.05, "shippingPrice": 0.0, "orderDate": "2023-01-07T04:14:23.723+00:00"}, {"condition": "Near Mint", "variant": "Normal", "language": "English", "quantity": 4, "title": "Gilded Pinions", "listingType": "ListingWithoutPhotos", "customListingId": "", "purchasePrice": 0.1, "shippingPrice": 0.0, "orderDate": "2023-01-06T23:41:14.3+00:00"}, {"condition": "Near Mint", "variant": "Foil", "language": "English", "quantity": 1, "title": "Gilded Pinions", "listingType": "ListingWithoutPhotos", "customListingId": "", "purchasePrice": 0.1, "shippingPrice": 0.0, "orderDate": "2023-01-06T11:14:21.413+00:00"}, {"condition": "Near Mint", "variant": "Normal", "language": "English", "quantity": 1, "title": "Gilded Pinions", "listingType": "ListingWithoutPhotos", "customListingId": "", "purchasePrice": 0.05, "shippingPrice": 0.99, "orderDate": "2023-01-06T06:26:01.656+00:00"}, {"condition": "Near Mint", "variant": "Normal", "language": "English", "quantity": 1, "title": "Gilded Pinions", "listingType": "ListingWithoutPhotos", "customListingId": "", "purchasePrice": 0.05, "shippingPrice": 0.0, "orderDate": "2023-01-06T04:32:36.836+00:00"}, {"condition": "Near Mint", "variant": "Normal", "language": "English", "quantity": 1, "title": "Gilded Pinions", "listingType": "ListingWithoutPhotos", "customListingId": "", "purchasePrice": 0.05, "shippingPrice": 0.0, "orderDate": "2023-01-06T01:16:18.596+00:00"}, {"condition": "Near Mint", "variant": "Foil", "language": "English", "quantity": 1, "title": "Gilded Pinions", "listingType": "ListingWithoutPhotos", "customListingId": "", "purchasePrice": 0.1, "shippingPrice": 0.0, "orderDate": "2023-01-05T08:48:05.72+00:00"}, {"condition": "Near Mint", "variant": "Normal", "language": "English", "quantity": 3, "title": "Gilded Pinions", "listingType": "ListingWithoutPhotos", "customListingId": "", "purchasePrice": 0.05, "shippingPrice": 0.99, "orderDate": "2023-01-04T23:22:46.673+00:00"}, {"condition": "Lightly Played", "variant": "Normal", "language": "English", "quantity": 1, "title": "Gilded Pinions", "listingType": "ListingWithoutPhotos", "customListingId": "", "purchasePrice": 0.04, "shippingPrice": 0.0, "orderDate": "2023-01-04T06:13:09.9+00:00"}, {"condition": "Lightly Played", "variant": "Normal", "language": "English", "quantity": 1, "title": "Gilded Pinions", "listingType": "ListingWithoutPhotos", "customListingId": "", "purchasePrice": 0.04, "shippingPrice": 0.0, "orderDate": "2023-01-04T03:47:45.406+00:00"}, {"condition": "Lightly Played", "variant": "Normal", "language": "English", "quantity": 1, "title": "Gilded Pinions", "listingType": "ListingWithoutPhotos", "customListingId": "", "purchasePrice": 0.04, "shippingPrice": 0.0, "orderDate": "2023-01-04T00:55:37.413+00:00"}, {"condition": "Near Mint", "variant": "Normal", "language": "English", "quantity": 1, "title": "Gilded Pinions", "listingType": "ListingWithoutPhotos", "customListingId": "", "purchasePrice": 0.2, "shippingPrice": 0.99, "orderDate": "2023-01-04T00:35:58.54+00:00"}, {"condition": "Near Mint", "variant": "Normal", "language": "English", "quantity": 4, "title": "Gilded Pinions", "listingType": "ListingWithoutPhotos", "customListingId": "", "purchasePrice": 0.05, "shippingPrice": 0.0, "orderDate": "2023-01-03T15:58:35.753+00:00"}, {"condition": "Near Mint", "variant": "Normal", "language": "English", "quantity": 4, "title": "Gilded Pinions", "listingType": "ListingWithoutPhotos", "customListingId": "", "purchasePrice": 0.02, "shippingPrice": 0.99, "orderDate": "2023-01-03T08:15:20.683+00:00"}, {"condition": "Near Mint", "variant": "Normal", "language": "English", "quantity": 1, "title": "Gilded Pinions", "listingType": "ListingWithoutPhotos", "customListingId": "", "purchasePrice": 0.01, "shippingPrice": 0.99, "orderDate": "2023-01-02T23:47:05.49+00:00"}, {"condition": "Near Mint", "variant": "Normal", "language": "English", "quantity": 1, "title": "Gilded Pinions", "listingType": "ListingWithoutPhotos", "customListingId": "", "purchasePrice": 0.06, "shippingPrice": 0.0, "orderDate": "2023-01-02T21:45:20.706+00:00"}, {"condition": "Near Mint", "variant": "Normal", "language": "English", "quantity": 1, "title": "Gilded Pinions", "listingType": "ListingWithoutPhotos", "customListingId": "", "purchasePrice": 0.06, "shippingPrice": 0.0, "orderDate": "2023-01-02T21:08:28.526+00:00"}, {"condition": "Near Mint", "variant": "Normal", "language": "English", "quantity": 2, "title": "Gilded Pinions", "listingType": "ListingWithoutPhotos", "customListingId": "", "purchasePrice": 0.06, "shippingPrice": 0.0, "orderDate": "2023-01-02T20:23:38.443+00:00"}, {"condition": "Lightly Played", "variant": "Normal", "language": "English", "quantity": 1, "title": "Gilded Pinions", "listingType": "ListingWithoutPhotos", "customListingId": "", "purchasePrice": 0.04, "shippingPrice": 0.0, "orderDate": "2023-01-02T04:35:12.59+00:00"}, {"condition": "Near Mint", "variant": "Normal", "language": "English", "quantity": 1, "title": "Gilded Pinions", "listingType": "ListingWithoutPhotos", "customListingId": "", "purchasePrice": 0.01, "shippingPrice": 0.0, "orderDate": "2023-01-01T21:27:24.31+00:00"}, {"condition": "Near Mint", "variant": "Normal", "language": "English", "quantity": 1, "title": "Gilded Pinions", "listingType": "ListingWithoutPhotos", "customListingId": "", "purchasePrice": 0.01, "shippingPrice": 0.0, "orderDate": "2023-01-01T19:53:01.49+00:00"}, {"condition": "Near Mint", "variant": "Normal", "language": "English", "quantity": 1, "title": "Gilded Pinions", "listingType": "ListingWithoutPhotos", "customListingId": "", "purchasePrice": 0.01, "shippingPrice": 2.99, "orderDate": "2023-01-01T02:45:24.28+00:00"}, {"condition": "Near Mint", "variant": "Normal", "language": "English", "quantity": 1, "title": "Gilded Pinions", "listingType": "ListingWithoutPhotos", "customListingId": "", "purchasePrice": 0.01, "shippingPrice": 0.99, "orderDate": "2022-12-31T14:58:27.09+00:00"}, {"condition": "Near Mint", "variant": "Normal", "language": "English", "quantity": 1, "title": "Gilded Pinions", "listingType": "ListingWithoutPhotos", "customListingId": "", "purchasePrice": 0.06, "shippingPrice": 0.0, "orderDate": "2022-12-31T07:17:50.14+00:00"}, {"condition": "Near Mint", "variant": "Normal", "language": "English", "quantity": 1, "title": "Gilded Pinions", "listingType": "ListingWithoutPhotos", "customListingId": "", "purchasePrice": 0.1, "shippingPrice": 0.99, "orderDate": "2022-12-31T06:04:46.013+00:00"}, {"condition": "Near Mint", "variant": "Foil", "language": "English", "quantity": 1, "title": "Gilded Pinions", "listingType": "ListingWithoutPhotos", "customListingId": "", "purchasePrice": 0.1, "shippingPrice": 0.0, "orderDate": "2022-12-31T04:33:44.346+00:00"}, {"condition": "Near Mint", "variant": "Normal", "language": "English", "quantity": 1, "title": "Gilded Pinions", "listingType": "ListingWithoutPhotos", "customListingId": "", "purchasePrice": 0.06, "shippingPrice": 0.0, "orderDate": "2022-12-31T00:22:22.7+00:00"}, {"condition": "Near Mint", "variant": "Normal", "language": "English", "quantity": 1, "title": "Gilded Pinions", "listingType": "ListingWithoutPhotos", "customListingId": "", "purchasePrice": 0.02, "shippingPrice": 0.99, "orderDate": "2022-12-30T22:13:40.736+00:00"}, {"condition": "Near Mint", "variant": "Normal", "language": "English", "quantity": 1, "title": "Gilded Pinions", "listingType": "ListingWithoutPhotos", "customListingId": "", "purchasePrice": 0.06, "shippingPrice": 0.99, "orderDate": "2022-12-30T08:40:33.883+00:00"}, {"condition": "Near Mint", "variant": "Normal", "language": "English", "quantity": 1, "title": "Gilded Pinions", "listingType": "ListingWithoutPhotos", "customListingId": "", "purchasePrice": 0.06, "shippingPrice": 0.0, "orderDate": "2022-12-29T01:09:47.63+00:00"}, {"condition": "Near Mint", "variant": "Normal", "language": "English", "quantity": 2, "title": "Gilded Pinions", "listingType": "ListingWithoutPhotos", "customListingId": "", "purchasePrice": 0.06, "shippingPrice": 0.0, "orderDate": "2022-12-28T21:54:06.53+00:00"}, {"condition": "Near Mint", "variant": "Normal", "language": "English", "quantity": 2, "title": "Gilded Pinions", "listingType": "ListingWithoutPhotos", "customListingId": "", "purchasePrice": 0.05, "shippingPrice": 0.0, "orderDate": "2022-12-28T21:54:06.516+00:00"}, {"condition": "Near Mint", "variant": "Normal", "language": "English", "quantity": 1, "title": "Gilded Pinions", "listingType": "ListingWithoutPhotos", "customListingId": "", "purchasePrice": 0.05, "shippingPrice": 0.0, "orderDate": "2022-12-28T06:19:41.193+00:00"}, {"condition": "Near Mint", "variant": "Foil", "language": "English", "quantity": 3, "title": "Gilded Pinions", "listingType": "ListingWithoutPhotos", "customListingId": "", "purchasePrice": 0.1, "shippingPrice": 0.0, "orderDate": "2022-12-28T00:38:12.293+00:00"}]